Workbook

Sheet Старт
A1: Старт: что делать по шагам
A2: Идите сверху вниз. В таблице 13 карточек, но для первого показа нужны 9 (лист «К Reddit», колонка «В наборе»). Остальные 4 лежат в конце таблицы и ждут.
A4: Шаг | B4: Что сделать | C4: Где в таблице | D4: Кто | E4: Усилие | F4: Статус
A5: 1 | B5: Второй круг чтения: прочитать все 13 карточек по-русски (cards-ru.md): там теперь отмечено, что я исправил по вашим замечаниям. Новые правки пишите под «Мои правки». | C5: Файл cards-ru.md. Правки: лист «Тексты», колонка U. | D5: вы | E5: среднее | F5: сделано
A6: 2 | B6: Ответить на 10 вопросов-решений (ниже). Одним словом на каждый. | C6: Этот лист, ниже. | D6: вы | E6: малое | F6: сделано
A7: 3 | B7: Картинки. A) Запустить fetch_images.py: Кантино, носорог, землетрясение. B) Прислать мне файлы, я соберу превью. C) Для Casa da Neve, Torres Vedras и Douro решить: своё фото или шаблон. Tripeiros и апельсины готовы. | C7: Лист «Картинки», «К Reddit» (колонка «Картинка»). | D7: вы, затем я | E7: среднее | F7: 1. Ты не дал мне этот скрипт. 2. Не могу определиться концептуальнО, нужно ли использовать такие картинки или интереснее генерированные в стиле азулеже или моем? Исходя из кконцепции проекта - твои рекомендации
A8: 4 | B8: Мосты. Открыть в Google Maps 8 мест и скопировать адрес и координаты в лист «Места» (колонки K–P), в P поставить «да»: Museu de Marinha, Torre de Belém, памятник Tripeiros, Café Martinho da Arcada, 17•56 в Гае, памятник Албукерки в Белеме, форт São Vicente, CIBA. | C8: Лист «Места». K название, L адрес, M и N координаты, O сайт, P проверено. | D8: вы | E8: среднее | F8: 1. Сайт объекта давай не будем указывать. Сайты часто меняются, кто захочет - перейдет в гугл карты и найдет. Что думаешь? Или я не прав?
A9: 5 | B9: Проверить факты с пометкой ⚠ по очереди карточек. Источники смотреть по фильтру id. | C9: «К Reddit», колонка «Факты». Ссылки: лист «Источники». | D9: вы, я помогаю | E9: большое | F9: нет
A10: 6 | B10: Португальский. Отправить хуки и истории 3–5 носителям. Файл для отправки я подготовлю по запросу. | C10: Лист «Тексты», колонки D, H, L. | D10: вы | E10: малое | F10: Я не смогу это сделать. Будем обкаытвать уже в реале и надеяться, что ИИ адекватно переведет
A11: 7 | B11: Прочитать условия использования картинок Gemini и правила выбранного сабреддита. | C11: — | D11: вы | E11: малое | F11: сделано
A12: 8 | B12: Поручить мне черновик поста (название, текст, раскрытие про ИИ, вопрос аудитории) и страницу для показа. | C12: — | D12: я | E12: малое | F12: в работе
A14: Решения владельца
A15: № | B15: Вопрос | C15: Мой вариант по умолчанию | F15: Ваш ответ
A16: 1 | B16: Метка носорога: documented (бой описан как факт) или legend (как в вашем design)? | C16: documented | F16: Documented
A17: 2 | B17: Алжубарроту: новый хук «25-летний коннетабль ушёл с совета и сам выбрал поле боя». Подходит? | C17: подходит | F17: Я бы что-то с численным превосходством сделал, чтобы показать их крутыми
A18: 3 | B18: Алжубарроту: «тяжёлая тема» нет или да? (в тексте нет крови) | C18: нет | F18: Не тяжелая
A19: 4 | B19: Вторая нить «Люди как мы» у Алжубарроту и Tripeiros: оставить? | C19: оставить | F19: Да
A20: 5 | B20: Голос проекта в «Подробнее»: «мы не нашли» или нейтрально? | C20: нейтрально | F20: Оставляем мы
A21: 6 | B21: Апельсиновая война: выбрать мост (форт в Элваше) или оставить карточку без моста? | C21: без моста пока | F21: Если это как-то связано - можно указать, только добавить примечание к мосту как связано именно
A22: 7 | B22: Casa da Neve, Torres Vedras, Douro: своё фото или шаблон превью? | C22: шаблон превью | F22: Где посмотреть? Не увидел у тебя нигде
A23: 8 | B23: Подпись ИИ-иллюстраций: «Иллюстрация, созданная ИИ по преданию, не историческое изображение». Подходит? | C23: подходит | F23: А это нужно, как думаешь? Какие практики, исходя из целей и ЦА моего проекта? Нужно ли это к каждому изображению писать?
A24: 9 | B24: Новые лимиты: история 40–90 слов, «Подробнее» до 250 (было 70 и 150). Принять? Тогда поправлю spec §7 и Zod. | C24: принять | F24: Принять, гораздо лучше.
A25: 10 | B25: Motim разделён на две карточки: основание Дору (douro-1756) и бунт. Оставляем? | C25: оставить | F25: Да, сдоработками. В файле отзыв оставил

Sheet К Reddit
A1: К публикации на Reddit: что проверить и поправить
A2: Набор из 9 лёгких карточек. Тяжёлые темы и карточки без моста придержаны. Колонка «Статус»: пометьте, когда сделано.
A4: Карточка | B4: В наборе | C4: Картинка | D4: Мост | E4: Факты и источники | F4: Язык и тон | G4: Статус
A5: cantino-1502 | B5: да | C5: Скачать «Cantino planisphere (1502).jpg» (fetch_images.py), проверить кадр превью. PD (Commons). | D5: Museu de Marinha: адрес, координаты, выставлена ли копия, часы. | E5: Как карта попала к Кантино (подкуп, покупка?). Письма Кантино не читаны. Цепочка Caverio → Waldseemüller по McIntosh и BnF; «дала имя Америке» общеизвестный факт, в найденных источниках явно не прочитан. Год находки в лавке. | F5: Вычитать PT, EN, RU. «Génova» и «talho» проверить носителем. | G5: нет
A6: rinoceronte-1515 | B6: да | C6: Гравюра Дюрера: Cleveland Open Access или Commons (fetch_images.py). | D6: Torre de Belém: полный адрес, официальный сайт, координаты. | E6: Судьба тела: версии расходятся (чучело папе или шкура сначала в Лиссабон); следов чучела не нашли. Метка documented: решение. Слон Ханно, 1514. | F6: Вычитать PT. «Подробнее» теперь 4 абзаца. | G6: нет
A7: tripeiros-1415 | B7: да | C7: Есть картинка (ИИ, азулежу). Проверить фахверк (в Порту гранит и сланец). Подпись стоит. Условия Gemini прочитать. | D7: Памятник Лагоа Энрикеша (1960): название, адрес, координаты, официальная страница. | E7: У Зурары не найдено. Голос «мы» оставлен по решению владельца. | F7: Вычитать PT. | G7: нет
A8: guerra-laranjas-1801 | B8: да | C8: Есть картинка (ИИ). Крепость как замок, а не звёздчатый форт (в превью обрезана). Ноги лошади проверить. | D8: Мост не выбран (Forte de Santa Luzia в Элваше не проверен). | E8: Предание: ветка апельсинов или цветов (источники расходятся). 18 дней, Норонья держал Элваш, Оливенса, ратификация 1817. Спросить себя: теперь понятно, зачем ветка? | F8: Новый хук. Вычитать PT («conta a tradição»). | G8: нет
A9: casa-da-neve-1782 | B9: да | C9: Свободного файла нет. Снять самому или шаблон превью. | D9: Café Martinho da Arcada: Praça do Comércio 3. Часы расходятся. Координаты. Сайт martinhodaarcada.pt. | E9: Год открытия 1778 или 1782 (в тексте оба); имя 1829 или 1845. Монополия на лёд (DN, getlisbon). Путь снега Эштрела, Лозан, Монтежунту. Ссора с Marrare (RTP). | F9: Вычитать PT. «Neveiro» и «хранитель льда» согласовать. | G9: нет
A10: douro-1756 | B10: да | C10: Фото marco pombalino с Commons (не искал) или шаблон превью. | D10: 17•56 Museu & Enoteca (Gaia): координаты, часы, адрес. | E10: Новая карточка. «Первая в мире демаркированная» подано как «часто называют». 335 столбов (1758, 1761), около 100 стоят. Бузина вырывалась против подделок; про цвет не заявлено. «Монополия на торговлю с Англией и Бразилией» из Taylor's. | F10: Вычитать PT. Хук про бузину: цепляет ли? | G10: нет
A11: elefantes-malaca-1511 | B11: да | C11: Рисунок «Malaca» Гаспара Корреи (Torre do Tombo): найти файл на Commons, лицензию снимка. | D11: Памятник Албукерки в Белеме: координаты, официальная страница (в источниках только блог). Запасной: Casa dos Bicos. | E11: Цитата Пиреша: в нескольких энциклопедиях, не в Suma Oriental. Число слонов, силы Албукерки (1000–1200), дата падения не названа. Первоисточники не читаны. | F11: Новый хук и история. Вычитать PT. | G11: нет
A12: torres-vedras-1810 | B12: да | C12: Карта Clements Library (лицензия) или фото форта на Commons. Файл не выбран. | D12: Центр интерпретации в форте São Vicente: координаты. Часы 10–13, 14–18, закрыт по понедельникам, 2 € (rhlt.pt). | E12: Силы Массена 50 000–61 000, число фортов (152?), «секретность» мягко. Ёмкость форта 2000/4000 (муниципалитет). | F12: Новый хук. Вычитать PT. | G12: нет
A13: aljubarrota-1385 | B13: да | C13: Миниатюра Froissart (BnF fr. 2643, f. 72): найти файл на Commons. | D13: CIBA (São Jorge): адрес, координаты, часы. | E13: Рвы и ямы известны по Froissart, у Лопеша и Айялы их нет («по Фруассару» в истории). 18 000 из слабого источника: заменить. «Час вечерни» через панно CIBA. Возраст Нуну вычислен. | F13: Хук и история переписаны. Вычитать PT. | G13: нет
A14: terramoto-1755 | B14: позже | C14: Гравюра 1755 г. (Commons) или панно «Grande Panorama de Lisboa» (лицензия снимка). | D14: Museu Arqueológico do Carmo: координаты, часы. | E14: Письмо короля: один источник, нужен Molesky. Высота цунами в Лиссабоне не найдена. | F14: Тяжёлая тема. Без правок. | G14: нет
A15: ponte-das-barcas-1809 | B15: позже | C15: Народная гравюра (Museu Soares dos Reis) или картина маслом: файл и лицензия. | D15: Alminhas da Ponte: координаты. Запасной: церковь Сан-Жозе-даш-Тайпаш. | E15: Число погибших (от сотен до 4000): теперь только в истории. «O Desastre» из блога. Свечи и месса из DN. | F15: Тяжёлая тема. Новый хук. | G15: нет
... A17: legiao-portuguesa-1812 | B17: позже | C17: Кандидата нет. | D17: Моста нет. | E17: «60 орденов Почётного легиона» не проверено. Алорна в Кёнигсберге: один источник. Слово «лучшие» убрано. | F17: Новый хук. | G17: нет
A19: Общее перед публикацией
A20: 1 | B20: Прочитать условия использования картинок сервиса (Gemini): коммерческое использование, атрибуция. | G20: нет
A21: 2 | B21: Прочитать правила выбранного сабреддита: ИИ-контент, самореклама, формат ссылок, нужны ли метки (я правил не смотрел). | G21: нет
A22: 3 | B22: Написать раскрытие: тексты написаны с помощью ИИ, факты сверены по открытым источникам, проект в бете. Не писать «проверено историком». | G22: нет
A23: 4 | B23: Показать 3–5 носителям португальского и спросить: есть ли неестественные фразы. | G23: нет
A24: 5 | B24: Закрыть координаты и адреса мостов у карточек набора. | G24: нет
A25: 6 | B25: Скачать картинки (fetch_images.py), проверить кадры превью 1200×630, подписать ИИ-иллюстрации. | G25: нет
A26: 7 | B26: Подготовить к каждой карточке 2–3 ссылки на источники из листа «Источники». | G26: нет
A27: 8 | B27: Подготовить одну страницу для показа и один конкретный вопрос аудитории («какой крючок открыли бы?»). | G27: нет
A28: 9 | B28: Подготовить ответы на ожидаемые возражения: спорные числа, предания, «это ИИ». | G28: нет
A29: 10 | B29: После вычитки RU/PT свериться, что факты совпадают во всех трёх языках. | G29: нет
A30: 11 | B30: Поправить spec §7 и схему Zod под новые лимиты (история 40–90, подробнее до 250 слов) и под три языка. | G30: нет

Sheet Карточки
A1: id | B1: Эпоха | C1: Уровень | D1: Год | E1: Название (RU, для себя) | F1: Нить 1 | G1: Нить 2 | H1: Важность 1–3 | I1: Метка | J1: Возраст | K1: Тяжёлая тема | L1: Статус работы | M1: Источников (найдено) | N1: Проверка | O1: Связанные id (через запятую) | P1: Интерактив: тип | Q1: Интерактив: данные (JSON) | R1: Рецензент | S1: Дата рецензии | T1: Заметки / ⚠ | U1: служ.: строка в Тексты | V1: служ.: строка в Места | W1: служ.: проблемы
A2: cantino-1502 | B2: avis-e-descobrimentos | C2: story | D2: 1502 | E2: Карта Кантино: шпион пришёл за лошадьми | F2: mar | H2: 1 | I2: documented | J2: all | K2: нет | L2: черновик | M2: =IF($A2="","",COUNTIFS(Источники!$A$2:$A$200,$A2,Источники!$G$2:$G$200,"нашли")) -> 8 | N2: =IF($A2="","",IF($W2="","OK",$W2)) -> координаты не проверены; | T2: Источники расходятся, когда карту нашли в лавке (Wikipedia: в 1859, NatGeo: через несколько лет): в тексте года находки нет. Копия в Museu de Marinha: проверить, выставлена ли. Адрес и координаты музея проверить. Картинку (Commons) найти и проверить лицензию. [16.10.2026] Кандидат на картинку записан в листе «Картинки» (файл ещё не скачан). Вид и кадрирование не проверялись. [16.10.2026] Правки владельца: в историю добавлено, как карта повлияла (копия в Генуе, затем карта Вальдземюллера 1507). «Подробнее» расширено и разбито на 4 абзаца. О судьбе самого Кантино после 1502 года надёжных данных не нашёл. | U2: =IF($A2="",0,IFERROR(MATCH($A2,Тексты!$A$1:$A$61,0),0)) -> 2 | V2: =IF($A2="",0,IFERROR(MATCH($A2,Места!$A$1:$A$61,0),0)) -> 2 | W2: =IF($A2="","",IF(COUNTIF($A$2:$A$61,$A2)>1,"дубль id; ","")&IF($B2="","нет эпохи; ","")&IF($C2="","нет уровня; ","")&IF($D2="","нет года; ","")&IF($F2="","нет нити; ","")&IF($H2="","нет важности; ","")&IF($I2="","нет метки; ","")&IF($J2="","нет возраста; ","")&IF($K2="","не указана тяжёлая тема; ","")&IF($M2<IF($C2="frame",2,1),"источников "&$M2&" из "&IF($C2="frame",2,1)&"; ","")&IF($U2=0,"нет строки в «Тексты»; ",IF(INDEX(Тексты!$C$1:$C$61,$U2)=0,"нет крючок EN; ",IF(OR(INDEX(Тексты!$C$1:$C$61,$U2)<1,INDEX(Тексты!$C$1:$C$61,$U2)>12),"крючок EN "&INDEX(Тексты!$C$1:$C$61,$U2)&" сл. (нужно 1–12); ",""))&IF(INDEX(Тексты!$E$1:$E$61,$U2)=0,"нет крючок PT; ",IF(OR(INDEX(Тексты!$E$1:$E$61,$U2)<1,INDEX(Тексты!$E$1:$E$61,$U2)>12),"крючок PT "&INDEX(Тексты!$E$1:$E$61,$U2)&" сл. (нужно 1–12); ",""))&IF(INDEX(Тексты!$O$1:$O$61,$U2)=0,"нет крючок RU; ",IF(OR(INDEX(Тексты!$O$1:$O$61,$U2)<1,INDEX(Тексты!$O$1:$O$61,$U2)>12),"крючок RU "&INDEX(Тексты!$O$1:$O$61,$U2)&" сл. (нужно 1–12); ",""))&IF(INDEX(Тексты!$G$1:$G$61,$U2)=0,"нет история EN; ",IF(OR(INDEX(Тексты!$G$1:$G$61,$U2)<40,INDEX(Тексты!$G$1:$G$61,$U2)>90),"история EN "&INDEX(Тексты!$G$1:$G$61,$U2)&" сл. (нужно 40–90); ",""))&IF(INDEX(Тексты!$I$1:$I$61,$U2)=0,"нет история PT; ",IF(OR(INDEX(Тексты!$I$1:$I$61,$U2)<40,INDEX(Тексты!$I$1:$I$61,$U2)>90),"история PT "&INDEX(Тексты!$I$1:$I$61,$U2)&" сл. (нужно 40–90); ",""))&IF(INDEX(Тексты!$Q$1:$Q$61,$U2)=0,"нет история RU; ",IF(OR(INDEX(Тексты!$Q$1:$Q$61,$U2)<40,INDEX(Тексты!$Q$1:$Q$61,$U2)>90),"история RU "&INDEX(Тексты!$Q$1:$Q$61,$U2)&" сл. (нужно 40–90); ",""))&IF(INDEX(Тексты!$K$1:$K$61,$U2)=0,"нет подробнее EN; ",IF(OR(INDEX(Тексты!$K$1:$K$61,$U2)<1,INDEX(Тексты!$K$1:$K$61,$U2)>250),"подробнее EN "&INDEX(Тексты!$K$1:$K$61,$U2)&" сл. (нужно 1–250); ",""))&IF(INDEX(Тексты!$M$1:$M$61,$U2)=0,"нет подробнее PT; ",IF(OR(INDEX(Тексты!$M$1:$M$61,$U2)<1,INDEX(Тексты!$M$1:$M$61,$U2)>250),"подробнее PT "&INDEX(Тексты!$M$1:$M$61,$U2)&" сл. (нужно 1–250); ",""))&IF(INDEX(Тексты!$S$1:$S$61,$U2)=0,"нет подробнее RU; ",IF(OR(INDEX(Тексты!$S$1:$S$61,$U2)<1,INDEX(Тексты!$S$1:$S$61,$U2)>250),"подробнее RU "&INDEX(Тексты!$S$1:$S$61,$U2)&" сл. (нужно 1–250); ","")))&IF($V2=0,"нет строки в «Места»; ",IF(OR(INDEX(Места!$B$1:$B$61,$V2)="",INDEX(Места!$C$1:$C$61,$V2)="",INDEX(Места!$Q$1:$Q$61,$V2)=""),"нет названия EN/PT/RU; ","")&IF(OR(INDEX(Места!$D$1:$D$61,$V2)="",INDEX(Места!$E$1:$E$61,$V2)="",INDEX(Места!$R$1:$R$61,$V2)=""),"нет slug EN/PT/RU; ","")&IF(INDEX(Места!$K$1:$K$61,$V2)="","нет моста в сегодня; ","")&IF(OR(INDEX(Места!$O$1:$O$61,$V2)="",INDEX(Места!$O$1:$O$61,$V2)="TODO"),"нет сайта моста; ","")&IF(INDEX(Места!$P$1:$P$61,$V2)<>"да","координаты не проверены; ",""))&IF(AND($L2="готово",OR($R2="",$S2="")),"нет рецензента/даты; ","")) -> координаты не проверены;
A3: rinoceronte-1515 | B3: avis-e-descobrimentos | C3: story | D3: 1515 | E3: Носорог и слон | F3: natureza | H3: 1 | I3: documented | J3: all | K3: нет | L3: черновик | M3: =IF($A3="","",COUNTIFS(Источники!$A$2:$A$200,$A3,Источники!$G$2:$G$200,"нашли")) -> 8 | N3: =IF($A3="","",IF($W3="","OK",$W3)) -> нет сайта моста; координаты не проверены; | T3: Метка documented, а не «Предание» как в design: решает историк. Адрес, сайт и координаты Торре-де-Белен проверить. [16.10.2026] Кандидат на картинку записан в листе «Картинки» (файл ещё не скачан). Вид и кадрирование не проверялись. [16.10.2026] Правки владельца: «Подробнее» разбито на 4 абзаца. Про чучело: версии расходятся, следов сохранившегося нет. | U3: =IF($A3="",0,IFERROR(MATCH($A3,Тексты!$A$1:$A$61,0),0)) -> 3 | V3: =IF($A3="",0,IFERROR(MATCH($A3,Места!$A$1:$A$61,0),0)) -> 3 | W3: =IF($A3="","",IF(COUNTIF($A$2:$A$61,$A3)>1,"дубль id; ","")&IF($B3="","нет эпохи; ","")&IF($C3="","нет уровня; ","")&IF($D3="","нет года; ","")&IF($F3="","нет нити; ","")&IF($H3="","нет важности; ","")&IF($I3="","нет метки; ","")&IF($J3="","нет возраста; ","")&IF($K3="","не указана тяжёлая тема; ","")&IF($M3<IF($C3="frame",2,1),"источников "&$M3&" из "&IF($C3="frame",2,1)&"; ","")&IF($U3=0,"нет строки в «Тексты»; ",IF(INDEX(Тексты!$C$1:$C$61,$U3)=0,"нет крючок EN; ",IF(OR(INDEX(Тексты!$C$1:$C$61,$U3)<1,INDEX(Тексты!$C$1:$C$61,$U3)>12),"крючок EN "&INDEX(Тексты!$C$1:$C$61,$U3)&" сл. (нужно 1–12); ",""))&IF(INDEX(Тексты!$E$1:$E$61,$U3)=0,"нет крючок PT; ",IF(OR(INDEX(Тексты!$E$1:$E$61,$U3)<1,INDEX(Тексты!$E$1:$E$61,$U3)>12),"крючок PT "&INDEX(Тексты!$E$1:$E$61,$U3)&" сл. (нужно 1–12); ",""))&IF(INDEX(Тексты!$O$1:$O$61,$U3)=0,"нет крючок RU; ",IF(OR(INDEX(Тексты!$O$1:$O$61,$U3)<1,INDEX(Тексты!$O$1:$O$61,$U3)>12),"крючок RU "&INDEX(Тексты!$O$1:$O$61,$U3)&" сл. (нужно 1–12); ",""))&IF(INDEX(Тексты!$G$1:$G$61,$U3)=0,"нет история EN; ",IF(OR(INDEX(Тексты!$G$1:$G$61,$U3)<40,INDEX(Тексты!$G$1:$G$61,$U3)>90),"история EN "&INDEX(Тексты!$G$1:$G$61,$U3)&" сл. (нужно 40–90); ",""))&IF(INDEX(Тексты!$I$1:$I$61,$U3)=0,"нет история PT; ",IF(OR(INDEX(Тексты!$I$1:$I$61,$U3)<40,INDEX(Тексты!$I$1:$I$61,$U3)>90),"история PT "&INDEX(Тексты!$I$1:$I$61,$U3)&" сл. (нужно 40–90); ",""))&IF(INDEX(Тексты!$Q$1:$Q$61,$U3)=0,"нет история RU; ",IF(OR(INDEX(Тексты!$Q$1:$Q$61,$U3)<40,INDEX(Тексты!$Q$1:$Q$61,$U3)>90),"история RU "&INDEX(Тексты!$Q$1:$Q$61,$U3)&" сл. (нужно 40–90); ",""))&IF(INDEX(Тексты!$K$1:$K$61,$U3)=0,"нет подробнее EN; ",IF(OR(INDEX(Тексты!$K$1:$K$61,$U3)<1,INDEX(Тексты!$K$1:$K$61,$U3)>250),"подробнее EN "&INDEX(Тексты!$K$1:$K$61,$U3)&" сл. (нужно 1–250); ",""))&IF(INDEX(Тексты!$M$1:$M$61,$U3)=0,"нет подробнее PT; ",IF(OR(INDEX(Тексты!$M$1:$M$61,$U3)<1,INDEX(Тексты!$M$1:$M$61,$U3)>250),"подробнее PT "&INDEX(Тексты!$M$1:$M$61,$U3)&" сл. (нужно 1–250); ",""))&IF(INDEX(Тексты!$S$1:$S$61,$U3)=0,"нет подробнее RU; ",IF(OR(INDEX(Тексты!$S$1:$S$61,$U3)<1,INDEX(Тексты!$S$1:$S$61,$U3)>250),"подробнее RU "&INDEX(Тексты!$S$1:$S$61,$U3)&" сл. (нужно 1–250); ","")))&IF($V3=0,"нет строки в «Места»; ",IF(OR(INDEX(Места!$B$1:$B$61,$V3)="",INDEX(Места!$C$1:$C$61,$V3)="",INDEX(Места!$Q$1:$Q$61,$V3)=""),"нет названия EN/PT/RU; ","")&IF(OR(INDEX(Места!$D$1:$D$61,$V3)="",INDEX(Места!$E$1:$E$61,$V3)="",INDEX(Места!$R$1:$R$61,$V3)=""),"нет slug EN/PT/RU; ","")&IF(INDEX(Места!$K$1:$K$61,$V3)="","нет моста в сегодня; ","")&IF(OR(INDEX(Места!$O$1:$O$61,$V3)="",INDEX(Места!$O$1:$O$61,$V3)="TODO"),"нет сайта моста; ","")&IF(INDEX(Места!$P$1:$P$61,$V3)<>"да","координаты не проверены; ",""))&IF(AND($L3="готово",OR($R3="",$S3="")),"нет рецензента/даты; ","")) -> нет сайта моста; координаты не проверены;
A4: tripeiros-1415 | B4: avis-e-descobrimentos | C4: story | D4: 1415 | E4: Tripeiros: город отдал мясо, оставил потроха | F4: comida-e-vinho | G4: gente-como-nos | H4: 1 | I4: legend | J4: all | K4: нет | L4: черновик | M4: =IF($A4="","",COUNTIFS(Источники!$A$2:$A$200,$A4,Источники!$G$2:$G$200,"нашли")) -> 5 | N4: =IF($A4="","",IF($W4="","OK",$W4)) -> координаты не проверены; | T4: Предание: у Зурары не нашли, современной хроники с этим сюжетом нет. Версии расходятся (в одной прозвище старше на 30 лет). Мост: памятник Лагоа Энрикеша 1960 г., официального названия, адреса и сайта нет: найти на сайте муниципалитета Порту. Запасной мост: вокзал Сан-Бенту (азулежу Жорже Колашу про Сеуту). Вторая нить «Люди как мы» на усмотрение владельца. [16.10.2026] Картинка v2 (азулежу, ИИ): мясо теперь читается, средневековая стена и порт ✓. ⚠ Дома с фахверком похожи на северную Европу, не на гранитный Порту; для превью использована обрезка 1200×630. Лицензия не проверена. | U4: =IF($A4="",0,IFERROR(MATCH($A4,Тексты!$A$1:$A$61,0),0)) -> 4 | V4: =IF($A4="",0,IFERROR(MATCH($A4,Места!$A$1:$A$61,0),0)) -> 4 | W4: =IF($A4="","",IF(COUNTIF($A$2:$A$61,$A4)>1,"дубль id; ","")&IF($B4="","нет эпохи; ","")&IF($C4="","нет уровня; ","")&IF($D4="","нет года; ","")&IF($F4="","нет нити; ","")&IF($H4="","нет важности; ","")&IF($I4="","нет метки; ","")&IF($J4="","нет возраста; ","")&IF($K4="","не указана тяжёлая тема; ","")&IF($M4<IF($C4="frame",2,1),"источников "&$M4&" из "&IF($C4="frame",2,1)&"; ","")&IF($U4=0,"нет строки в «Тексты»; ",IF(INDEX(Тексты!$C$1:$C$61,$U4)=0,"нет крючок EN; ",IF(OR(INDEX(Тексты!$C$1:$C$61,$U4)<1,INDEX(Тексты!$C$1:$C$61,$U4)>12),"крючок EN "&INDEX(Тексты!$C$1:$C$61,$U4)&" сл. (нужно 1–12); ",""))&IF(INDEX(Тексты!$E$1:$E$61,$U4)=0,"нет крючок PT; ",IF(OR(INDEX(Тексты!$E$1:$E$61,$U4)<1,INDEX(Тексты!$E$1:$E$61,$U4)>12),"крючок PT "&INDEX(Тексты!$E$1:$E$61,$U4)&" сл. (нужно 1–12); ",""))&IF(INDEX(Тексты!$O$1:$O$61,$U4)=0,"нет крючок RU; ",IF(OR(INDEX(Тексты!$O$1:$O$61,$U4)<1,INDEX(Тексты!$O$1:$O$61,$U4)>12),"крючок RU "&INDEX(Тексты!$O$1:$O$61,$U4)&" сл. (нужно 1–12); ",""))&IF(INDEX(Тексты!$G$1:$G$61,$U4)=0,"нет история EN; ",IF(OR(INDEX(Тексты!$G$1:$G$61,$U4)<40,INDEX(Тексты!$G$1:$G$61,$U4)>90),"история EN "&INDEX(Тексты!$G$1:$G$61,$U4)&" сл. (нужно 40–90); ",""))&IF(INDEX(Тексты!$I$1:$I$61,$U4)=0,"нет история PT; ",IF(OR(INDEX(Тексты!$I$1:$I$61,$U4)<40,INDEX(Тексты!$I$1:$I$61,$U4)>90),"история PT "&INDEX(Тексты!$I$1:$I$61,$U4)&" сл. (нужно 40–90); ",""))&IF(INDEX(Тексты!$Q$1:$Q$61,$U4)=0,"нет история RU; ",IF(OR(INDEX(Тексты!$Q$1:$Q$61,$U4)<40,INDEX(Тексты!$Q$1:$Q$61,$U4)>90),"история RU "&INDEX(Тексты!$Q$1:$Q$61,$U4)&" сл. (нужно 40–90); ",""))&IF(INDEX(Тексты!$K$1:$K$61,$U4)=0,"нет подробнее EN; ",IF(OR(INDEX(Тексты!$K$1:$K$61,$U4)<1,INDEX(Тексты!$K$1:$K$61,$U4)>250),"подробнее EN "&INDEX(Тексты!$K$1:$K$61,$U4)&" сл. (нужно 1–250); ",""))&IF(INDEX(Тексты!$M$1:$M$61,$U4)=0,"нет подробнее PT; ",IF(OR(INDEX(Тексты!$M$1:$M$61,$U4)<1,INDEX(Тексты!$M$1:$M$61,$U4)>250),"подробнее PT "&INDEX(Тексты!$M$1:$M$61,$U4)&" сл. (нужно 1–250); ",""))&IF(INDEX(Тексты!$S$1:$S$61,$U4)=0,"нет подробнее RU; ",IF(OR(INDEX(Тексты!$S$1:$S$61,$U4)<1,INDEX(Тексты!$S$1:$S$61,$U4)>250),"подробнее RU "&INDEX(Тексты!$S$1:$S$61,$U4)&" сл. (нужно 1–250); ","")))&IF($V4=0,"нет строки в «Места»; ",IF(OR(INDEX(Места!$B$1:$B$61,$V4)="",INDEX(Места!$C$1:$C$61,$V4)="",INDEX(Места!$Q$1:$Q$61,$V4)=""),"нет названия EN/PT/RU; ","")&IF(OR(INDEX(Места!$D$1:$D$61,$V4)="",INDEX(Места!$E$1:$E$61,$V4)="",INDEX(Места!$R$1:$R$61,$V4)=""),"нет slug EN/PT/RU; ","")&IF(INDEX(Места!$K$1:$K$61,$V4)="","нет моста в сегодня; ","")&IF(OR(INDEX(Места!$O$1:$O$61,$V4)="",INDEX(Места!$O$1:$O$61,$V4)="TODO"),"нет сайта моста; ","")&IF(INDEX(Места!$P$1:$P$61,$V4)<>"да","координаты не проверены; ",""))&IF(AND($L4="готово",OR($R4="",$S4="")),"нет рецензента/даты; ","")) -> координаты не проверены;
A5: guerra-laranjas-1801 | B5: pombal-e-terramoto | C5: frame | D5: 1801 | E5: Апельсиновая война: Годой теряет Элваш, Португалия теряет Оливенсу | F5: poder-e-revolta | H5: 2 | I5: documented | J5: all | K5: нет | L5: черновик | M5: =IF($A5="","",COUNTIFS(Источники!$A$2:$A$200,$A5,Источники!$G$2:$G$200,"нашли")) -> 8 | N5: =IF($A5="","",IF($W5="","OK",$W5)) -> нет сайта моста; координаты не проверены; | O5: torres-vedras-1810 | T5: Анекдот про ветку апельсина (в PT-источниках «ramo de flores de laranjeira», в документе «ветки апельсина») подан как предание, метка карточки documented относится к войне и договору. Даты расходятся: 20 мая–6 июня или 9 июня; в тексте только «май 1801» и подпись договора 6 июня. Вена 1815 / ратификация Испанией 7 мая 1817: Observador и MNE, лучше взять сам Заключительный акт (ст. 105). Мост: Эльваш (ЮНЕСКО), точка посещения и адрес не выбраны; Оливенса как второй мост. Крепость Santa Luzia из документа не проверена. Координаты приблизительные. [Перепроверка 16.10.2026] Мост в Эльваше не выбран: Forte de Santa Luzia не проверен, в этом раунде не искал. [16.10.2026] Картинка (азулежу, ИИ): сцена с веткой апельсина читается. ⚠ Крепость на холме нарисована как средневековый замок, а не звёздчатый форт Эльваша; в превью она обрезана. Подпись говорит, что это предание. Лицензия не проверена. [16.10.2026] Правки владельца: новый хук; в истории объяснено, почему апельсиновая ветка; «Подробнее» расширено. | U5: =IF($A5="",0,IFERROR(MATCH($A5,Тексты!$A$1:$A$61,0),0)) -> 5 | V5: =IF($A5="",0,IFERROR(MATCH($A5,Места!$A$1:$A$61,0),0)) -> 5 | W5: =IF($A5="","",IF(COUNTIF($A$2:$A$61,$A5)>1,"дубль id; ","")&IF($B5="","нет эпохи; ","")&IF($C5="","нет уровня; ","")&IF($D5="","нет года; ","")&IF($F5="","нет нити; ","")&IF($H5="","нет важности; ","")&IF($I5="","нет метки; ","")&IF($J5="","нет возраста; ","")&IF($K5="","не указана тяжёлая тема; ","")&IF($M5<IF($C5="frame",2,1),"источников "&$M5&" из "&IF($C5="frame",2,1)&"; ","")&IF($U5=0,"нет строки в «Тексты»; ",IF(INDEX(Тексты!$C$1:$C$61,$U5)=0,"нет крючок EN; ",IF(OR(INDEX(Тексты!$C$1:$C$61,$U5)<1,INDEX(Тексты!$C$1:$C$61,$U5)>12),"крючок EN "&INDEX(Тексты!$C$1:$C$61,$U5)&" сл. (нужно 1–12); ",""))&IF(INDEX(Тексты!$E$1:$E$61,$U5)=0,"нет крючок PT; ",IF(OR(INDEX(Тексты!$E$1:$E$61,$U5)<1,INDEX(Тексты!$E$1:$E$61,$U5)>12),"крючок PT "&INDEX(Тексты!$E$1:$E$61,$U5)&" сл. (нужно 1–12); ",""))&IF(INDEX(Тексты!$O$1:$O$61,$U5)=0,"нет крючок RU; ",IF(OR(INDEX(Тексты!$O$1:$O$61,$U5)<1,INDEX(Тексты!$O$1:$O$61,$U5)>12),"крючок RU "&INDEX(Тексты!$O$1:$O$61,$U5)&" сл. (нужно 1–12); ",""))&IF(INDEX(Тексты!$G$1:$G$61,$U5)=0,"нет история EN; ",IF(OR(INDEX(Тексты!$G$1:$G$61,$U5)<40,INDEX(Тексты!$G$1:$G$61,$U5)>90),"история EN "&INDEX(Тексты!$G$1:$G$61,$U5)&" сл. (нужно 40–90); ",""))&IF(INDEX(Тексты!$I$1:$I$61,$U5)=0,"нет история PT; ",IF(OR(INDEX(Тексты!$I$1:$I$61,$U5)<40,INDEX(Тексты!$I$1:$I$61,$U5)>90),"история PT "&INDEX(Тексты!$I$1:$I$61,$U5)&" сл. (нужно 40–90); ",""))&IF(INDEX(Тексты!$Q$1:$Q$61,$U5)=0,"нет история RU; ",IF(OR(INDEX(Тексты!$Q$1:$Q$61,$U5)<40,INDEX(Тексты!$Q$1:$Q$61,$U5)>90),"история RU "&INDEX(Тексты!$Q$1:$Q$61,$U5)&" сл. (нужно 40–90); ",""))&IF(INDEX(Тексты!$K$1:$K$61,$U5)=0,"нет подробнее EN; ",IF(OR(INDEX(Тексты!$K$1:$K$61,$U5)<1,INDEX(Тексты!$K$1:$K$61,$U5)>250),"подробнее EN "&INDEX(Тексты!$K$1:$K$61,$U5)&" сл. (нужно 1–250); ",""))&IF(INDEX(Тексты!$M$1:$M$61,$U5)=0,"нет подробнее PT; ",IF(OR(INDEX(Тексты!$M$1:$M$61,$U5)<1,INDEX(Тексты!$M$1:$M$61,$U5)>250),"подробнее PT "&INDEX(Тексты!$M$1:$M$61,$U5)&" сл. (нужно 1–250); ",""))&IF(INDEX(Тексты!$S$1:$S$61,$U5)=0,"нет подробнее RU; ",IF(OR(INDEX(Тексты!$S$1:$S$61,$U5)<1,INDEX(Тексты!$S$1:$S$61,$U5)>250),"подробнее RU "&INDEX(Тексты!$S$1:$S$61,$U5)&" сл. (нужно 1–250); ","")))&IF($V5=0,"нет строки в «Места»; ",IF(OR(INDEX(Места!$B$1:$B$61,$V5)="",INDEX(Места!$C$1:$C$61,$V5)="",INDEX(Места!$Q$1:$Q$61,$V5)=""),"нет названия EN/PT/RU; ","")&IF(OR(INDEX(Места!$D$1:$D$61,$V5)="",INDEX(Места!$E$1:$E$61,$V5)="",INDEX(Места!$R$1:$R$61,$V5)=""),"нет slug EN/PT/RU; ","")&IF(INDEX(Места!$K$1:$K$61,$V5)="","нет моста в сегодня; ","")&IF(OR(INDEX(Места!$O$1:$O$61,$V5)="",INDEX(Места!$O$1:$O$61,$V5)="TODO"),"нет сайта моста; ","")&IF(INDEX(Места!$P$1:$P$61,$V5)<>"да","координаты не проверены; ",""))&IF(AND($L5="готово",OR($R5="",$S5="")),"нет рецензента/даты; ","")) -> нет сайта моста; координаты не проверены;
A6: casa-da-neve-1782 | B6: pombal-e-terramoto | C6: story | D6: 1782 | E6: Casa da Neve: кафе, которое открыл «снежный мастер» короля | F6: comida-e-vinho | G6: gente-como-nos | H6: 1 | I6: documented | J6: all | K6: нет | L6: черновик | M6: =IF($A6="","",COUNTIFS(Источники!$A$2:$A$200,$A6,Источники!$G$2:$G$200,"нашли")) -> 14 | N6: =IF($A6="","",IF($W6="","OK",$W6)) -> координаты не проверены; | O6: terramoto-1755 | T6: Источники расходятся: день открытия (2 или 7 января 1782), год, когда кафе получило имя Martinho (1829 или 1845). В тексте дня нет, в «Подробнее» оба варианта. Откуда возили снег (Эштрела, Монтежунту?) источники не говорят: в текст не включено. Основатель Julião Pereira de Castro, neveiro-mor da Casa Real: одна газетная статья (CM), нужен второй источник. «Площадь отстроена после 1755» взято из общих знаний, подтвердить. Вторая нить на усмотрение владельца. Официальный сайт кафе найти (пока страница «Lojas com História»). Координаты приблизительные. [Перепроверка 16.10.2026] Год основания в одном источнике 1778 (Ara), в остальных 1782. Источников стало 6. Мост: часы и название стола проверить на сайте кафе. [16.10.2026] Мост заполнен: Café Martinho da Arcada, Praça do Comércio 3 (в реестре города указан Rua da Prata 2/8). Часы расходятся: пн–сб 7–23 по реестру города, ежедневно 12–22 по Time Out; смотреть на martinhodaarcada.pt. Координат нет. Картинка: свободного файла не нашёл, можно снять самому. [16.10.2026] Правки владельца: «Подробнее» расширено (путь снега, монополия, «neve», ссора с Marrare). Год открытия 1778 или 1782 вынесен в историю и подпись года. | U6: =IF($A6="",0,IFERROR(MATCH($A6,Тексты!$A$1:$A$61,0),0)) -> 6 | V6: =IF($A6="",0,IFERROR(MATCH($A6,Места!$A$1:$A$61,0),0)) -> 6 | W6: =IF($A6="","",IF(COUNTIF($A$2:$A$61,$A6)>1,"дубль id; ","")&IF($B6="","нет эпохи; ","")&IF($C6="","нет уровня; ","")&IF($D6="","нет года; ","")&IF($F6="","нет нити; ","")&IF($H6="","нет важности; ","")&IF($I6="","нет метки; ","")&IF($J6="","нет возраста; ","")&IF($K6="","не указана тяжёлая тема; ","")&IF($M6<IF($C6="frame",2,1),"источников "&$M6&" из "&IF($C6="frame",2,1)&"; ","")&IF($U6=0,"нет строки в «Тексты»; ",IF(INDEX(Тексты!$C$1:$C$61,$U6)=0,"нет крючок EN; ",IF(OR(INDEX(Тексты!$C$1:$C$61,$U6)<1,INDEX(Тексты!$C$1:$C$61,$U6)>12),"крючок EN "&INDEX(Тексты!$C$1:$C$61,$U6)&" сл. (нужно 1–12); ",""))&IF(INDEX(Тексты!$E$1:$E$61,$U6)=0,"нет крючок PT; ",IF(OR(INDEX(Тексты!$E$1:$E$61,$U6)<1,INDEX(Тексты!$E$1:$E$61,$U6)>12),"крючок PT "&INDEX(Тексты!$E$1:$E$61,$U6)&" сл. (нужно 1–12); ",""))&IF(INDEX(Тексты!$O$1:$O$61,$U6)=0,"нет крючок RU; ",IF(OR(INDEX(Тексты!$O$1:$O$61,$U6)<1,INDEX(Тексты!$O$1:$O$61,$U6)>12),"крючок RU "&INDEX(Тексты!$O$1:$O$61,$U6)&" сл. (нужно 1–12); ",""))&IF(INDEX(Тексты!$G$1:$G$61,$U6)=0,"нет история EN; ",IF(OR(INDEX(Тексты!$G$1:$G$61,$U6)<40,INDEX(Тексты!$G$1:$G$61,$U6)>90),"история EN "&INDEX(Тексты!$G$1:$G$61,$U6)&" сл. (нужно 40–90); ",""))&IF(INDEX(Тексты!$I$1:$I$61,$U6)=0,"нет история PT; ",IF(OR(INDEX(Тексты!$I$1:$I$61,$U6)<40,INDEX(Тексты!$I$1:$I$61,$U6)>90),"история PT "&INDEX(Тексты!$I$1:$I$61,$U6)&" сл. (нужно 40–90); ",""))&IF(INDEX(Тексты!$Q$1:$Q$61,$U6)=0,"нет история RU; ",IF(OR(INDEX(Тексты!$Q$1:$Q$61,$U6)<40,INDEX(Тексты!$Q$1:$Q$61,$U6)>90),"история RU "&INDEX(Тексты!$Q$1:$Q$61,$U6)&" сл. (нужно 40–90); ",""))&IF(INDEX(Тексты!$K$1:$K$61,$U6)=0,"нет подробнее EN; ",IF(OR(INDEX(Тексты!$K$1:$K$61,$U6)<1,INDEX(Тексты!$K$1:$K$61,$U6)>250),"подробнее EN "&INDEX(Тексты!$K$1:$K$61,$U6)&" сл. (нужно 1–250); ",""))&IF(INDEX(Тексты!$M$1:$M$61,$U6)=0,"нет подробнее PT; ",IF(OR(INDEX(Тексты!$M$1:$M$61,$U6)<1,INDEX(Тексты!$M$1:$M$61,$U6)>250),"подробнее PT "&INDEX(Тексты!$M$1:$M$61,$U6)&" сл. (нужно 1–250); ",""))&IF(INDEX(Тексты!$S$1:$S$61,$U6)=0,"нет подробнее RU; ",IF(OR(INDEX(Тексты!$S$1:$S$61,$U6)<1,INDEX(Тексты!$S$1:$S$61,$U6)>250),"подробнее RU "&INDEX(Тексты!$S$1:$S$61,$U6)&" сл. (нужно 1–250); ","")))&IF($V6=0,"нет строки в «Места»; ",IF(OR(INDEX(Места!$B$1:$B$61,$V6)="",INDEX(Места!$C$1:$C$61,$V6)="",INDEX(Места!$Q$1:$Q$61,$V6)=""),"нет названия EN/PT/RU; ","")&IF(OR(INDEX(Места!$D$1:$D$61,$V6)="",INDEX(Места!$E$1:$E$61,$V6)="",INDEX(Места!$R$1:$R$61,$V6)=""),"нет slug EN/PT/RU; ","")&IF(INDEX(Места!$K$1:$K$61,$V6)="","нет моста в сегодня; ","")&IF(OR(INDEX(Места!$O$1:$O$61,$V6)="",INDEX(Места!$O$1:$O$61,$V6)="TODO"),"нет сайта моста; ","")&IF(INDEX(Места!$P$1:$P$61,$V6)<>"да","координаты не проверены; ",""))&IF(AND($L6="готово",OR($R6="",$S6="")),"нет рецензента/даты; ","")) -> координаты не проверены;
A7: douro-1756 | B7: pombal-e-terramoto | C7: story | D7: 1756 | E7: Камни, которыми огородили портвейн | F7: comida-e-vinho | G7: poder-e-revolta | H7: 1 | I7: documented | J7: all | K7: нет | L7: черновик | M7: =IF($A7="","",COUNTIFS(Источники!$A$2:$A$200,$A7,Источники!$G$2:$G$200,"нашли")) -> 4 | N7: =IF($A7="","",IF($W7="","OK",$W7)) -> координаты не проверены; | O7: motim-companhia-1757 | T7: [16.10.2026] Новая карточка: выделена из Motim по замечанию владельца (основание Компании и демаркация отдельно от бунта). Факты по Taylor's, Wine Anorak, UP; «бузина» подана без подробностей про подделку цвета. Картинка: фото marco pombalino на Commons не искал. | U7: =IF($A7="",0,IFERROR(MATCH($A7,Тексты!$A$1:$A$61,0),0)) -> 7 | V7: =IF($A7="",0,IFERROR(MATCH($A7,Места!$A$1:$A$61,0),0)) -> 7 | W7: =IF($A7="","",IF(COUNTIF($A$2:$A$61,$A7)>1,"дубль id; ","")&IF($B7="","нет эпохи; ","")&IF($C7="","нет уровня; ","")&IF($D7="","нет года; ","")&IF($F7="","нет нити; ","")&IF($H7="","нет важности; ","")&IF($I7="","нет метки; ","")&IF($J7="","нет возраста; ","")&IF($K7="","не указана тяжёлая тема; ","")&IF($M7<IF($C7="frame",2,1),"источников "&$M7&" из "&IF($C7="frame",2,1)&"; ","")&IF($U7=0,"нет строки в «Тексты»; ",IF(INDEX(Тексты!$C$1:$C$61,$U7)=0,"нет крючок EN; ",IF(OR(INDEX(Тексты!$C$1:$C$61,$U7)<1,INDEX(Тексты!$C$1:$C$61,$U7)>12),"крючок EN "&INDEX(Тексты!$C$1:$C$61,$U7)&" сл. (нужно 1–12); ",""))&IF(INDEX(Тексты!$E$1:$E$61,$U7)=0,"нет крючок PT; ",IF(OR(INDEX(Тексты!$E$1:$E$61,$U7)<1,INDEX(Тексты!$E$1:$E$61,$U7)>12),"крючок PT "&INDEX(Тексты!$E$1:$E$61,$U7)&" сл. (нужно 1–12); ",""))&IF(INDEX(Тексты!$O$1:$O$61,$U7)=0,"нет крючок RU; ",IF(OR(INDEX(Тексты!$O$1:$O$61,$U7)<1,INDEX(Тексты!$O$1:$O$61,$U7)>12),"крючок RU "&INDEX(Тексты!$O$1:$O$61,$U7)&" сл. (нужно 1–12); ",""))&IF(INDEX(Тексты!$G$1:$G$61,$U7)=0,"нет история EN; ",IF(OR(INDEX(Тексты!$G$1:$G$61,$U7)<40,INDEX(Тексты!$G$1:$G$61,$U7)>90),"история EN "&INDEX(Тексты!$G$1:$G$61,$U7)&" сл. (нужно 40–90); ",""))&IF(INDEX(Тексты!$I$1:$I$61,$U7)=0,"нет история PT; ",IF(OR(INDEX(Тексты!$I$1:$I$61,$U7)<40,INDEX(Тексты!$I$1:$I$61,$U7)>90),"история PT "&INDEX(Тексты!$I$1:$I$61,$U7)&" сл. (нужно 40–90); ",""))&IF(INDEX(Тексты!$Q$1:$Q$61,$U7)=0,"нет история RU; ",IF(OR(INDEX(Тексты!$Q$1:$Q$61,$U7)<40,INDEX(Тексты!$Q$1:$Q$61,$U7)>90),"история RU "&INDEX(Тексты!$Q$1:$Q$61,$U7)&" сл. (нужно 40–90); ",""))&IF(INDEX(Тексты!$K$1:$K$61,$U7)=0,"нет подробнее EN; ",IF(OR(INDEX(Тексты!$K$1:$K$61,$U7)<1,INDEX(Тексты!$K$1:$K$61,$U7)>250),"подробнее EN "&INDEX(Тексты!$K$1:$K$61,$U7)&" сл. (нужно 1–250); ",""))&IF(INDEX(Тексты!$M$1:$M$61,$U7)=0,"нет подробнее PT; ",IF(OR(INDEX(Тексты!$M$1:$M$61,$U7)<1,INDEX(Тексты!$M$1:$M$61,$U7)>250),"подробнее PT "&INDEX(Тексты!$M$1:$M$61,$U7)&" сл. (нужно 1–250); ",""))&IF(INDEX(Тексты!$S$1:$S$61,$U7)=0,"нет подробнее RU; ",IF(OR(INDEX(Тексты!$S$1:$S$61,$U7)<1,INDEX(Тексты!$S$1:$S$61,$U7)>250),"подробнее RU "&INDEX(Тексты!$S$1:$S$61,$U7)&" сл. (нужно 1–250); ","")))&IF($V7=0,"нет строки в «Места»; ",IF(OR(INDEX(Места!$B$1:$B$61,$V7)="",INDEX(Места!$C$1:$C$61,$V7)="",INDEX(Места!$Q$1:$Q$61,$V7)=""),"нет названия EN/PT/RU; ","")&IF(OR(INDEX(Места!$D$1:$D$61,$V7)="",INDEX(Места!$E$1:$E$61,$V7)="",INDEX(Места!$R$1:$R$61,$V7)=""),"нет slug EN/PT/RU; ","")&IF(INDEX(Места!$K$1:$K$61,$V7)="","нет моста в сегодня; ","")&IF(OR(INDEX(Места!$O$1:$O$61,$V7)="",INDEX(Места!$O$1:$O$61,$V7)="TODO"),"нет сайта моста; ","")&IF(INDEX(Места!$P$1:$P$61,$V7)<>"да","координаты не проверены; ",""))&IF(AND($L7="готово",OR($R7="",$S7="")),"нет рецензента/даты; ","")) -> координаты не проверены;
A8: elefantes-malaca-1511 | B8: avis-e-descobrimentos | C8: story | D8: 1511 | E8: День, когда слоны повернули назад (Малакка) | F8: natureza | H8: 1 | I8: documented | J8: 12 | K8: нет | L8: черновик | M8: =IF($A8="","",COUNTIFS(Источники!$A$2:$A$200,$A8,Источники!$G$2:$G$200,"нашли")) -> 10 | N8: =IF($A8="","",IF($W8="","OK",$W8)) -> нет сайта моста; координаты не проверены; | T8: Источники расходятся: число слонов (≈20 по одному, «стадо» по другому) и как упал султан. «Отравленные дротики» и «4-метровые пики» из списка Gemini не подтвердились: в тексте только «лэнс/копьё». Первоисточник (хроники, «Комментарии») не читан. Мост: Casa dos Bicos, построена сыном Албукерки Брасом: проверить координаты, часы работы (источники расходятся: пн–пт или пн–сб). [16.10.2026] Дата падения города (15 или 24 августа) и численность сил расходятся: см. заметку в «Тексты». Кандидат на картинку: рисунок «Malaca» из Lendas da Índia Гаспара Корреи (Torre do Tombo). [16.10.2026] Кандидат на картинку записан в листе «Картинки» (файл ещё не скачан). Вид и кадрирование не проверялись. [16.10.2026] Правки владельца: новый хук, история с цитатой Пиреша. Мост заменён на памятник Албукерки в Белеме (Casa dos Bicos осталась в тексте через сына Браша). Официальной страницы моста нет. | U8: =IF($A8="",0,IFERROR(MATCH($A8,Тексты!$A$1:$A$61,0),0)) -> 8 | V8: =IF($A8="",0,IFERROR(MATCH($A8,Места!$A$1:$A$61,0),0)) -> 8 | W8: =IF($A8="","",IF(COUNTIF($A$2:$A$61,$A8)>1,"дубль id; ","")&IF($B8="","нет эпохи; ","")&IF($C8="","нет уровня; ","")&IF($D8="","нет года; ","")&IF($F8="","нет нити; ","")&IF($H8="","нет важности; ","")&IF($I8="","нет метки; ","")&IF($J8="","нет возраста; ","")&IF($K8="","не указана тяжёлая тема; ","")&IF($M8<IF($C8="frame",2,1),"источников "&$M8&" из "&IF($C8="frame",2,1)&"; ","")&IF($U8=0,"нет строки в «Тексты»; ",IF(INDEX(Тексты!$C$1:$C$61,$U8)=0,"нет крючок EN; ",IF(OR(INDEX(Тексты!$C$1:$C$61,$U8)<1,INDEX(Тексты!$C$1:$C$61,$U8)>12),"крючок EN "&INDEX(Тексты!$C$1:$C$61,$U8)&" сл. (нужно 1–12); ",""))&IF(INDEX(Тексты!$E$1:$E$61,$U8)=0,"нет крючок PT; ",IF(OR(INDEX(Тексты!$E$1:$E$61,$U8)<1,INDEX(Тексты!$E$1:$E$61,$U8)>12),"крючок PT "&INDEX(Тексты!$E$1:$E$61,$U8)&" сл. (нужно 1–12); ",""))&IF(INDEX(Тексты!$O$1:$O$61,$U8)=0,"нет крючок RU; ",IF(OR(INDEX(Тексты!$O$1:$O$61,$U8)<1,INDEX(Тексты!$O$1:$O$61,$U8)>12),"крючок RU "&INDEX(Тексты!$O$1:$O$61,$U8)&" сл. (нужно 1–12); ",""))&IF(INDEX(Тексты!$G$1:$G$61,$U8)=0,"нет история EN; ",IF(OR(INDEX(Тексты!$G$1:$G$61,$U8)<40,INDEX(Тексты!$G$1:$G$61,$U8)>90),"история EN "&INDEX(Тексты!$G$1:$G$61,$U8)&" сл. (нужно 40–90); ",""))&IF(INDEX(Тексты!$I$1:$I$61,$U8)=0,"нет история PT; ",IF(OR(INDEX(Тексты!$I$1:$I$61,$U8)<40,INDEX(Тексты!$I$1:$I$61,$U8)>90),"история PT "&INDEX(Тексты!$I$1:$I$61,$U8)&" сл. (нужно 40–90); ",""))&IF(INDEX(Тексты!$Q$1:$Q$61,$U8)=0,"нет история RU; ",IF(OR(INDEX(Тексты!$Q$1:$Q$61,$U8)<40,INDEX(Тексты!$Q$1:$Q$61,$U8)>90),"история RU "&INDEX(Тексты!$Q$1:$Q$61,$U8)&" сл. (нужно 40–90); ",""))&IF(INDEX(Тексты!$K$1:$K$61,$U8)=0,"нет подробнее EN; ",IF(OR(INDEX(Тексты!$K$1:$K$61,$U8)<1,INDEX(Тексты!$K$1:$K$61,$U8)>250),"подробнее EN "&INDEX(Тексты!$K$1:$K$61,$U8)&" сл. (нужно 1–250); ",""))&IF(INDEX(Тексты!$M$1:$M$61,$U8)=0,"нет подробнее PT; ",IF(OR(INDEX(Тексты!$M$1:$M$61,$U8)<1,INDEX(Тексты!$M$1:$M$61,$U8)>250),"подробнее PT "&INDEX(Тексты!$M$1:$M$61,$U8)&" сл. (нужно 1–250); ",""))&IF(INDEX(Тексты!$S$1:$S$61,$U8)=0,"нет подробнее RU; ",IF(OR(INDEX(Тексты!$S$1:$S$61,$U8)<1,INDEX(Тексты!$S$1:$S$61,$U8)>250),"подробнее RU "&INDEX(Тексты!$S$1:$S$61,$U8)&" сл. (нужно 1–250); ","")))&IF($V8=0,"нет строки в «Места»; ",IF(OR(INDEX(Места!$B$1:$B$61,$V8)="",INDEX(Места!$C$1:$C$61,$V8)="",INDEX(Места!$Q$1:$Q$61,$V8)=""),"нет названия EN/PT/RU; ","")&IF(OR(INDEX(Места!$D$1:$D$61,$V8)="",INDEX(Места!$E$1:$E$61,$V8)="",INDEX(Места!$R$1:$R$61,$V8)=""),"нет slug EN/PT/RU; ","")&IF(INDEX(Места!$K$1:$K$61,$V8)="","нет моста в сегодня; ","")&IF(OR(INDEX(Места!$O$1:$O$61,$V8)="",INDEX(Места!$O$1:$O$61,$V8)="TODO"),"нет сайта моста; ","")&IF(INDEX(Места!$P$1:$P$61,$V8)<>"да","координаты не проверены; ",""))&IF(AND($L8="готово",OR($R8="",$S8="")),"нет рецензента/даты; ","")) -> нет сайта моста; координаты не проверены;
A9: torres-vedras-1810 | B9: pombal-e-terramoto | C9: frame | D9: 1810 | E9: Линии Торрес-Ведрас: Массена нашёл крепость, о которой не знал | F9: poder-e-revolta | G9: gente-como-nos | H9: 3 | I9: documented | J9: 12 | K9: да | L9: черновик | M9: =IF($A9="","",COUNTIFS(Источники!$A$2:$A$200,$A9,Источники!$G$2:$G$200,"нашли")) -> 7 | N9: =IF($A9="","",IF($W9="","OK",$W9)) -> координаты не проверены; | O9: legiao-portuguesa-1812, ponte-das-barcas-1809 | T9: Число фортов не вынесено в текст: источники расходятся (в документе 152, в справочниках «более 150»). «Тысячи рабочих» заменено на «Portuguese workers»: число не подтверждено. Число португальских мирных жертв (≈50 тыс. по Military Wiki) слабый источник: в «Подробнее» только «десятки тысяч» с оговоркой, нужен научный источник. Заданные в тексте 60 000 у Массены: Wikipedia (61 000), историки дают 60–65 тыс. Форт São Vicente и его часы работы не проверены. Координаты форта не заполнены. Вторая нить на усмотрение владельца. [Перепроверка 16.10.2026] Мост выбран: Центр интерпретации Линий в форте São Vicente (официальный сайт маршрута). Часы (10–13, 14–18, закрыт по понедельникам) и цена (2 €) смотрите на сайте при публикации. Координаты форта ещё не заполнены. [16.10.2026] Кандидат на картинку записан в листе «Картинки» (файл ещё не скачан). Вид и кадрирование не проверялись. [16.10.2026] Правки владельца: новый хук. | U9: =IF($A9="",0,IFERROR(MATCH($A9,Тексты!$A$1:$A$61,0),0)) -> 9 | V9: =IF($A9="",0,IFERROR(MATCH($A9,Места!$A$1:$A$61,0),0)) -> 9 | W9: =IF($A9="","",IF(COUNTIF($A$2:$A$61,$A9)>1,"дубль id; ","")&IF($B9="","нет эпохи; ","")&IF($C9="","нет уровня; ","")&IF($D9="","нет года; ","")&IF($F9="","нет нити; ","")&IF($H9="","нет важности; ","")&IF($I9="","нет метки; ","")&IF($J9="","нет возраста; ","")&IF($K9="","не указана тяжёлая тема; ","")&IF($M9<IF($C9="frame",2,1),"источников "&$M9&" из "&IF($C9="frame",2,1)&"; ","")&IF($U9=0,"нет строки в «Тексты»; ",IF(INDEX(Тексты!$C$1:$C$61,$U9)=0,"нет крючок EN; ",IF(OR(INDEX(Тексты!$C$1:$C$61,$U9)<1,INDEX(Тексты!$C$1:$C$61,$U9)>12),"крючок EN "&INDEX(Тексты!$C$1:$C$61,$U9)&" сл. (нужно 1–12); ",""))&IF(INDEX(Тексты!$E$1:$E$61,$U9)=0,"нет крючок PT; ",IF(OR(INDEX(Тексты!$E$1:$E$61,$U9)<1,INDEX(Тексты!$E$1:$E$61,$U9)>12),"крючок PT "&INDEX(Тексты!$E$1:$E$61,$U9)&" сл. (нужно 1–12); ",""))&IF(INDEX(Тексты!$O$1:$O$61,$U9)=0,"нет крючок RU; ",IF(OR(INDEX(Тексты!$O$1:$O$61,$U9)<1,INDEX(Тексты!$O$1:$O$61,$U9)>12),"крючок RU "&INDEX(Тексты!$O$1:$O$61,$U9)&" сл. (нужно 1–12); ",""))&IF(INDEX(Тексты!$G$1:$G$61,$U9)=0,"нет история EN; ",IF(OR(INDEX(Тексты!$G$1:$G$61,$U9)<40,INDEX(Тексты!$G$1:$G$61,$U9)>90),"история EN "&INDEX(Тексты!$G$1:$G$61,$U9)&" сл. (нужно 40–90); ",""))&IF(INDEX(Тексты!$I$1:$I$61,$U9)=0,"нет история PT; ",IF(OR(INDEX(Тексты!$I$1:$I$61,$U9)<40,INDEX(Тексты!$I$1:$I$61,$U9)>90),"история PT "&INDEX(Тексты!$I$1:$I$61,$U9)&" сл. (нужно 40–90); ",""))&IF(INDEX(Тексты!$Q$1:$Q$61,$U9)=0,"нет история RU; ",IF(OR(INDEX(Тексты!$Q$1:$Q$61,$U9)<40,INDEX(Тексты!$Q$1:$Q$61,$U9)>90),"история RU "&INDEX(Тексты!$Q$1:$Q$61,$U9)&" сл. (нужно 40–90); ",""))&IF(INDEX(Тексты!$K$1:$K$61,$U9)=0,"нет подробнее EN; ",IF(OR(INDEX(Тексты!$K$1:$K$61,$U9)<1,INDEX(Тексты!$K$1:$K$61,$U9)>250),"подробнее EN "&INDEX(Тексты!$K$1:$K$61,$U9)&" сл. (нужно 1–250); ",""))&IF(INDEX(Тексты!$M$1:$M$61,$U9)=0,"нет подробнее PT; ",IF(OR(INDEX(Тексты!$M$1:$M$61,$U9)<1,INDEX(Тексты!$M$1:$M$61,$U9)>250),"подробнее PT "&INDEX(Тексты!$M$1:$M$61,$U9)&" сл. (нужно 1–250); ",""))&IF(INDEX(Тексты!$S$1:$S$61,$U9)=0,"нет подробнее RU; ",IF(OR(INDEX(Тексты!$S$1:$S$61,$U9)<1,INDEX(Тексты!$S$1:$S$61,$U9)>250),"подробнее RU "&INDEX(Тексты!$S$1:$S$61,$U9)&" сл. (нужно 1–250); ","")))&IF($V9=0,"нет строки в «Места»; ",IF(OR(INDEX(Места!$B$1:$B$61,$V9)="",INDEX(Места!$C$1:$C$61,$V9)="",INDEX(Места!$Q$1:$Q$61,$V9)=""),"нет названия EN/PT/RU; ","")&IF(OR(INDEX(Места!$D$1:$D$61,$V9)="",INDEX(Места!$E$1:$E$61,$V9)="",INDEX(Места!$R$1:$R$61,$V9)=""),"нет slug EN/PT/RU; ","")&IF(INDEX(Места!$K$1:$K$61,$V9)="","нет моста в сегодня; ","")&IF(OR(INDEX(Места!$O$1:$O$61,$V9)="",INDEX(Места!$O$1:$O$61,$V9)="TODO"),"нет сайта моста; ","")&IF(INDEX(Места!$P$1:$P$61,$V9)<>"да","координаты не проверены; ",""))&IF(AND($L9="готово",OR($R9="",$S9="")),"нет рецензента/даты; ","")) -> координаты не проверены;
A10: aljubarrota-1385 | B10: avis-e-descobrimentos | C10: frame | D10: 1385 | E10: Алжубарроту | F10: poder-e-revolta | G10: gente-como-nos | H10: 3 | I10: documented | J10: 12 | K10: нет | L10: черновик | M10: =IF($A10="","",COUNTIFS(Источники!$A$2:$A$200,$A10,Источники!$G$2:$G$200,"нашли")) -> 9 | N10: =IF($A10="","",IF($W10="","OK",$W10)) -> координаты не проверены; | O10: terramoto-1755 | P10: army_dots | Q10: {"dot_value": 1000, "portuguese": {"low": 7000, "high": 7000}, "castilian": {"low": 18000, "high": 44000}, "castilian_in_combat": 10000, "caption": {"en": "By historians' estimates. Figures vary widely between sources.", "pt": "Segundo estimativas de historiadores. Os números variam muito entre fontes."}} | T10: Текст переписан (v3): совет не согласился, Нуну 25 лет, конец через Кармо. Цифра 18 000 из слабого источника. sensitive=нет и вторая нить: решения владельца. Лопеш про «час вечерни» взят из панно CIBA, сам текст хроники не читан. [16.10.2026] Хук и история смягчены: рвы и ямы известны по Froissart, у Лопеша и очевидца Айялы их нет. Кандидат на картинку: миниатюра Froissart (BnF fr. 2643, f. 72), PD на Commons. [16.10.2026] Правки владельца: хук переписан, история начинается с Нуну и не скомкана (лимит расширен). | U10: =IF($A10="",0,IFERROR(MATCH($A10,Тексты!$A$1:$A$61,0),0)) -> 10 | V10: =IF($A10="",0,IFERROR(MATCH($A10,Места!$A$1:$A$61,0),0)) -> 10 | W10: =IF($A10="","",IF(COUNTIF($A$2:$A$61,$A10)>1,"дубль id; ","")&IF($B10="","нет эпохи; ","")&IF($C10="","нет уровня; ","")&IF($D10="","нет года; ","")&IF($F10="","нет нити; ","")&IF($H10="","нет важности; ","")&IF($I10="","нет метки; ","")&IF($J10="","нет возраста; ","")&IF($K10="","не указана тяжёлая тема; ","")&IF($M10<IF($C10="frame",2,1),"источников "&$M10&" из "&IF($C10="frame",2,1)&"; ","")&IF($U10=0,"нет строки в «Тексты»; ",IF(INDEX(Тексты!$C$1:$C$61,$U10)=0,"нет крючок EN; ",IF(OR(INDEX(Тексты!$C$1:$C$61,$U10)<1,INDEX(Тексты!$C$1:$C$61,$U10)>12),"крючок EN "&INDEX(Тексты!$C$1:$C$61,$U10)&" сл. (нужно 1–12); ",""))&IF(INDEX(Тексты!$E$1:$E$61,$U10)=0,"нет крючок PT; ",IF(OR(INDEX(Тексты!$E$1:$E$61,$U10)<1,INDEX(Тексты!$E$1:$E$61,$U10)>12),"крючок PT "&INDEX(Тексты!$E$1:$E$61,$U10)&" сл. (нужно 1–12); ",""))&IF(INDEX(Тексты!$O$1:$O$61,$U10)=0,"нет крючок RU; ",IF(OR(INDEX(Тексты!$O$1:$O$61,$U10)<1,INDEX(Тексты!$O$1:$O$61,$U10)>12),"крючок RU "&INDEX(Тексты!$O$1:$O$61,$U10)&" сл. (нужно 1–12); ",""))&IF(INDEX(Тексты!$G$1:$G$61,$U10)=0,"нет история EN; ",IF(OR(INDEX(Тексты!$G$1:$G$61,$U10)<40,INDEX(Тексты!$G$1:$G$61,$U10)>90),"история EN "&INDEX(Тексты!$G$1:$G$61,$U10)&" сл. (нужно 40–90); ",""))&IF(INDEX(Тексты!$I$1:$I$61,$U10)=0,"нет история PT; ",IF(OR(INDEX(Тексты!$I$1:$I$61,$U10)<40,INDEX(Тексты!$I$1:$I$61,$U10)>90),"история PT "&INDEX(Тексты!$I$1:$I$61,$U10)&" сл. (нужно 40–90); ",""))&IF(INDEX(Тексты!$Q$1:$Q$61,$U10)=0,"нет история RU; ",IF(OR(INDEX(Тексты!$Q$1:$Q$61,$U10)<40,INDEX(Тексты!$Q$1:$Q$61,$U10)>90),"история RU "&INDEX(Тексты!$Q$1:$Q$61,$U10)&" сл. (нужно 40–90); ",""))&IF(INDEX(Тексты!$K$1:$K$61,$U10)=0,"нет подробнее EN; ",IF(OR(INDEX(Тексты!$K$1:$K$61,$U10)<1,INDEX(Тексты!$K$1:$K$61,$U10)>250),"подробнее EN "&INDEX(Тексты!$K$1:$K$61,$U10)&" сл. (нужно 1–250); ",""))&IF(INDEX(Тексты!$M$1:$M$61,$U10)=0,"нет подробнее PT; ",IF(OR(INDEX(Тексты!$M$1:$M$61,$U10)<1,INDEX(Тексты!$M$1:$M$61,$U10)>250),"подробнее PT "&INDEX(Тексты!$M$1:$M$61,$U10)&" сл. (нужно 1–250); ",""))&IF(INDEX(Тексты!$S$1:$S$61,$U10)=0,"нет подробнее RU; ",IF(OR(INDEX(Тексты!$S$1:$S$61,$U10)<1,INDEX(Тексты!$S$1:$S$61,$U10)>250),"подробнее RU "&INDEX(Тексты!$S$1:$S$61,$U10)&" сл. (нужно 1–250); ","")))&IF($V10=0,"нет строки в «Места»; ",IF(OR(INDEX(Места!$B$1:$B$61,$V10)="",INDEX(Места!$C$1:$C$61,$V10)="",INDEX(Места!$Q$1:$Q$61,$V10)=""),"нет названия EN/PT/RU; ","")&IF(OR(INDEX(Места!$D$1:$D$61,$V10)="",INDEX(Места!$E$1:$E$61,$V10)="",INDEX(Места!$R$1:$R$61,$V10)=""),"нет slug EN/PT/RU; ","")&IF(INDEX(Места!$K$1:$K$61,$V10)="","нет моста в сегодня; ","")&IF(OR(INDEX(Места!$O$1:$O$61,$V10)="",INDEX(Места!$O$1:$O$61,$V10)="TODO"),"нет сайта моста; ","")&IF(INDEX(Места!$P$1:$P$61,$V10)<>"да","координаты не проверены; ",""))&IF(AND($L10="готово",OR($R10="",$S10="")),"нет рецензента/даты; ","")) -> координаты не проверены;
A11: terramoto-1755 | B11: pombal-e-terramoto | C11: frame | D11: 1755 | E11: Землетрясение 1755 | F11: natureza | H11: 3 | I11: documented | J11: 12 | K11: да | L11: черновик | M11: =IF($A11="","",COUNTIFS(Источники!$A$2:$A$200,$A11,Источники!$G$2:$G$200,"нашли")) -> 7 | N11: =IF($A11="","",IF($W11="","OK",$W11)) -> координаты не проверены; | O11: aljubarrota-1385 | T11: Текст переписан (v2): король, дочь, палатки, Помбал. Письмо короля: один источник. Кант и Вольтер убраны из «Подробнее» ради места. Высоту цунами в Лиссабоне не нашли: числа в тексте нет. [16.10.2026] Кандидат на картинку записан в листе «Картинки» (файл ещё не скачан). Вид и кадрирование не проверялись. | U11: =IF($A11="",0,IFERROR(MATCH($A11,Тексты!$A$1:$A$61,0),0)) -> 11 | V11: =IF($A11="",0,IFERROR(MATCH($A11,Места!$A$1:$A$61,0),0)) -> 11 | W11: =IF($A11="","",IF(COUNTIF($A$2:$A$61,$A11)>1,"дубль id; ","")&IF($B11="","нет эпохи; ","")&IF($C11="","нет уровня; ","")&IF($D11="","нет года; ","")&IF($F11="","нет нити; ","")&IF($H11="","нет важности; ","")&IF($I11="","нет метки; ","")&IF($J11="","нет возраста; ","")&IF($K11="","не указана тяжёлая тема; ","")&IF($M11<IF($C11="frame",2,1),"источников "&$M11&" из "&IF($C11="frame",2,1)&"; ","")&IF($U11=0,"нет строки в «Тексты»; ",IF(INDEX(Тексты!$C$1:$C$61,$U11)=0,"нет крючок EN; ",IF(OR(INDEX(Тексты!$C$1:$C$61,$U11)<1,INDEX(Тексты!$C$1:$C$61,$U11)>12),"крючок EN "&INDEX(Тексты!$C$1:$C$61,$U11)&" сл. (нужно 1–12); ",""))&IF(INDEX(Тексты!$E$1:$E$61,$U11)=0,"нет крючок PT; ",IF(OR(INDEX(Тексты!$E$1:$E$61,$U11)<1,INDEX(Тексты!$E$1:$E$61,$U11)>12),"крючок PT "&INDEX(Тексты!$E$1:$E$61,$U11)&" сл. (нужно 1–12); ",""))&IF(INDEX(Тексты!$O$1:$O$61,$U11)=0,"нет крючок RU; ",IF(OR(INDEX(Тексты!$O$1:$O$61,$U11)<1,INDEX(Тексты!$O$1:$O$61,$U11)>12),"крючок RU "&INDEX(Тексты!$O$1:$O$61,$U11)&" сл. (нужно 1–12); ",""))&IF(INDEX(Тексты!$G$1:$G$61,$U11)=0,"нет история EN; ",IF(OR(INDEX(Тексты!$G$1:$G$61,$U11)<40,INDEX(Тексты!$G$1:$G$61,$U11)>90),"история EN "&INDEX(Тексты!$G$1:$G$61,$U11)&" сл. (нужно 40–90); ",""))&IF(INDEX(Тексты!$I$1:$I$61,$U11)=0,"нет история PT; ",IF(OR(INDEX(Тексты!$I$1:$I$61,$U11)<40,INDEX(Тексты!$I$1:$I$61,$U11)>90),"история PT "&INDEX(Тексты!$I$1:$I$61,$U11)&" сл. (нужно 40–90); ",""))&IF(INDEX(Тексты!$Q$1:$Q$61,$U11)=0,"нет история RU; ",IF(OR(INDEX(Тексты!$Q$1:$Q$61,$U11)<40,INDEX(Тексты!$Q$1:$Q$61,$U11)>90),"история RU "&INDEX(Тексты!$Q$1:$Q$61,$U11)&" сл. (нужно 40–90); ",""))&IF(INDEX(Тексты!$K$1:$K$61,$U11)=0,"нет подробнее EN; ",IF(OR(INDEX(Тексты!$K$1:$K$61,$U11)<1,INDEX(Тексты!$K$1:$K$61,$U11)>250),"подробнее EN "&INDEX(Тексты!$K$1:$K$61,$U11)&" сл. (нужно 1–250); ",""))&IF(INDEX(Тексты!$M$1:$M$61,$U11)=0,"нет подробнее PT; ",IF(OR(INDEX(Тексты!$M$1:$M$61,$U11)<1,INDEX(Тексты!$M$1:$M$61,$U11)>250),"подробнее PT "&INDEX(Тексты!$M$1:$M$61,$U11)&" сл. (нужно 1–250); ",""))&IF(INDEX(Тексты!$S$1:$S$61,$U11)=0,"нет подробнее RU; ",IF(OR(INDEX(Тексты!$S$1:$S$61,$U11)<1,INDEX(Тексты!$S$1:$S$61,$U11)>250),"подробнее RU "&INDEX(Тексты!$S$1:$S$61,$U11)&" сл. (нужно 1–250); ","")))&IF($V11=0,"нет строки в «Места»; ",IF(OR(INDEX(Места!$B$1:$B$61,$V11)="",INDEX(Места!$C$1:$C$61,$V11)="",INDEX(Места!$Q$1:$Q$61,$V11)=""),"нет названия EN/PT/RU; ","")&IF(OR(INDEX(Места!$D$1:$D$61,$V11)="",INDEX(Места!$E$1:$E$61,$V11)="",INDEX(Места!$R$1:$R$61,$V11)=""),"нет slug EN/PT/RU; ","")&IF(INDEX(Места!$K$1:$K$61,$V11)="","нет моста в сегодня; ","")&IF(OR(INDEX(Места!$O$1:$O$61,$V11)="",INDEX(Места!$O$1:$O$61,$V11)="TODO"),"нет сайта моста; ","")&IF(INDEX(Места!$P$1:$P$61,$V11)<>"да","координаты не проверены; ",""))&IF(AND($L11="готово",OR($R11="",$S11="")),"нет рецензента/даты; ","")) -> координаты не проверены;
A12: ponte-das-barcas-1809 | B12: pombal-e-terramoto | C12: story | D12: 1809 | E12: Мост из лодок: бегство из Порту 29 марта 1809 | F12: gente-como-nos | H12: 2 | I12: documented | J12: 12 | K12: да | L12: черновик | M12: =IF($A12="","",COUNTIFS(Источники!$A$2:$A$200,$A12,Источники!$G$2:$G$200,"нашли")) -> 6 | N12: =IF($A12="","",IF($W12="","OK",$W12)) -> нет сайта моста; координаты не проверены; | O12: motim-companhia-1757, torres-vedras-1810 | T12: Тяжёлая тема: массовая гибель людей. Число погибших: ≈4000 (Wikipedia, список бедствий) и ≈5000 (Infopédia): в тексте диапазон 4000–5000. Скульптор Teixeira Lopes и дата 1897: Wikipedia, нужен второй источник. «Мост построен в 1806»: Infopédia. Исправление к списку: «Alminhas da Ponte» — бронзовый барельеф 1897, не «свечи из старины»; ежегодные процессии упомянуты слабым источником (audiala), в текст не включены. Координаты места и памятника не заполнены: найти. Нет второй нити. [Перепроверка 16.10.2026] Запасной мост: церковь São José das Taipas (Rua das Taipas 89, адрес из слабого источника). Рядом с барельефом есть современный монумент Souto de Moura (2009, DN): уточнить название и использовать как ориентир. [16.10.2026] Кандидат на картинку записан в листе «Картинки» (файл ещё не скачан). Вид и кадрирование не проверялись. [16.10.2026] Правки владельца: новый хук; история и «Подробнее» больше не дублируют друг друга. | U12: =IF($A12="",0,IFERROR(MATCH($A12,Тексты!$A$1:$A$61,0),0)) -> 12 | V12: =IF($A12="",0,IFERROR(MATCH($A12,Места!$A$1:$A$61,0),0)) -> 12 | W12: =IF($A12="","",IF(COUNTIF($A$2:$A$61,$A12)>1,"дубль id; ","")&IF($B12="","нет эпохи; ","")&IF($C12="","нет уровня; ","")&IF($D12="","нет года; ","")&IF($F12="","нет нити; ","")&IF($H12="","нет важности; ","")&IF($I12="","нет метки; ","")&IF($J12="","нет возраста; ","")&IF($K12="","не указана тяжёлая тема; ","")&IF($M12<IF($C12="frame",2,1),"источников "&$M12&" из "&IF($C12="frame",2,1)&"; ","")&IF($U12=0,"нет строки в «Тексты»; ",IF(INDEX(Тексты!$C$1:$C$61,$U12)=0,"нет крючок EN; ",IF(OR(INDEX(Тексты!$C$1:$C$61,$U12)<1,INDEX(Тексты!$C$1:$C$61,$U12)>12),"крючок EN "&INDEX(Тексты!$C$1:$C$61,$U12)&" сл. (нужно 1–12); ",""))&IF(INDEX(Тексты!$E$1:$E$61,$U12)=0,"нет крючок PT; ",IF(OR(INDEX(Тексты!$E$1:$E$61,$U12)<1,INDEX(Тексты!$E$1:$E$61,$U12)>12),"крючок PT "&INDEX(Тексты!$E$1:$E$61,$U12)&" сл. (нужно 1–12); ",""))&IF(INDEX(Тексты!$O$1:$O$61,$U12)=0,"нет крючок RU; ",IF(OR(INDEX(Тексты!$O$1:$O$61,$U12)<1,INDEX(Тексты!$O$1:$O$61,$U12)>12),"крючок RU "&INDEX(Тексты!$O$1:$O$61,$U12)&" сл. (нужно 1–12); ",""))&IF(INDEX(Тексты!$G$1:$G$61,$U12)=0,"нет история EN; ",IF(OR(INDEX(Тексты!$G$1:$G$61,$U12)<40,INDEX(Тексты!$G$1:$G$61,$U12)>90),"история EN "&INDEX(Тексты!$G$1:$G$61,$U12)&" сл. (нужно 40–90); ",""))&IF(INDEX(Тексты!$I$1:$I$61,$U12)=0,"нет история PT; ",IF(OR(INDEX(Тексты!$I$1:$I$61,$U12)<40,INDEX(Тексты!$I$1:$I$61,$U12)>90),"история PT "&INDEX(Тексты!$I$1:$I$61,$U12)&" сл. (нужно 40–90); ",""))&IF(INDEX(Тексты!$Q$1:$Q$61,$U12)=0,"нет история RU; ",IF(OR(INDEX(Тексты!$Q$1:$Q$61,$U12)<40,INDEX(Тексты!$Q$1:$Q$61,$U12)>90),"история RU "&INDEX(Тексты!$Q$1:$Q$61,$U12)&" сл. (нужно 40–90); ",""))&IF(INDEX(Тексты!$K$1:$K$61,$U12)=0,"нет подробнее EN; ",IF(OR(INDEX(Тексты!$K$1:$K$61,$U12)<1,INDEX(Тексты!$K$1:$K$61,$U12)>250),"подробнее EN "&INDEX(Тексты!$K$1:$K$61,$U12)&" сл. (нужно 1–250); ",""))&IF(INDEX(Тексты!$M$1:$M$61,$U12)=0,"нет подробнее PT; ",IF(OR(INDEX(Тексты!$M$1:$M$61,$U12)<1,INDEX(Тексты!$M$1:$M$61,$U12)>250),"подробнее PT "&INDEX(Тексты!$M$1:$M$61,$U12)&" сл. (нужно 1–250); ",""))&IF(INDEX(Тексты!$S$1:$S$61,$U12)=0,"нет подробнее RU; ",IF(OR(INDEX(Тексты!$S$1:$S$61,$U12)<1,INDEX(Тексты!$S$1:$S$61,$U12)>250),"подробнее RU "&INDEX(Тексты!$S$1:$S$61,$U12)&" сл. (нужно 1–250); ","")))&IF($V12=0,"нет строки в «Места»; ",IF(OR(INDEX(Места!$B$1:$B$61,$V12)="",INDEX(Места!$C$1:$C$61,$V12)="",INDEX(Места!$Q$1:$Q$61,$V12)=""),"нет названия EN/PT/RU; ","")&IF(OR(INDEX(Места!$D$1:$D$61,$V12)="",INDEX(Места!$E$1:$E$61,$V12)="",INDEX(Места!$R$1:$R$61,$V12)=""),"нет slug EN/PT/RU; ","")&IF(INDEX(Места!$K$1:$K$61,$V12)="","нет моста в сегодня; ","")&IF(OR(INDEX(Места!$O$1:$O$61,$V12)="",INDEX(Места!$O$1:$O$61,$V12)="TODO"),"нет сайта моста; ","")&IF(INDEX(Места!$P$1:$P$61,$V12)<>"да","координаты не проверены; ",""))&IF(AND($L12="готово",OR($R12="",$S12="")),"нет рецензента/даты; ","")) -> нет сайта моста; координаты не проверены;
A13: motim-companhia-1757 | B13: pombal-e-terramoto | C13: story | D13: 1757 | E13: Порту 1757: «Да здравствует король! Смерть Компании!» | F13: comida-e-vinho | G13: poder-e-revolta | H13: 2 | I13: documented | J13: 12 | K13: да | L13: черновик | M13: =IF($A13="","",COUNTIFS(Источники!$A$2:$A$200,$A13,Источники!$G$2:$G$200,"нашли")) -> 7 | N13: =IF($A13="","",IF($W13="","OK",$W13)) -> координаты не проверены; | O13: douro-1756 | T13: Исправление к списку из документа: названия «Motim dos Bordoairos / dos Bêbados» не нашли; в научных текстах «Motim da Companhia» (англ. Tipplers' Revolt), «Motins do Porto de 1757». Казнено 17 человек (13 мужчин, 4 женщины), а не 25. Число 17 и дата 14 октября из блога Executed Today: нужен научный источник (Ribeiro da Silva, «Os motins do Porto de 1757», 1990). «Первая в мире демаркированная винная зона»: формулировка из того же блога, в тексте «часто называют». Мост: Real Companhia Velha (Vila Nova de Gaia), та же Компания: название и адрес не проверены. Пограничные столбы (marcos de feitoria) в текст не включены: нет источника. Тяжёлая тема: казни. Вторая нить на усмотрение владельца. [Перепроверка 16.10.2026] Мост заменён на реальный: 17•56 Museu & Enoteca (Cais de Gaia), название по году основания. Координаты и часы проверить. Источников стало 7. [16.10.2026] Правки владельца: основание Компании и камни выделены в карточку douro-1756; здесь остался бунт. Новый хук. | U13: =IF($A13="",0,IFERROR(MATCH($A13,Тексты!$A$1:$A$61,0),0)) -> 13 | V13: =IF($A13="",0,IFERROR(MATCH($A13,Места!$A$1:$A$61,0),0)) -> 13 | W13: =IF($A13="","",IF(COUNTIF($A$2:$A$61,$A13)>1,"дубль id; ","")&IF($B13="","нет эпохи; ","")&IF($C13="","нет уровня; ","")&IF($D13="","нет года; ","")&IF($F13="","нет нити; ","")&IF($H13="","нет важности; ","")&IF($I13="","нет метки; ","")&IF($J13="","нет возраста; ","")&IF($K13="","не указана тяжёлая тема; ","")&IF($M13<IF($C13="frame",2,1),"источников "&$M13&" из "&IF($C13="frame",2,1)&"; ","")&IF($U13=0,"нет строки в «Тексты»; ",IF(INDEX(Тексты!$C$1:$C$61,$U13)=0,"нет крючок EN; ",IF(OR(INDEX(Тексты!$C$1:$C$61,$U13)<1,INDEX(Тексты!$C$1:$C$61,$U13)>12),"крючок EN "&INDEX(Тексты!$C$1:$C$61,$U13)&" сл. (нужно 1–12); ",""))&IF(INDEX(Тексты!$E$1:$E$61,$U13)=0,"нет крючок PT; ",IF(OR(INDEX(Тексты!$E$1:$E$61,$U13)<1,INDEX(Тексты!$E$1:$E$61,$U13)>12),"крючок PT "&INDEX(Тексты!$E$1:$E$61,$U13)&" сл. (нужно 1–12); ",""))&IF(INDEX(Тексты!$O$1:$O$61,$U13)=0,"нет крючок RU; ",IF(OR(INDEX(Тексты!$O$1:$O$61,$U13)<1,INDEX(Тексты!$O$1:$O$61,$U13)>12),"крючок RU "&INDEX(Тексты!$O$1:$O$61,$U13)&" сл. (нужно 1–12); ",""))&IF(INDEX(Тексты!$G$1:$G$61,$U13)=0,"нет история EN; ",IF(OR(INDEX(Тексты!$G$1:$G$61,$U13)<40,INDEX(Тексты!$G$1:$G$61,$U13)>90),"история EN "&INDEX(Тексты!$G$1:$G$61,$U13)&" сл. (нужно 40–90); ",""))&IF(INDEX(Тексты!$I$1:$I$61,$U13)=0,"нет история PT; ",IF(OR(INDEX(Тексты!$I$1:$I$61,$U13)<40,INDEX(Тексты!$I$1:$I$61,$U13)>90),"история PT "&INDEX(Тексты!$I$1:$I$61,$U13)&" сл. (нужно 40–90); ",""))&IF(INDEX(Тексты!$Q$1:$Q$61,$U13)=0,"нет история RU; ",IF(OR(INDEX(Тексты!$Q$1:$Q$61,$U13)<40,INDEX(Тексты!$Q$1:$Q$61,$U13)>90),"история RU "&INDEX(Тексты!$Q$1:$Q$61,$U13)&" сл. (нужно 40–90); ",""))&IF(INDEX(Тексты!$K$1:$K$61,$U13)=0,"нет подробнее EN; ",IF(OR(INDEX(Тексты!$K$1:$K$61,$U13)<1,INDEX(Тексты!$K$1:$K$61,$U13)>250),"подробнее EN "&INDEX(Тексты!$K$1:$K$61,$U13)&" сл. (нужно 1–250); ",""))&IF(INDEX(Тексты!$M$1:$M$61,$U13)=0,"нет подробнее PT; ",IF(OR(INDEX(Тексты!$M$1:$M$61,$U13)<1,INDEX(Тексты!$M$1:$M$61,$U13)>250),"подробнее PT "&INDEX(Тексты!$M$1:$M$61,$U13)&" сл. (нужно 1–250); ",""))&IF(INDEX(Тексты!$S$1:$S$61,$U13)=0,"нет подробнее RU; ",IF(OR(INDEX(Тексты!$S$1:$S$61,$U13)<1,INDEX(Тексты!$S$1:$S$61,$U13)>250),"подробнее RU "&INDEX(Тексты!$S$1:$S$61,$U13)&" сл. (нужно 1–250); ","")))&IF($V13=0,"нет строки в «Места»; ",IF(OR(INDEX(Места!$B$1:$B$61,$V13)="",INDEX(Места!$C$1:$C$61,$V13)="",INDEX(Места!$Q$1:$Q$61,$V13)=""),"нет названия EN/PT/RU; ","")&IF(OR(INDEX(Места!$D$1:$D$61,$V13)="",INDEX(Места!$E$1:$E$61,$V13)="",INDEX(Места!$R$1:$R$61,$V13)=""),"нет slug EN/PT/RU; ","")&IF(INDEX(Места!$K$1:$K$61,$V13)="","нет моста в сегодня; ","")&IF(OR(INDEX(Места!$O$1:$O$61,$V13)="",INDEX(Места!$O$1:$O$61,$V13)="TODO"),"нет сайта моста; ","")&IF(INDEX(Места!$P$1:$P$61,$V13)<>"да","координаты не проверены; ",""))&IF(AND($L13="готово",OR($R13="",$S13="")),"нет рецензента/даты; ","")) -> координаты не проверены;
A14: legiao-portuguesa-1812 | B14: pombal-e-terramoto | C14: story | D14: 1812 | E14: Португальский легион: от Лиссабона до Бородино | F14: gente-como-nos | G14: poder-e-revolta | H14: 2 | I14: documented | J14: 12 | K14: нет | L14: черновик | M14: =IF($A14="","",COUNTIFS(Источники!$A$2:$A$200,$A14,Источники!$G$2:$G$200,"нашли")) -> 5 | N14: =IF($A14="","",IF($W14="","OK",$W14)) -> нет моста в сегодня; нет сайта моста; координаты не проверены; | O14: torres-vedras-1810 | T14: Цифры: 9000 человек (Wikipedia), около 100 оставшихся к 1813 (Infopédia): в источниках разброс, в «Подробнее» оговорка. «Борoдино/Смоленск/Березина/Ваграм» взяты из Wikipedia: нужен второй источник. Моста в сегодня нет: идея Museu Militar de Lisboa, проверить, есть ли экспонаты Легиона. Идея для второй карточки: Gomes Freire de Andrade, заместитель командира Легиона (казнён в 1817 по делу о заговоре, из общих знаний: проверить), связь с Синедрионом 1818 и революцией 1820. Вторая нить на усмотрение владельца. Координаты Бородино приблизительные. [Перепроверка 16.10.2026] Моста по-прежнему нет. Для сверки с карточкой 1815–1817: Gomes Freire де Andrade (казнён в 1817) связан с этим же Легионом. [16.10.2026] Правки владельца: новый хук; слово «лучшие» из истории убрано (в моих проверках не подтвердилось). | U14: =IF($A14="",0,IFERROR(MATCH($A14,Тексты!$A$1:$A$61,0),0)) -> 14 | V14: =IF($A14="",0,IFERROR(MATCH($A14,Места!$A$1:$A$61,0),0)) -> 14 | W14: =IF($A14="","",IF(COUNTIF($A$2:$A$61,$A14)>1,"дубль id; ","")&IF($B14="","нет эпохи; ","")&IF($C14="","нет уровня; ","")&IF($D14="","нет года; ","")&IF($F14="","нет нити; ","")&IF($H14="","нет важности; ","")&IF($I14="","нет метки; ","")&IF($J14="","нет возраста; ","")&IF($K14="","не указана тяжёлая тема; ","")&IF($M14<IF($C14="frame",2,1),"источников "&$M14&" из "&IF($C14="frame",2,1)&"; ","")&IF($U14=0,"нет строки в «Тексты»; ",IF(INDEX(Тексты!$C$1:$C$61,$U14)=0,"нет крючок EN; ",IF(OR(INDEX(Тексты!$C$1:$C$61,$U14)<1,INDEX(Тексты!$C$1:$C$61,$U14)>12),"крючок EN "&INDEX(Тексты!$C$1:$C$61,$U14)&" сл. (нужно 1–12); ",""))&IF(INDEX(Тексты!$E$1:$E$61,$U14)=0,"нет крючок PT; ",IF(OR(INDEX(Тексты!$E$1:$E$61,$U14)<1,INDEX(Тексты!$E$1:$E$61,$U14)>12),"крючок PT "&INDEX(Тексты!$E$1:$E$61,$U14)&" сл. (нужно 1–12); ",""))&IF(INDEX(Тексты!$O$1:$O$61,$U14)=0,"нет крючок RU; ",IF(OR(INDEX(Тексты!$O$1:$O$61,$U14)<1,INDEX(Тексты!$O$1:$O$61,$U14)>12),"крючок RU "&INDEX(Тексты!$O$1:$O$61,$U14)&" сл. (нужно 1–12); ",""))&IF(INDEX(Тексты!$G$1:$G$61,$U14)=0,"нет история EN; ",IF(OR(INDEX(Тексты!$G$1:$G$61,$U14)<40,INDEX(Тексты!$G$1:$G$61,$U14)>90),"история EN "&INDEX(Тексты!$G$1:$G$61,$U14)&" сл. (нужно 40–90); ",""))&IF(INDEX(Тексты!$I$1:$I$61,$U14)=0,"нет история PT; ",IF(OR(INDEX(Тексты!$I$1:$I$61,$U14)<40,INDEX(Тексты!$I$1:$I$61,$U14)>90),"история PT "&INDEX(Тексты!$I$1:$I$61,$U14)&" сл. (нужно 40–90); ",""))&IF(INDEX(Тексты!$Q$1:$Q$61,$U14)=0,"нет история RU; ",IF(OR(INDEX(Тексты!$Q$1:$Q$61,$U14)<40,INDEX(Тексты!$Q$1:$Q$61,$U14)>90),"история RU "&INDEX(Тексты!$Q$1:$Q$61,$U14)&" сл. (нужно 40–90); ",""))&IF(INDEX(Тексты!$K$1:$K$61,$U14)=0,"нет подробнее EN; ",IF(OR(INDEX(Тексты!$K$1:$K$61,$U14)<1,INDEX(Тексты!$K$1:$K$61,$U14)>250),"подробнее EN "&INDEX(Тексты!$K$1:$K$61,$U14)&" сл. (нужно 1–250); ",""))&IF(INDEX(Тексты!$M$1:$M$61,$U14)=0,"нет подробнее PT; ",IF(OR(INDEX(Тексты!$M$1:$M$61,$U14)<1,INDEX(Тексты!$M$1:$M$61,$U14)>250),"подробнее PT "&INDEX(Тексты!$M$1:$M$61,$U14)&" сл. (нужно 1–250); ",""))&IF(INDEX(Тексты!$S$1:$S$61,$U14)=0,"нет подробнее RU; ",IF(OR(INDEX(Тексты!$S$1:$S$61,$U14)<1,INDEX(Тексты!$S$1:$S$61,$U14)>250),"подробнее RU "&INDEX(Тексты!$S$1:$S$61,$U14)&" сл. (нужно 1–250); ","")))&IF($V14=0,"нет строки в «Места»; ",IF(OR(INDEX(Места!$B$1:$B$61,$V14)="",INDEX(Места!$C$1:$C$61,$V14)="",INDEX(Места!$Q$1:$Q$61,$V14)=""),"нет названия EN/PT/RU; ","")&IF(OR(INDEX(Места!$D$1:$D$61,$V14)="",INDEX(Места!$E$1:$E$61,$V14)="",INDEX(Места!$R$1:$R$61,$V14)=""),"нет slug EN/PT/RU; ","")&IF(INDEX(Места!$K$1:$K$61,$V14)="","нет моста в сегодня; ","")&IF(OR(INDEX(Места!$O$1:$O$61,$V14)="",INDEX(Места!$O$1:$O$61,$V14)="TODO"),"нет сайта моста; ","")&IF(INDEX(Места!$P$1:$P$61,$V14)<>"да","координаты не проверены; ",""))&IF(AND($L14="готово",OR($R14="",$S14="")),"нет рецензента/даты; ","")) -> нет моста в сегодня; нет сайта моста; координаты не проверены;
M15: =IF($A15="","",COUNTIFS(Источники!$A$2:$A$200,$A15,Источники!$G$2:$G$200,"нашли")) | N15: =IF($A15="","",IF($W15="","OK",$W15)) | U15: =IF($A15="",0,IFERROR(MATCH($A15,Тексты!$A$1:$A$61,0),0)) -> 0 | V15: =IF($A15="",0,IFERROR(MATCH($A15,Места!$A$1:$A$61,0),0)) -> 0 | W15: =IF($A15="","",IF(COUNTIF($A$2:$A$61,$A15)>1,"дубль id; ","")&IF($B15="","нет эпохи; ","")&IF($C15="","нет уровня; ","")&IF($D15="","нет года; ","")&IF($F15="","нет нити; ","")&IF($H15="","нет важности; ","")&IF($I15="","нет метки; ","")&IF($J15="","нет возраста; ","")&IF($K15="","не указана тяжёлая тема; ","")&IF($M15<IF($C15="frame",2,1),"источников "&$M15&" из "&IF($C15="frame",2,1)&"; ","")&IF($U15=0,"нет строки в «Тексты»; ",IF(INDEX(Тексты!$C$1:$C$61,$U15)=0,"нет крючок EN; ",IF(OR(INDEX(Тексты!$C$1:$C$61,$U15)<1,INDEX(Тексты!$C$1:$C$61,$U15)>12),"крючок EN "&INDEX(Тексты!$C$1:$C$61,$U15)&" сл. (нужно 1–12); ",""))&IF(INDEX(Тексты!$E$1:$E$61,$U15)=0,"нет крючок PT; ",IF(OR(INDEX(Тексты!$E$1:$E$61,$U15)<1,INDEX(Тексты!$E$1:$E$61,$U15)>12),"крючок PT "&INDEX(Тексты!$E$1:$E$61,$U15)&" сл. (нужно 1–12); ",""))&IF(INDEX(Тексты!$O$1:$O$61,$U15)=0,"нет крючок RU; ",IF(OR(INDEX(Тексты!$O$1:$O$61,$U15)<1,INDEX(Тексты!$O$1:$O$61,$U15)>12),"крючок RU "&INDEX(Тексты!$O$1:$O$61,$U15)&" сл. (нужно 1–12); ",""))&IF(INDEX(Тексты!$G$1:$G$61,$U15)=0,"нет история EN; ",IF(OR(INDEX(Тексты!$G$1:$G$61,$U15)<40,INDEX(Тексты!$G$1:$G$61,$U15)>90),"история EN "&INDEX(Тексты!$G$1:$G$61,$U15)&" сл. (нужно 40–90); ",""))&IF(INDEX(Тексты!$I$1:$I$61,$U15)=0,"нет история PT; ",IF(OR(INDEX(Тексты!$I$1:$I$61,$U15)<40,INDEX(Тексты!$I$1:$I$61,$U15)>90),"история PT "&INDEX(Тексты!$I$1:$I$61,$U15)&" сл. (нужно 40–90); ",""))&IF(INDEX(Тексты!$Q$1:$Q$61,$U15)=0,"нет история RU; ",IF(OR(INDEX(Тексты!$Q$1:$Q$61,$U15)<40,INDEX(Тексты!$Q$1:$Q$61,$U15)>90),"история RU "&INDEX(Тексты!$Q$1:$Q$61,$U15)&" сл. (нужно 40–90); ",""))&IF(INDEX(Тексты!$K$1:$K$61,$U15)=0,"нет подробнее EN; ",IF(OR(INDEX(Тексты!$K$1:$K$61,$U15)<1,INDEX(Тексты!$K$1:$K$61,$U15)>250),"подробнее EN "&INDEX(Тексты!$K$1:$K$61,$U15)&" сл. (нужно 1–250); ",""))&IF(INDEX(Тексты!$M$1:$M$61,$U15)=0,"нет подробнее PT; ",IF(OR(INDEX(Тексты!$M$1:$M$61,$U15)<1,INDEX(Тексты!$M$1:$M$61,$U15)>250),"подробнее PT "&INDEX(Тексты!$M$1:$M$61,$U15)&" сл. (нужно 1–250); ",""))&IF(INDEX(Тексты!$S$1:$S$61,$U15)=0,"нет подробнее RU; ",IF(OR(INDEX(Тексты!$S$1:$S$61,$U15)<1,INDEX(Тексты!$S$1:$S$61,$U15)>250),"подробнее RU "&INDEX(Тексты!$S$1:$S$61,$U15)&" сл. (нужно 1–250); ","")))&IF($V15=0,"нет строки в «Места»; ",IF(OR(INDEX(Места!$B$1:$B$61,$V15)="",INDEX(Места!$C$1:$C$61,$V15)="",INDEX(Места!$Q$1:$Q$61,$V15)=""),"нет названия EN/PT/RU; ","")&IF(OR(INDEX(Места!$D$1:$D$61,$V15)="",INDEX(Места!$E$1:$E$61,$V15)="",INDEX(Места!$R$1:$R$61,$V15)=""),"нет slug EN/PT/RU; ","")&IF(INDEX(Места!$K$1:$K$61,$V15)="","нет моста в сегодня; ","")&IF(OR(INDEX(Места!$O$1:$O$61,$V15)="",INDEX(Места!$O$1:$O$61,$V15)="TODO"),"нет сайта моста; ","")&IF(INDEX(Места!$P$1:$P$61,$V15)<>"да","координаты не проверены; ",""))&IF(AND($L15="готово",OR($R15="",$S15="")),"нет рецензента/даты; ",""))
M16: =IF($A16="","",COUNTIFS(Источники!$A$2:$A$200,$A16,Источники!$G$2:$G$200,"нашли")) | N16: =IF($A16="","",IF($W16="","OK",$W16)) | U16: =IF($A16="",0,IFERROR(MATCH($A16,Тексты!$A$1:$A$61,0),0)) -> 0 | V16: =IF($A16="",0,IFERROR(MATCH($A16,Места!$A$1:$A$61,0),0)) -> 0 | W16: =IF($A16="","",IF(COUNTIF($A$2:$A$61,$A16)>1,"дубль id; ","")&IF($B16="","нет эпохи; ","")&IF($C16="","нет уровня; ","")&IF($D16="","нет года; ","")&IF($F16="","нет нити; ","")&IF($H16="","нет важности; ","")&IF($I16="","нет метки; ","")&IF($J16="","нет возраста; ","")&IF($K16="","не указана тяжёлая тема; ","")&IF($M16<IF($C16="frame",2,1),"источников "&$M16&" из "&IF($C16="frame",2,1)&"; ","")&IF($U16=0,"нет строки в «Тексты»; ",IF(INDEX(Тексты!$C$1:$C$61,$U16)=0,"нет крючок EN; ",IF(OR(INDEX(Тексты!$C$1:$C$61,$U16)<1,INDEX(Тексты!$C$1:$C$61,$U16)>12),"крючок EN "&INDEX(Тексты!$C$1:$C$61,$U16)&" сл. (нужно 1–12); ",""))&IF(INDEX(Тексты!$E$1:$E$61,$U16)=0,"нет крючок PT; ",IF(OR(INDEX(Тексты!$E$1:$E$61,$U16)<1,INDEX(Тексты!$E$1:$E$61,$U16)>12),"крючок PT "&INDEX(Тексты!$E$1:$E$61,$U16)&" сл. (нужно 1–12); ",""))&IF(INDEX(Тексты!$O$1:$O$61,$U16)=0,"нет крючок RU; ",IF(OR(INDEX(Тексты!$O$1:$O$61,$U16)<1,INDEX(Тексты!$O$1:$O$61,$U16)>12),"крючок RU "&INDEX(Тексты!$O$1:$O$61,$U16)&" сл. (нужно 1–12); ",""))&IF(INDEX(Тексты!$G$1:$G$61,$U16)=0,"нет история EN; ",IF(OR(INDEX(Тексты!$G$1:$G$61,$U16)<40,INDEX(Тексты!$G$1:$G$61,$U16)>90),"история EN "&INDEX(Тексты!$G$1:$G$61,$U16)&" сл. (нужно 40–90); ",""))&IF(INDEX(Тексты!$I$1:$I$61,$U16)=0,"нет история PT; ",IF(OR(INDEX(Тексты!$I$1:$I$61,$U16)<40,INDEX(Тексты!$I$1:$I$61,$U16)>90),"история PT "&INDEX(Тексты!$I$1:$I$61,$U16)&" сл. (нужно 40–90); ",""))&IF(INDEX(Тексты!$Q$1:$Q$61,$U16)=0,"нет история RU; ",IF(OR(INDEX(Тексты!$Q$1:$Q$61,$U16)<40,INDEX(Тексты!$Q$1:$Q$61,$U16)>90),"история RU "&INDEX(Тексты!$Q$1:$Q$61,$U16)&" сл. (нужно 40–90); ",""))&IF(INDEX(Тексты!$K$1:$K$61,$U16)=0,"нет подробнее EN; ",IF(OR(INDEX(Тексты!$K$1:$K$61,$U16)<1,INDEX(Тексты!$K$1:$K$61,$U16)>250),"подробнее EN "&INDEX(Тексты!$K$1:$K$61,$U16)&" сл. (нужно 1–250); ",""))&IF(INDEX(Тексты!$M$1:$M$61,$U16)=0,"нет подробнее PT; ",IF(OR(INDEX(Тексты!$M$1:$M$61,$U16)<1,INDEX(Тексты!$M$1:$M$61,$U16)>250),"подробнее PT "&INDEX(Тексты!$M$1:$M$61,$U16)&" сл. (нужно 1–250); ",""))&IF(INDEX(Тексты!$S$1:$S$61,$U16)=0,"нет подробнее RU; ",IF(OR(INDEX(Тексты!$S$1:$S$61,$U16)<1,INDEX(Тексты!$S$1:$S$61,$U16)>250),"подробнее RU "&INDEX(Тексты!$S$1:$S$61,$U16)&" сл. (нужно 1–250); ","")))&IF($V16=0,"нет строки в «Места»; ",IF(OR(INDEX(Места!$B$1:$B$61,$V16)="",INDEX(Места!$C$1:$C$61,$V16)="",INDEX(Места!$Q$1:$Q$61,$V16)=""),"нет названия EN/PT/RU; ","")&IF(OR(INDEX(Места!$D$1:$D$61,$V16)="",INDEX(Места!$E$1:$E$61,$V16)="",INDEX(Места!$R$1:$R$61,$V16)=""),"нет slug EN/PT/RU; ","")&IF(INDEX(Места!$K$1:$K$61,$V16)="","нет моста в сегодня; ","")&IF(OR(INDEX(Места!$O$1:$O$61,$V16)="",INDEX(Места!$O$1:$O$61,$V16)="TODO"),"нет сайта моста; ","")&IF(INDEX(Места!$P$1:$P$61,$V16)<>"да","координаты не проверены; ",""))&IF(AND($L16="готово",OR($R16="",$S16="")),"нет рецензента/даты; ",""))
M17: =IF($A17="","",COUNTIFS(Источники!$A$2:$A$200,$A17,Источники!$G$2:$G$200,"нашли")) | N17: =IF($A17="","",IF($W17="","OK",$W17)) | U17: =IF($A17="",0,IFERROR(MATCH($A17,Тексты!$A$1:$A$61,0),0)) -> 0 | V17: =IF($A17="",0,IFERROR(MATCH($A17,Места!$A$1:$A$61,0),0)) -> 0 | W17: =IF($A17="","",IF(COUNTIF($A$2:$A$61,$A17)>1,"дубль id; ","")&IF($B17="","нет эпохи; ","")&IF($C17="","нет уровня; ","")&IF($D17="","нет года; ","")&IF($F17="","нет нити; ","")&IF($H17="","нет важности; ","")&IF($I17="","нет метки; ","")&IF($J17="","нет возраста; ","")&IF($K17="","не указана тяжёлая тема; ","")&IF($M17<IF($C17="frame",2,1),"источников "&$M17&" из "&IF($C17="frame",2,1)&"; ","")&IF($U17=0,"нет строки в «Тексты»; ",IF(INDEX(Тексты!$C$1:$C$61,$U17)=0,"нет крючок EN; ",IF(OR(INDEX(Тексты!$C$1:$C$61,$U17)<1,INDEX(Тексты!$C$1:$C$61,$U17)>12),"крючок EN "&INDEX(Тексты!$C$1:$C$61,$U17)&" сл. (нужно 1–12); ",""))&IF(INDEX(Тексты!$E$1:$E$61,$U17)=0,"нет крючок PT; ",IF(OR(INDEX(Тексты!$E$1:$E$61,$U17)<1,INDEX(Тексты!$E$1:$E$61,$U17)>12),"крючок PT "&INDEX(Тексты!$E$1:$E$61,$U17)&" сл. (нужно 1–12); ",""))&IF(INDEX(Тексты!$O$1:$O$61,$U17)=0,"нет крючок RU; ",IF(OR(INDEX(Тексты!$O$1:$O$61,$U17)<1,INDEX(Тексты!$O$1:$O$61,$U17)>12),"крючок RU "&INDEX(Тексты!$O$1:$O$61,$U17)&" сл. (нужно 1–12); ",""))&IF(INDEX(Тексты!$G$1:$G$61,$U17)=0,"нет история EN; ",IF(OR(INDEX(Тексты!$G$1:$G$61,$U17)<40,INDEX(Тексты!$G$1:$G$61,$U17)>90),"история EN "&INDEX(Тексты!$G$1:$G$61,$U17)&" сл. (нужно 40–90); ",""))&IF(INDEX(Тексты!$I$1:$I$61,$U17)=0,"нет история PT; ",IF(OR(INDEX(Тексты!$I$1:$I$61,$U17)<40,INDEX(Тексты!$I$1:$I$61,$U17)>90),"история PT "&INDEX(Тексты!$I$1:$I$61,$U17)&" сл. (нужно 40–90); ",""))&IF(INDEX(Тексты!$Q$1:$Q$61,$U17)=0,"нет история RU; ",IF(OR(INDEX(Тексты!$Q$1:$Q$61,$U17)<40,INDEX(Тексты!$Q$1:$Q$61,$U17)>90),"история RU "&INDEX(Тексты!$Q$1:$Q$61,$U17)&" сл. (нужно 40–90); ",""))&IF(INDEX(Тексты!$K$1:$K$61,$U17)=0,"нет подробнее EN; ",IF(OR(INDEX(Тексты!$K$1:$K$61,$U17)<1,INDEX(Тексты!$K$1:$K$61,$U17)>250),"подробнее EN "&INDEX(Тексты!$K$1:$K$61,$U17)&" сл. (нужно 1–250); ",""))&IF(INDEX(Тексты!$M$1:$M$61,$U17)=0,"нет подробнее PT; ",IF(OR(INDEX(Тексты!$M$1:$M$61,$U17)<1,INDEX(Тексты!$M$1:$M$61,$U17)>250),"подробнее PT "&INDEX(Тексты!$M$1:$M$61,$U17)&" сл. (нужно 1–250); ",""))&IF(INDEX(Тексты!$S$1:$S$61,$U17)=0,"нет подробнее RU; ",IF(OR(INDEX(Тексты!$S$1:$S$61,$U17)<1,INDEX(Тексты!$S$1:$S$61,$U17)>250),"подробнее RU "&INDEX(Тексты!$S$1:$S$61,$U17)&" сл. (нужно 1–250); ","")))&IF($V17=0,"нет строки в «Места»; ",IF(OR(INDEX(Места!$B$1:$B$61,$V17)="",INDEX(Места!$C$1:$C$61,$V17)="",INDEX(Места!$Q$1:$Q$61,$V17)=""),"нет названия EN/PT/RU; ","")&IF(OR(INDEX(Места!$D$1:$D$61,$V17)="",INDEX(Места!$E$1:$E$61,$V17)="",INDEX(Места!$R$1:$R$61,$V17)=""),"нет slug EN/PT/RU; ","")&IF(INDEX(Места!$K$1:$K$61,$V17)="","нет моста в сегодня; ","")&IF(OR(INDEX(Места!$O$1:$O$61,$V17)="",INDEX(Места!$O$1:$O$61,$V17)="TODO"),"нет сайта моста; ","")&IF(INDEX(Места!$P$1:$P$61,$V17)<>"да","координаты не проверены; ",""))&IF(AND($L17="готово",OR($R17="",$S17="")),"нет рецензента/даты; ",""))
M18: =IF($A18="","",COUNTIFS(Источники!$A$2:$A$200,$A18,Источники!$G$2:$G$200,"нашли")) | N18: =IF($A18="","",IF($W18="","OK",$W18)) | U18: =IF($A18="",0,IFERROR(MATCH($A18,Тексты!$A$1:$A$61,0),0)) -> 0 | V18: =IF($A18="",0,IFERROR(MATCH($A18,Места!$A$1:$A$61,0),0)) -> 0 | W18: =IF($A18="","",IF(COUNTIF($A$2:$A$61,$A18)>1,"дубль id; ","")&IF($B18="","нет эпохи; ","")&IF($C18="","нет уровня; ","")&IF($D18="","нет года; ","")&IF($F18="","нет нити; ","")&IF($H18="","нет важности; ","")&IF($I18="","нет метки; ","")&IF($J18="","нет возраста; ","")&IF($K18="","не указана тяжёлая тема; ","")&IF($M18<IF($C18="frame",2,1),"источников "&$M18&" из "&IF($C18="frame",2,1)&"; ","")&IF($U18=0,"нет строки в «Тексты»; ",IF(INDEX(Тексты!$C$1:$C$61,$U18)=0,"нет крючок EN; ",IF(OR(INDEX(Тексты!$C$1:$C$61,$U18)<1,INDEX(Тексты!$C$1:$C$61,$U18)>12),"крючок EN "&INDEX(Тексты!$C$1:$C$61,$U18)&" сл. (нужно 1–12); ",""))&IF(INDEX(Тексты!$E$1:$E$61,$U18)=0,"нет крючок PT; ",IF(OR(INDEX(Тексты!$E$1:$E$61,$U18)<1,INDEX(Тексты!$E$1:$E$61,$U18)>12),"крючок PT "&INDEX(Тексты!$E$1:$E$61,$U18)&" сл. (нужно 1–12); ",""))&IF(INDEX(Тексты!$O$1:$O$61,$U18)=0,"нет крючок RU; ",IF(OR(INDEX(Тексты!$O$1:$O$61,$U18)<1,INDEX(Тексты!$O$1:$O$61,$U18)>12),"крючок RU "&INDEX(Тексты!$O$1:$O$61,$U18)&" сл. (нужно 1–12); ",""))&IF(INDEX(Тексты!$G$1:$G$61,$U18)=0,"нет история EN; ",IF(OR(INDEX(Тексты!$G$1:$G$61,$U18)<40,INDEX(Тексты!$G$1:$G$61,$U18)>90),"история EN "&INDEX(Тексты!$G$1:$G$61,$U18)&" сл. (нужно 40–90); ",""))&IF(INDEX(Тексты!$I$1:$I$61,$U18)=0,"нет история PT; ",IF(OR(INDEX(Тексты!$I$1:$I$61,$U18)<40,INDEX(Тексты!$I$1:$I$61,$U18)>90),"история PT "&INDEX(Тексты!$I$1:$I$61,$U18)&" сл. (нужно 40–90); ",""))&IF(INDEX(Тексты!$Q$1:$Q$61,$U18)=0,"нет история RU; ",IF(OR(INDEX(Тексты!$Q$1:$Q$61,$U18)<40,INDEX(Тексты!$Q$1:$Q$61,$U18)>90),"история RU "&INDEX(Тексты!$Q$1:$Q$61,$U18)&" сл. (нужно 40–90); ",""))&IF(INDEX(Тексты!$K$1:$K$61,$U18)=0,"нет подробнее EN; ",IF(OR(INDEX(Тексты!$K$1:$K$61,$U18)<1,INDEX(Тексты!$K$1:$K$61,$U18)>250),"подробнее EN "&INDEX(Тексты!$K$1:$K$61,$U18)&" сл. (нужно 1–250); ",""))&IF(INDEX(Тексты!$M$1:$M$61,$U18)=0,"нет подробнее PT; ",IF(OR(INDEX(Тексты!$M$1:$M$61,$U18)<1,INDEX(Тексты!$M$1:$M$61,$U18)>250),"подробнее PT "&INDEX(Тексты!$M$1:$M$61,$U18)&" сл. (нужно 1–250); ",""))&IF(INDEX(Тексты!$S$1:$S$61,$U18)=0,"нет подробнее RU; ",IF(OR(INDEX(Тексты!$S$1:$S$61,$U18)<1,INDEX(Тексты!$S$1:$S$61,$U18)>250),"подробнее RU "&INDEX(Тексты!$S$1:$S$61,$U18)&" сл. (нужно 1–250); ","")))&IF($V18=0,"нет строки в «Места»; ",IF(OR(INDEX(Места!$B$1:$B$61,$V18)="",INDEX(Места!$C$1:$C$61,$V18)="",INDEX(Места!$Q$1:$Q$61,$V18)=""),"нет названия EN/PT/RU; ","")&IF(OR(INDEX(Места!$D$1:$D$61,$V18)="",INDEX(Места!$E$1:$E$61,$V18)="",INDEX(Места!$R$1:$R$61,$V18)=""),"нет slug EN/PT/RU; ","")&IF(INDEX(Места!$K$1:$K$61,$V18)="","нет моста в сегодня; ","")&IF(OR(INDEX(Места!$O$1:$O$61,$V18)="",INDEX(Места!$O$1:$O$61,$V18)="TODO"),"нет сайта моста; ","")&IF(INDEX(Места!$P$1:$P$61,$V18)<>"да","координаты не проверены; ",""))&IF(AND($L18="готово",OR($R18="",$S18="")),"нет рецензента/даты; ",""))
M19: =IF($A19="","",COUNTIFS(Источники!$A$2:$A$200,$A19,Источники!$G$2:$G$200,"нашли")) | N19: =IF($A19="","",IF($W19="","OK",$W19)) | U19: =IF($A19="",0,IFERROR(MATCH($A19,Тексты!$A$1:$A$61,0),0)) -> 0 | V19: =IF($A19="",0,IFERROR(MATCH($A19,Места!$A$1:$A$61,0),0)) -> 0 | W19: =IF($A19="","",IF(COUNTIF($A$2:$A$61,$A19)>1,"дубль id; ","")&IF($B19="","нет эпохи; ","")&IF($C19="","нет уровня; ","")&IF($D19="","нет года; ","")&IF($F19="","нет нити; ","")&IF($H19="","нет важности; ","")&IF($I19="","нет метки; ","")&IF($J19="","нет возраста; ","")&IF($K19="","не указана тяжёлая тема; ","")&IF($M19<IF($C19="frame",2,1),"источников "&$M19&" из "&IF($C19="frame",2,1)&"; ","")&IF($U19=0,"нет строки в «Тексты»; ",IF(INDEX(Тексты!$C$1:$C$61,$U19)=0,"нет крючок EN; ",IF(OR(INDEX(Тексты!$C$1:$C$61,$U19)<1,INDEX(Тексты!$C$1:$C$61,$U19)>12),"крючок EN "&INDEX(Тексты!$C$1:$C$61,$U19)&" сл. (нужно 1–12); ",""))&IF(INDEX(Тексты!$E$1:$E$61,$U19)=0,"нет крючок PT; ",IF(OR(INDEX(Тексты!$E$1:$E$61,$U19)<1,INDEX(Тексты!$E$1:$E$61,$U19)>12),"крючок PT "&INDEX(Тексты!$E$1:$E$61,$U19)&" сл. (нужно 1–12); ",""))&IF(INDEX(Тексты!$O$1:$O$61,$U19)=0,"нет крючок RU; ",IF(OR(INDEX(Тексты!$O$1:$O$61,$U19)<1,INDEX(Тексты!$O$1:$O$61,$U19)>12),"крючок RU "&INDEX(Тексты!$O$1:$O$61,$U19)&" сл. (нужно 1–12); ",""))&IF(INDEX(Тексты!$G$1:$G$61,$U19)=0,"нет история EN; ",IF(OR(INDEX(Тексты!$G$1:$G$61,$U19)<40,INDEX(Тексты!$G$1:$G$61,$U19)>90),"история EN "&INDEX(Тексты!$G$1:$G$61,$U19)&" сл. (нужно 40–90); ",""))&IF(INDEX(Тексты!$I$1:$I$61,$U19)=0,"нет история PT; ",IF(OR(INDEX(Тексты!$I$1:$I$61,$U19)<40,INDEX(Тексты!$I$1:$I$61,$U19)>90),"история PT "&INDEX(Тексты!$I$1:$I$61,$U19)&" сл. (нужно 40–90); ",""))&IF(INDEX(Тексты!$Q$1:$Q$61,$U19)=0,"нет история RU; ",IF(OR(INDEX(Тексты!$Q$1:$Q$61,$U19)<40,INDEX(Тексты!$Q$1:$Q$61,$U19)>90),"история RU "&INDEX(Тексты!$Q$1:$Q$61,$U19)&" сл. (нужно 40–90); ",""))&IF(INDEX(Тексты!$K$1:$K$61,$U19)=0,"нет подробнее EN; ",IF(OR(INDEX(Тексты!$K$1:$K$61,$U19)<1,INDEX(Тексты!$K$1:$K$61,$U19)>250),"подробнее EN "&INDEX(Тексты!$K$1:$K$61,$U19)&" сл. (нужно 1–250); ",""))&IF(INDEX(Тексты!$M$1:$M$61,$U19)=0,"нет подробнее PT; ",IF(OR(INDEX(Тексты!$M$1:$M$61,$U19)<1,INDEX(Тексты!$M$1:$M$61,$U19)>250),"подробнее PT "&INDEX(Тексты!$M$1:$M$61,$U19)&" сл. (нужно 1–250); ",""))&IF(INDEX(Тексты!$S$1:$S$61,$U19)=0,"нет подробнее RU; ",IF(OR(INDEX(Тексты!$S$1:$S$61,$U19)<1,INDEX(Тексты!$S$1:$S$61,$U19)>250),"подробнее RU "&INDEX(Тексты!$S$1:$S$61,$U19)&" сл. (нужно 1–250); ","")))&IF($V19=0,"нет строки в «Места»; ",IF(OR(INDEX(Места!$B$1:$B$61,$V19)="",INDEX(Места!$C$1:$C$61,$V19)="",INDEX(Места!$Q$1:$Q$61,$V19)=""),"нет названия EN/PT/RU; ","")&IF(OR(INDEX(Места!$D$1:$D$61,$V19)="",INDEX(Места!$E$1:$E$61,$V19)="",INDEX(Места!$R$1:$R$61,$V19)=""),"нет slug EN/PT/RU; ","")&IF(INDEX(Места!$K$1:$K$61,$V19)="","нет моста в сегодня; ","")&IF(OR(INDEX(Места!$O$1:$O$61,$V19)="",INDEX(Места!$O$1:$O$61,$V19)="TODO"),"нет сайта моста; ","")&IF(INDEX(Места!$P$1:$P$61,$V19)<>"да","координаты не проверены; ",""))&IF(AND($L19="готово",OR($R19="",$S19="")),"нет рецензента/даты; ",""))
M20: =IF($A20="","",COUNTIFS(Источники!$A$2:$A$200,$A20,Источники!$G$2:$G$200,"нашли")) | N20: =IF($A20="","",IF($W20="","OK",$W20)) | U20: =IF($A20="",0,IFERROR(MATCH($A20,Тексты!$A$1:$A$61,0),0)) -> 0 | V20: =IF($A20="",0,IFERROR(MATCH($A20,Места!$A$1:$A$61,0),0)) -> 0 | W20: =IF($A20="","",IF(COUNTIF($A$2:$A$61,$A20)>1,"дубль id; ","")&IF($B20="","нет эпохи; ","")&IF($C20="","нет уровня; ","")&IF($D20="","нет года; ","")&IF($F20="","нет нити; ","")&IF($H20="","нет важности; ","")&IF($I20="","нет метки; ","")&IF($J20="","нет возраста; ","")&IF($K20="","не указана тяжёлая тема; ","")&IF($M20<IF($C20="frame",2,1),"источников "&$M20&" из "&IF($C20="frame",2,1)&"; ","")&IF($U20=0,"нет строки в «Тексты»; ",IF(INDEX(Тексты!$C$1:$C$61,$U20)=0,"нет крючок EN; ",IF(OR(INDEX(Тексты!$C$1:$C$61,$U20)<1,INDEX(Тексты!$C$1:$C$61,$U20)>12),"крючок EN "&INDEX(Тексты!$C$1:$C$61,$U20)&" сл. (нужно 1–12); ",""))&IF(INDEX(Тексты!$E$1:$E$61,$U20)=0,"нет крючок PT; ",IF(OR(INDEX(Тексты!$E$1:$E$61,$U20)<1,INDEX(Тексты!$E$1:$E$61,$U20)>12),"крючок PT "&INDEX(Тексты!$E$1:$E$61,$U20)&" сл. (нужно 1–12); ",""))&IF(INDEX(Тексты!$O$1:$O$61,$U20)=0,"нет крючок RU; ",IF(OR(INDEX(Тексты!$O$1:$O$61,$U20)<1,INDEX(Тексты!$O$1:$O$61,$U20)>12),"крючок RU "&INDEX(Тексты!$O$1:$O$61,$U20)&" сл. (нужно 1–12); ",""))&IF(INDEX(Тексты!$G$1:$G$61,$U20)=0,"нет история EN; ",IF(OR(INDEX(Тексты!$G$1:$G$61,$U20)<40,INDEX(Тексты!$G$1:$G$61,$U20)>90),"история EN "&INDEX(Тексты!$G$1:$G$61,$U20)&" сл. (нужно 40–90); ",""))&IF(INDEX(Тексты!$I$1:$I$61,$U20)=0,"нет история PT; ",IF(OR(INDEX(Тексты!$I$1:$I$61,$U20)<40,INDEX(Тексты!$I$1:$I$61,$U20)>90),"история PT "&INDEX(Тексты!$I$1:$I$61,$U20)&" сл. (нужно 40–90); ",""))&IF(INDEX(Тексты!$Q$1:$Q$61,$U20)=0,"нет история RU; ",IF(OR(INDEX(Тексты!$Q$1:$Q$61,$U20)<40,INDEX(Тексты!$Q$1:$Q$61,$U20)>90),"история RU "&INDEX(Тексты!$Q$1:$Q$61,$U20)&" сл. (нужно 40–90); ",""))&IF(INDEX(Тексты!$K$1:$K$61,$U20)=0,"нет подробнее EN; ",IF(OR(INDEX(Тексты!$K$1:$K$61,$U20)<1,INDEX(Тексты!$K$1:$K$61,$U20)>250),"подробнее EN "&INDEX(Тексты!$K$1:$K$61,$U20)&" сл. (нужно 1–250); ",""))&IF(INDEX(Тексты!$M$1:$M$61,$U20)=0,"нет подробнее PT; ",IF(OR(INDEX(Тексты!$M$1:$M$61,$U20)<1,INDEX(Тексты!$M$1:$M$61,$U20)>250),"подробнее PT "&INDEX(Тексты!$M$1:$M$61,$U20)&" сл. (нужно 1–250); ",""))&IF(INDEX(Тексты!$S$1:$S$61,$U20)=0,"нет подробнее RU; ",IF(OR(INDEX(Тексты!$S$1:$S$61,$U20)<1,INDEX(Тексты!$S$1:$S$61,$U20)>250),"подробнее RU "&INDEX(Тексты!$S$1:$S$61,$U20)&" сл. (нужно 1–250); ","")))&IF($V20=0,"нет строки в «Места»; ",IF(OR(INDEX(Места!$B$1:$B$61,$V20)="",INDEX(Места!$C$1:$C$61,$V20)="",INDEX(Места!$Q$1:$Q$61,$V20)=""),"нет названия EN/PT/RU; ","")&IF(OR(INDEX(Места!$D$1:$D$61,$V20)="",INDEX(Места!$E$1:$E$61,$V20)="",INDEX(Места!$R$1:$R$61,$V20)=""),"нет slug EN/PT/RU; ","")&IF(INDEX(Места!$K$1:$K$61,$V20)="","нет моста в сегодня; ","")&IF(OR(INDEX(Места!$O$1:$O$61,$V20)="",INDEX(Места!$O$1:$O$61,$V20)="TODO"),"нет сайта моста; ","")&IF(INDEX(Места!$P$1:$P$61,$V20)<>"да","координаты не проверены; ",""))&IF(AND($L20="готово",OR($R20="",$S20="")),"нет рецензента/даты; ",""))
M21: =IF($A21="","",COUNTIFS(Источники!$A$2:$A$200,$A21,Источники!$G$2:$G$200,"нашли")) | N21: =IF($A21="","",IF($W21="","OK",$W21)) | U21: =IF($A21="",0,IFERROR(MATCH($A21,Тексты!$A$1:$A$61,0),0)) -> 0 | V21: =IF($A21="",0,IFERROR(MATCH($A21,Места!$A$1:$A$61,0),0)) -> 0 | W21: =IF($A21="","",IF(COUNTIF($A$2:$A$61,$A21)>1,"дубль id; ","")&IF($B21="","нет эпохи; ","")&IF($C21="","нет уровня; ","")&IF($D21="","нет года; ","")&IF($F21="","нет нити; ","")&IF($H21="","нет важности; ","")&IF($I21="","нет метки; ","")&IF($J21="","нет возраста; ","")&IF($K21="","не указана тяжёлая тема; ","")&IF($M21<IF($C21="frame",2,1),"источников "&$M21&" из "&IF($C21="frame",2,1)&"; ","")&IF($U21=0,"нет строки в «Тексты»; ",IF(INDEX(Тексты!$C$1:$C$61,$U21)=0,"нет крючок EN; ",IF(OR(INDEX(Тексты!$C$1:$C$61,$U21)<1,INDEX(Тексты!$C$1:$C$61,$U21)>12),"крючок EN "&INDEX(Тексты!$C$1:$C$61,$U21)&" сл. (нужно 1–12); ",""))&IF(INDEX(Тексты!$E$1:$E$61,$U21)=0,"нет крючок PT; ",IF(OR(INDEX(Тексты!$E$1:$E$61,$U21)<1,INDEX(Тексты!$E$1:$E$61,$U21)>12),"крючок PT "&INDEX(Тексты!$E$1:$E$61,$U21)&" сл. (нужно 1–12); ",""))&IF(INDEX(Тексты!$O$1:$O$61,$U21)=0,"нет крючок RU; ",IF(OR(INDEX(Тексты!$O$1:$O$61,$U21)<1,INDEX(Тексты!$O$1:$O$61,$U21)>12),"крючок RU "&INDEX(Тексты!$O$1:$O$61,$U21)&" сл. (нужно 1–12); ",""))&IF(INDEX(Тексты!$G$1:$G$61,$U21)=0,"нет история EN; ",IF(OR(INDEX(Тексты!$G$1:$G$61,$U21)<40,INDEX(Тексты!$G$1:$G$61,$U21)>90),"история EN "&INDEX(Тексты!$G$1:$G$61,$U21)&" сл. (нужно 40–90); ",""))&IF(INDEX(Тексты!$I$1:$I$61,$U21)=0,"нет история PT; ",IF(OR(INDEX(Тексты!$I$1:$I$61,$U21)<40,INDEX(Тексты!$I$1:$I$61,$U21)>90),"история PT "&INDEX(Тексты!$I$1:$I$61,$U21)&" сл. (нужно 40–90); ",""))&IF(INDEX(Тексты!$Q$1:$Q$61,$U21)=0,"нет история RU; ",IF(OR(INDEX(Тексты!$Q$1:$Q$61,$U21)<40,INDEX(Тексты!$Q$1:$Q$61,$U21)>90),"история RU "&INDEX(Тексты!$Q$1:$Q$61,$U21)&" сл. (нужно 40–90); ",""))&IF(INDEX(Тексты!$K$1:$K$61,$U21)=0,"нет подробнее EN; ",IF(OR(INDEX(Тексты!$K$1:$K$61,$U21)<1,INDEX(Тексты!$K$1:$K$61,$U21)>250),"подробнее EN "&INDEX(Тексты!$K$1:$K$61,$U21)&" сл. (нужно 1–250); ",""))&IF(INDEX(Тексты!$M$1:$M$61,$U21)=0,"нет подробнее PT; ",IF(OR(INDEX(Тексты!$M$1:$M$61,$U21)<1,INDEX(Тексты!$M$1:$M$61,$U21)>250),"подробнее PT "&INDEX(Тексты!$M$1:$M$61,$U21)&" сл. (нужно 1–250); ",""))&IF(INDEX(Тексты!$S$1:$S$61,$U21)=0,"нет подробнее RU; ",IF(OR(INDEX(Тексты!$S$1:$S$61,$U21)<1,INDEX(Тексты!$S$1:$S$61,$U21)>250),"подробнее RU "&INDEX(Тексты!$S$1:$S$61,$U21)&" сл. (нужно 1–250); ","")))&IF($V21=0,"нет строки в «Места»; ",IF(OR(INDEX(Места!$B$1:$B$61,$V21)="",INDEX(Места!$C$1:$C$61,$V21)="",INDEX(Места!$Q$1:$Q$61,$V21)=""),"нет названия EN/PT/RU; ","")&IF(OR(INDEX(Места!$D$1:$D$61,$V21)="",INDEX(Места!$E$1:$E$61,$V21)="",INDEX(Места!$R$1:$R$61,$V21)=""),"нет slug EN/PT/RU; ","")&IF(INDEX(Места!$K$1:$K$61,$V21)="","нет моста в сегодня; ","")&IF(OR(INDEX(Места!$O$1:$O$61,$V21)="",INDEX(Места!$O$1:$O$61,$V21)="TODO"),"нет сайта моста; ","")&IF(INDEX(Места!$P$1:$P$61,$V21)<>"да","координаты не проверены; ",""))&IF(AND($L21="готово",OR($R21="",$S21="")),"нет рецензента/даты; ",""))
M22: =IF($A22="","",COUNTIFS(Источники!$A$2:$A$200,$A22,Источники!$G$2:$G$200,"нашли")) | N22: =IF($A22="","",IF($W22="","OK",$W22)) | U22: =IF($A22="",0,IFERROR(MATCH($A22,Тексты!$A$1:$A$61,0),0)) -> 0 | V22: =IF($A22="",0,IFERROR(MATCH($A22,Места!$A$1:$A$61,0),0)) -> 0 | W22: =IF($A22="","",IF(COUNTIF($A$2:$A$61,$A22)>1,"дубль id; ","")&IF($B22="","нет эпохи; ","")&IF($C22="","нет уровня; ","")&IF($D22="","нет года; ","")&IF($F22="","нет нити; ","")&IF($H22="","нет важности; ","")&IF($I22="","нет метки; ","")&IF($J22="","нет возраста; ","")&IF($K22="","не указана тяжёлая тема; ","")&IF($M22<IF($C22="frame",2,1),"источников "&$M22&" из "&IF($C22="frame",2,1)&"; ","")&IF($U22=0,"нет строки в «Тексты»; ",IF(INDEX(Тексты!$C$1:$C$61,$U22)=0,"нет крючок EN; ",IF(OR(INDEX(Тексты!$C$1:$C$61,$U22)<1,INDEX(Тексты!$C$1:$C$61,$U22)>12),"крючок EN "&INDEX(Тексты!$C$1:$C$61,$U22)&" сл. (нужно 1–12); ",""))&IF(INDEX(Тексты!$E$1:$E$61,$U22)=0,"нет крючок PT; ",IF(OR(INDEX(Тексты!$E$1:$E$61,$U22)<1,INDEX(Тексты!$E$1:$E$61,$U22)>12),"крючок PT "&INDEX(Тексты!$E$1:$E$61,$U22)&" сл. (нужно 1–12); ",""))&IF(INDEX(Тексты!$O$1:$O$61,$U22)=0,"нет крючок RU; ",IF(OR(INDEX(Тексты!$O$1:$O$61,$U22)<1,INDEX(Тексты!$O$1:$O$61,$U22)>12),"крючок RU "&INDEX(Тексты!$O$1:$O$61,$U22)&" сл. (нужно 1–12); ",""))&IF(INDEX(Тексты!$G$1:$G$61,$U22)=0,"нет история EN; ",IF(OR(INDEX(Тексты!$G$1:$G$61,$U22)<40,INDEX(Тексты!$G$1:$G$61,$U22)>90),"история EN "&INDEX(Тексты!$G$1:$G$61,$U22)&" сл. (нужно 40–90); ",""))&IF(INDEX(Тексты!$I$1:$I$61,$U22)=0,"нет история PT; ",IF(OR(INDEX(Тексты!$I$1:$I$61,$U22)<40,INDEX(Тексты!$I$1:$I$61,$U22)>90),"история PT "&INDEX(Тексты!$I$1:$I$61,$U22)&" сл. (нужно 40–90); ",""))&IF(INDEX(Тексты!$Q$1:$Q$61,$U22)=0,"нет история RU; ",IF(OR(INDEX(Тексты!$Q$1:$Q$61,$U22)<40,INDEX(Тексты!$Q$1:$Q$61,$U22)>90),"история RU "&INDEX(Тексты!$Q$1:$Q$61,$U22)&" сл. (нужно 40–90); ",""))&IF(INDEX(Тексты!$K$1:$K$61,$U22)=0,"нет подробнее EN; ",IF(OR(INDEX(Тексты!$K$1:$K$61,$U22)<1,INDEX(Тексты!$K$1:$K$61,$U22)>250),"подробнее EN "&INDEX(Тексты!$K$1:$K$61,$U22)&" сл. (нужно 1–250); ",""))&IF(INDEX(Тексты!$M$1:$M$61,$U22)=0,"нет подробнее PT; ",IF(OR(INDEX(Тексты!$M$1:$M$61,$U22)<1,INDEX(Тексты!$M$1:$M$61,$U22)>250),"подробнее PT "&INDEX(Тексты!$M$1:$M$61,$U22)&" сл. (нужно 1–250); ",""))&IF(INDEX(Тексты!$S$1:$S$61,$U22)=0,"нет подробнее RU; ",IF(OR(INDEX(Тексты!$S$1:$S$61,$U22)<1,INDEX(Тексты!$S$1:$S$61,$U22)>250),"подробнее RU "&INDEX(Тексты!$S$1:$S$61,$U22)&" сл. (нужно 1–250); ","")))&IF($V22=0,"нет строки в «Места»; ",IF(OR(INDEX(Места!$B$1:$B$61,$V22)="",INDEX(Места!$C$1:$C$61,$V22)="",INDEX(Места!$Q$1:$Q$61,$V22)=""),"нет названия EN/PT/RU; ","")&IF(OR(INDEX(Места!$D$1:$D$61,$V22)="",INDEX(Места!$E$1:$E$61,$V22)="",INDEX(Места!$R$1:$R$61,$V22)=""),"нет slug EN/PT/RU; ","")&IF(INDEX(Места!$K$1:$K$61,$V22)="","нет моста в сегодня; ","")&IF(OR(INDEX(Места!$O$1:$O$61,$V22)="",INDEX(Места!$O$1:$O$61,$V22)="TODO"),"нет сайта моста; ","")&IF(INDEX(Места!$P$1:$P$61,$V22)<>"да","координаты не проверены; ",""))&IF(AND($L22="готово",OR($R22="",$S22="")),"нет рецензента/даты; ",""))
M23: =IF($A23="","",COUNTIFS(Источники!$A$2:$A$200,$A23,Источники!$G$2:$G$200,"нашли")) | N23: =IF($A23="","",IF($W23="","OK",$W23)) | U23: =IF($A23="",0,IFERROR(MATCH($A23,Тексты!$A$1:$A$61,0),0)) -> 0 | V23: =IF($A23="",0,IFERROR(MATCH($A23,Места!$A$1:$A$61,0),0)) -> 0 | W23: =IF($A23="","",IF(COUNTIF($A$2:$A$61,$A23)>1,"дубль id; ","")&IF($B23="","нет эпохи; ","")&IF($C23="","нет уровня; ","")&IF($D23="","нет года; ","")&IF($F23="","нет нити; ","")&IF($H23="","нет важности; ","")&IF($I23="","нет метки; ","")&IF($J23="","нет возраста; ","")&IF($K23="","не указана тяжёлая тема; ","")&IF($M23<IF($C23="frame",2,1),"источников "&$M23&" из "&IF($C23="frame",2,1)&"; ","")&IF($U23=0,"нет строки в «Тексты»; ",IF(INDEX(Тексты!$C$1:$C$61,$U23)=0,"нет крючок EN; ",IF(OR(INDEX(Тексты!$C$1:$C$61,$U23)<1,INDEX(Тексты!$C$1:$C$61,$U23)>12),"крючок EN "&INDEX(Тексты!$C$1:$C$61,$U23)&" сл. (нужно 1–12); ",""))&IF(INDEX(Тексты!$E$1:$E$61,$U23)=0,"нет крючок PT; ",IF(OR(INDEX(Тексты!$E$1:$E$61,$U23)<1,INDEX(Тексты!$E$1:$E$61,$U23)>12),"крючок PT "&INDEX(Тексты!$E$1:$E$61,$U23)&" сл. (нужно 1–12); ",""))&IF(INDEX(Тексты!$O$1:$O$61,$U23)=0,"нет крючок RU; ",IF(OR(INDEX(Тексты!$O$1:$O$61,$U23)<1,INDEX(Тексты!$O$1:$O$61,$U23)>12),"крючок RU "&INDEX(Тексты!$O$1:$O$61,$U23)&" сл. (нужно 1–12); ",""))&IF(INDEX(Тексты!$G$1:$G$61,$U23)=0,"нет история EN; ",IF(OR(INDEX(Тексты!$G$1:$G$61,$U23)<40,INDEX(Тексты!$G$1:$G$61,$U23)>90),"история EN "&INDEX(Тексты!$G$1:$G$61,$U23)&" сл. (нужно 40–90); ",""))&IF(INDEX(Тексты!$I$1:$I$61,$U23)=0,"нет история PT; ",IF(OR(INDEX(Тексты!$I$1:$I$61,$U23)<40,INDEX(Тексты!$I$1:$I$61,$U23)>90),"история PT "&INDEX(Тексты!$I$1:$I$61,$U23)&" сл. (нужно 40–90); ",""))&IF(INDEX(Тексты!$Q$1:$Q$61,$U23)=0,"нет история RU; ",IF(OR(INDEX(Тексты!$Q$1:$Q$61,$U23)<40,INDEX(Тексты!$Q$1:$Q$61,$U23)>90),"история RU "&INDEX(Тексты!$Q$1:$Q$61,$U23)&" сл. (нужно 40–90); ",""))&IF(INDEX(Тексты!$K$1:$K$61,$U23)=0,"нет подробнее EN; ",IF(OR(INDEX(Тексты!$K$1:$K$61,$U23)<1,INDEX(Тексты!$K$1:$K$61,$U23)>250),"подробнее EN "&INDEX(Тексты!$K$1:$K$61,$U23)&" сл. (нужно 1–250); ",""))&IF(INDEX(Тексты!$M$1:$M$61,$U23)=0,"нет подробнее PT; ",IF(OR(INDEX(Тексты!$M$1:$M$61,$U23)<1,INDEX(Тексты!$M$1:$M$61,$U23)>250),"подробнее PT "&INDEX(Тексты!$M$1:$M$61,$U23)&" сл. (нужно 1–250); ",""))&IF(INDEX(Тексты!$S$1:$S$61,$U23)=0,"нет подробнее RU; ",IF(OR(INDEX(Тексты!$S$1:$S$61,$U23)<1,INDEX(Тексты!$S$1:$S$61,$U23)>250),"подробнее RU "&INDEX(Тексты!$S$1:$S$61,$U23)&" сл. (нужно 1–250); ","")))&IF($V23=0,"нет строки в «Места»; ",IF(OR(INDEX(Места!$B$1:$B$61,$V23)="",INDEX(Места!$C$1:$C$61,$V23)="",INDEX(Места!$Q$1:$Q$61,$V23)=""),"нет названия EN/PT/RU; ","")&IF(OR(INDEX(Места!$D$1:$D$61,$V23)="",INDEX(Места!$E$1:$E$61,$V23)="",INDEX(Места!$R$1:$R$61,$V23)=""),"нет slug EN/PT/RU; ","")&IF(INDEX(Места!$K$1:$K$61,$V23)="","нет моста в сегодня; ","")&IF(OR(INDEX(Места!$O$1:$O$61,$V23)="",INDEX(Места!$O$1:$O$61,$V23)="TODO"),"нет сайта моста; ","")&IF(INDEX(Места!$P$1:$P$61,$V23)<>"да","координаты не проверены; ",""))&IF(AND($L23="готово",OR($R23="",$S23="")),"нет рецензента/даты; ",""))
M24: =IF($A24="","",COUNTIFS(Источники!$A$2:$A$200,$A24,Источники!$G$2:$G$200,"нашли")) | N24: =IF($A24="","",IF($W24="","OK",$W24)) | U24: =IF($A24="",0,IFERROR(MATCH($A24,Тексты!$A$1:$A$61,0),0)) -> 0 | V24: =IF($A24="",0,IFERROR(MATCH($A24,Места!$A$1:$A$61,0),0)) -> 0 | W24: =IF($A24="","",IF(COUNTIF($A$2:$A$61,$A24)>1,"дубль id; ","")&IF($B24="","нет эпохи; ","")&IF($C24="","нет уровня; ","")&IF($D24="","нет года; ","")&IF($F24="","нет нити; ","")&IF($H24="","нет важности; ","")&IF($I24="","нет метки; ","")&IF($J24="","нет возраста; ","")&IF($K24="","не указана тяжёлая тема; ","")&IF($M24<IF($C24="frame",2,1),"источников "&$M24&" из "&IF($C24="frame",2,1)&"; ","")&IF($U24=0,"нет строки в «Тексты»; ",IF(INDEX(Тексты!$C$1:$C$61,$U24)=0,"нет крючок EN; ",IF(OR(INDEX(Тексты!$C$1:$C$61,$U24)<1,INDEX(Тексты!$C$1:$C$61,$U24)>12),"крючок EN "&INDEX(Тексты!$C$1:$C$61,$U24)&" сл. (нужно 1–12); ",""))&IF(INDEX(Тексты!$E$1:$E$61,$U24)=0,"нет крючок PT; ",IF(OR(INDEX(Тексты!$E$1:$E$61,$U24)<1,INDEX(Тексты!$E$1:$E$61,$U24)>12),"крючок PT "&INDEX(Тексты!$E$1:$E$61,$U24)&" сл. (нужно 1–12); ",""))&IF(INDEX(Тексты!$O$1:$O$61,$U24)=0,"нет крючок RU; ",IF(OR(INDEX(Тексты!$O$1:$O$61,$U24)<1,INDEX(Тексты!$O$1:$O$61,$U24)>12),"крючок RU "&INDEX(Тексты!$O$1:$O$61,$U24)&" сл. (нужно 1–12); ",""))&IF(INDEX(Тексты!$G$1:$G$61,$U24)=0,"нет история EN; ",IF(OR(INDEX(Тексты!$G$1:$G$61,$U24)<40,INDEX(Тексты!$G$1:$G$61,$U24)>90),"история EN "&INDEX(Тексты!$G$1:$G$61,$U24)&" сл. (нужно 40–90); ",""))&IF(INDEX(Тексты!$I$1:$I$61,$U24)=0,"нет история PT; ",IF(OR(INDEX(Тексты!$I$1:$I$61,$U24)<40,INDEX(Тексты!$I$1:$I$61,$U24)>90),"история PT "&INDEX(Тексты!$I$1:$I$61,$U24)&" сл. (нужно 40–90); ",""))&IF(INDEX(Тексты!$Q$1:$Q$61,$U24)=0,"нет история RU; ",IF(OR(INDEX(Тексты!$Q$1:$Q$61,$U24)<40,INDEX(Тексты!$Q$1:$Q$61,$U24)>90),"история RU "&INDEX(Тексты!$Q$1:$Q$61,$U24)&" сл. (нужно 40–90); ",""))&IF(INDEX(Тексты!$K$1:$K$61,$U24)=0,"нет подробнее EN; ",IF(OR(INDEX(Тексты!$K$1:$K$61,$U24)<1,INDEX(Тексты!$K$1:$K$61,$U24)>250),"подробнее EN "&INDEX(Тексты!$K$1:$K$61,$U24)&" сл. (нужно 1–250); ",""))&IF(INDEX(Тексты!$M$1:$M$61,$U24)=0,"нет подробнее PT; ",IF(OR(INDEX(Тексты!$M$1:$M$61,$U24)<1,INDEX(Тексты!$M$1:$M$61,$U24)>250),"подробнее PT "&INDEX(Тексты!$M$1:$M$61,$U24)&" сл. (нужно 1–250); ",""))&IF(INDEX(Тексты!$S$1:$S$61,$U24)=0,"нет подробнее RU; ",IF(OR(INDEX(Тексты!$S$1:$S$61,$U24)<1,INDEX(Тексты!$S$1:$S$61,$U24)>250),"подробнее RU "&INDEX(Тексты!$S$1:$S$61,$U24)&" сл. (нужно 1–250); ","")))&IF($V24=0,"нет строки в «Места»; ",IF(OR(INDEX(Места!$B$1:$B$61,$V24)="",INDEX(Места!$C$1:$C$61,$V24)="",INDEX(Места!$Q$1:$Q$61,$V24)=""),"нет названия EN/PT/RU; ","")&IF(OR(INDEX(Места!$D$1:$D$61,$V24)="",INDEX(Места!$E$1:$E$61,$V24)="",INDEX(Места!$R$1:$R$61,$V24)=""),"нет slug EN/PT/RU; ","")&IF(INDEX(Места!$K$1:$K$61,$V24)="","нет моста в сегодня; ","")&IF(OR(INDEX(Места!$O$1:$O$61,$V24)="",INDEX(Места!$O$1:$O$61,$V24)="TODO"),"нет сайта моста; ","")&IF(INDEX(Места!$P$1:$P$61,$V24)<>"да","координаты не проверены; ",""))&IF(AND($L24="готово",OR($R24="",$S24="")),"нет рецензента/даты; ",""))
M25: =IF($A25="","",COUNTIFS(Источники!$A$2:$A$200,$A25,Источники!$G$2:$G$200,"нашли")) | N25: =IF($A25="","",IF($W25="","OK",$W25)) | U25: =IF($A25="",0,IFERROR(MATCH($A25,Тексты!$A$1:$A$61,0),0)) -> 0 | V25: =IF($A25="",0,IFERROR(MATCH($A25,Места!$A$1:$A$61,0),0)) -> 0 | W25: =IF($A25="","",IF(COUNTIF($A$2:$A$61,$A25)>1,"дубль id; ","")&IF($B25="","нет эпохи; ","")&IF($C25="","нет уровня; ","")&IF($D25="","нет года; ","")&IF($F25="","нет нити; ","")&IF($H25="","нет важности; ","")&IF($I25="","нет метки; ","")&IF($J25="","нет возраста; ","")&IF($K25="","не указана тяжёлая тема; ","")&IF($M25<IF($C25="frame",2,1),"источников "&$M25&" из "&IF($C25="frame",2,1)&"; ","")&IF($U25=0,"нет строки в «Тексты»; ",IF(INDEX(Тексты!$C$1:$C$61,$U25)=0,"нет крючок EN; ",IF(OR(INDEX(Тексты!$C$1:$C$61,$U25)<1,INDEX(Тексты!$C$1:$C$61,$U25)>12),"крючок EN "&INDEX(Тексты!$C$1:$C$61,$U25)&" сл. (нужно 1–12); ",""))&IF(INDEX(Тексты!$E$1:$E$61,$U25)=0,"нет крючок PT; ",IF(OR(INDEX(Тексты!$E$1:$E$61,$U25)<1,INDEX(Тексты!$E$1:$E$61,$U25)>12),"крючок PT "&INDEX(Тексты!$E$1:$E$61,$U25)&" сл. (нужно 1–12); ",""))&IF(INDEX(Тексты!$O$1:$O$61,$U25)=0,"нет крючок RU; ",IF(OR(INDEX(Тексты!$O$1:$O$61,$U25)<1,INDEX(Тексты!$O$1:$O$61,$U25)>12),"крючок RU "&INDEX(Тексты!$O$1:$O$61,$U25)&" сл. (нужно 1–12); ",""))&IF(INDEX(Тексты!$G$1:$G$61,$U25)=0,"нет история EN; ",IF(OR(INDEX(Тексты!$G$1:$G$61,$U25)<40,INDEX(Тексты!$G$1:$G$61,$U25)>90),"история EN "&INDEX(Тексты!$G$1:$G$61,$U25)&" сл. (нужно 40–90); ",""))&IF(INDEX(Тексты!$I$1:$I$61,$U25)=0,"нет история PT; ",IF(OR(INDEX(Тексты!$I$1:$I$61,$U25)<40,INDEX(Тексты!$I$1:$I$61,$U25)>90),"история PT "&INDEX(Тексты!$I$1:$I$61,$U25)&" сл. (нужно 40–90); ",""))&IF(INDEX(Тексты!$Q$1:$Q$61,$U25)=0,"нет история RU; ",IF(OR(INDEX(Тексты!$Q$1:$Q$61,$U25)<40,INDEX(Тексты!$Q$1:$Q$61,$U25)>90),"история RU "&INDEX(Тексты!$Q$1:$Q$61,$U25)&" сл. (нужно 40–90); ",""))&IF(INDEX(Тексты!$K$1:$K$61,$U25)=0,"нет подробнее EN; ",IF(OR(INDEX(Тексты!$K$1:$K$61,$U25)<1,INDEX(Тексты!$K$1:$K$61,$U25)>250),"подробнее EN "&INDEX(Тексты!$K$1:$K$61,$U25)&" сл. (нужно 1–250); ",""))&IF(INDEX(Тексты!$M$1:$M$61,$U25)=0,"нет подробнее PT; ",IF(OR(INDEX(Тексты!$M$1:$M$61,$U25)<1,INDEX(Тексты!$M$1:$M$61,$U25)>250),"подробнее PT "&INDEX(Тексты!$M$1:$M$61,$U25)&" сл. (нужно 1–250); ",""))&IF(INDEX(Тексты!$S$1:$S$61,$U25)=0,"нет подробнее RU; ",IF(OR(INDEX(Тексты!$S$1:$S$61,$U25)<1,INDEX(Тексты!$S$1:$S$61,$U25)>250),"подробнее RU "&INDEX(Тексты!$S$1:$S$61,$U25)&" сл. (нужно 1–250); ","")))&IF($V25=0,"нет строки в «Места»; ",IF(OR(INDEX(Места!$B$1:$B$61,$V25)="",INDEX(Места!$C$1:$C$61,$V25)="",INDEX(Места!$Q$1:$Q$61,$V25)=""),"нет названия EN/PT/RU; ","")&IF(OR(INDEX(Места!$D$1:$D$61,$V25)="",INDEX(Места!$E$1:$E$61,$V25)="",INDEX(Места!$R$1:$R$61,$V25)=""),"нет slug EN/PT/RU; ","")&IF(INDEX(Места!$K$1:$K$61,$V25)="","нет моста в сегодня; ","")&IF(OR(INDEX(Места!$O$1:$O$61,$V25)="",INDEX(Места!$O$1:$O$61,$V25)="TODO"),"нет сайта моста; ","")&IF(INDEX(Места!$P$1:$P$61,$V25)<>"да","координаты не проверены; ",""))&IF(AND($L25="готово",OR($R25="",$S25="")),"нет рецензента/даты; ",""))
M26: =IF($A26="","",COUNTIFS(Источники!$A$2:$A$200,$A26,Источники!$G$2:$G$200,"нашли")) | N26: =IF($A26="","",IF($W26="","OK",$W26)) | U26: =IF($A26="",0,IFERROR(MATCH($A26,Тексты!$A$1:$A$61,0),0)) -> 0 | V26: =IF($A26="",0,IFERROR(MATCH($A26,Места!$A$1:$A$61,0),0)) -> 0 | W26: =IF($A26="","",IF(COUNTIF($A$2:$A$61,$A26)>1,"дубль id; ","")&IF($B26="","нет эпохи; ","")&IF($C26="","нет уровня; ","")&IF($D26="","нет года; ","")&IF($F26="","нет нити; ","")&IF($H26="","нет важности; ","")&IF($I26="","нет метки; ","")&IF($J26="","нет возраста; ","")&IF($K26="","не указана тяжёлая тема; ","")&IF($M26<IF($C26="frame",2,1),"источников "&$M26&" из "&IF($C26="frame",2,1)&"; ","")&IF($U26=0,"нет строки в «Тексты»; ",IF(INDEX(Тексты!$C$1:$C$61,$U26)=0,"нет крючок EN; ",IF(OR(INDEX(Тексты!$C$1:$C$61,$U26)<1,INDEX(Тексты!$C$1:$C$61,$U26)>12),"крючок EN "&INDEX(Тексты!$C$1:$C$61,$U26)&" сл. (нужно 1–12); ",""))&IF(INDEX(Тексты!$E$1:$E$61,$U26)=0,"нет крючок PT; ",IF(OR(INDEX(Тексты!$E$1:$E$61,$U26)<1,INDEX(Тексты!$E$1:$E$61,$U26)>12),"крючок PT "&INDEX(Тексты!$E$1:$E$61,$U26)&" сл. (нужно 1–12); ",""))&IF(INDEX(Тексты!$O$1:$O$61,$U26)=0,"нет крючок RU; ",IF(OR(INDEX(Тексты!$O$1:$O$61,$U26)<1,INDEX(Тексты!$O$1:$O$61,$U26)>12),"крючок RU "&INDEX(Тексты!$O$1:$O$61,$U26)&" сл. (нужно 1–12); ",""))&IF(INDEX(Тексты!$G$1:$G$61,$U26)=0,"нет история EN; ",IF(OR(INDEX(Тексты!$G$1:$G$61,$U26)<40,INDEX(Тексты!$G$1:$G$61,$U26)>90),"история EN "&INDEX(Тексты!$G$1:$G$61,$U26)&" сл. (нужно 40–90); ",""))&IF(INDEX(Тексты!$I$1:$I$61,$U26)=0,"нет история PT; ",IF(OR(INDEX(Тексты!$I$1:$I$61,$U26)<40,INDEX(Тексты!$I$1:$I$61,$U26)>90),"история PT "&INDEX(Тексты!$I$1:$I$61,$U26)&" сл. (нужно 40–90); ",""))&IF(INDEX(Тексты!$Q$1:$Q$61,$U26)=0,"нет история RU; ",IF(OR(INDEX(Тексты!$Q$1:$Q$61,$U26)<40,INDEX(Тексты!$Q$1:$Q$61,$U26)>90),"история RU "&INDEX(Тексты!$Q$1:$Q$61,$U26)&" сл. (нужно 40–90); ",""))&IF(INDEX(Тексты!$K$1:$K$61,$U26)=0,"нет подробнее EN; ",IF(OR(INDEX(Тексты!$K$1:$K$61,$U26)<1,INDEX(Тексты!$K$1:$K$61,$U26)>250),"подробнее EN "&INDEX(Тексты!$K$1:$K$61,$U26)&" сл. (нужно 1–250); ",""))&IF(INDEX(Тексты!$M$1:$M$61,$U26)=0,"нет подробнее PT; ",IF(OR(INDEX(Тексты!$M$1:$M$61,$U26)<1,INDEX(Тексты!$M$1:$M$61,$U26)>250),"подробнее PT "&INDEX(Тексты!$M$1:$M$61,$U26)&" сл. (нужно 1–250); ",""))&IF(INDEX(Тексты!$S$1:$S$61,$U26)=0,"нет подробнее RU; ",IF(OR(INDEX(Тексты!$S$1:$S$61,$U26)<1,INDEX(Тексты!$S$1:$S$61,$U26)>250),"подробнее RU "&INDEX(Тексты!$S$1:$S$61,$U26)&" сл. (нужно 1–250); ","")))&IF($V26=0,"нет строки в «Места»; ",IF(OR(INDEX(Места!$B$1:$B$61,$V26)="",INDEX(Места!$C$1:$C$61,$V26)="",INDEX(Места!$Q$1:$Q$61,$V26)=""),"нет названия EN/PT/RU; ","")&IF(OR(INDEX(Места!$D$1:$D$61,$V26)="",INDEX(Места!$E$1:$E$61,$V26)="",INDEX(Места!$R$1:$R$61,$V26)=""),"нет slug EN/PT/RU; ","")&IF(INDEX(Места!$K$1:$K$61,$V26)="","нет моста в сегодня; ","")&IF(OR(INDEX(Места!$O$1:$O$61,$V26)="",INDEX(Места!$O$1:$O$61,$V26)="TODO"),"нет сайта моста; ","")&IF(INDEX(Места!$P$1:$P$61,$V26)<>"да","координаты не проверены; ",""))&IF(AND($L26="готово",OR($R26="",$S26="")),"нет рецензента/даты; ",""))
... M61: =IF($A61="","",COUNTIFS(Источники!$A$2:$A$200,$A61,Источники!$G$2:$G$200,"нашли")) | N61: =IF($A61="","",IF($W61="","OK",$W61)) | U61: =IF($A61="",0,IFERROR(MATCH($A61,Тексты!$A$1:$A$61,0),0)) -> 0 | V61: =IF($A61="",0,IFERROR(MATCH($A61,Места!$A$1:$A$61,0),0)) -> 0 | W61: =IF($A61="","",IF(COUNTIF($A$2:$A$61,$A61)>1,"дубль id; ","")&IF($B61="","нет эпохи; ","")&IF($C61="","нет уровня; ","")&IF($D61="","нет года; ","")&IF($F61="","нет нити; ","")&IF($H61="","нет важности; ","")&IF($I61="","нет метки; ","")&IF($J61="","нет возраста; ","")&IF($K61="","не указана тяжёлая тема; ","")&IF($M61<IF($C61="frame",2,1),"источников "&$M61&" из "&IF($C61="frame",2,1)&"; ","")&IF($U61=0,"нет строки в «Тексты»; ",IF(INDEX(Тексты!$C$1:$C$61,$U61)=0,"нет крючок EN; ",IF(OR(INDEX(Тексты!$C$1:$C$61,$U61)<1,INDEX(Тексты!$C$1:$C$61,$U61)>12),"крючок EN "&INDEX(Тексты!$C$1:$C$61,$U61)&" сл. (нужно 1–12); ",""))&IF(INDEX(Тексты!$E$1:$E$61,$U61)=0,"нет крючок PT; ",IF(OR(INDEX(Тексты!$E$1:$E$61,$U61)<1,INDEX(Тексты!$E$1:$E$61,$U61)>12),"крючок PT "&INDEX(Тексты!$E$1:$E$61,$U61)&" сл. (нужно 1–12); ",""))&IF(INDEX(Тексты!$O$1:$O$61,$U61)=0,"нет крючок RU; ",IF(OR(INDEX(Тексты!$O$1:$O$61,$U61)<1,INDEX(Тексты!$O$1:$O$61,$U61)>12),"крючок RU "&INDEX(Тексты!$O$1:$O$61,$U61)&" сл. (нужно 1–12); ",""))&IF(INDEX(Тексты!$G$1:$G$61,$U61)=0,"нет история EN; ",IF(OR(INDEX(Тексты!$G$1:$G$61,$U61)<40,INDEX(Тексты!$G$1:$G$61,$U61)>90),"история EN "&INDEX(Тексты!$G$1:$G$61,$U61)&" сл. (нужно 40–90); ",""))&IF(INDEX(Тексты!$I$1:$I$61,$U61)=0,"нет история PT; ",IF(OR(INDEX(Тексты!$I$1:$I$61,$U61)<40,INDEX(Тексты!$I$1:$I$61,$U61)>90),"история PT "&INDEX(Тексты!$I$1:$I$61,$U61)&" сл. (нужно 40–90); ",""))&IF(INDEX(Тексты!$Q$1:$Q$61,$U61)=0,"нет история RU; ",IF(OR(INDEX(Тексты!$Q$1:$Q$61,$U61)<40,INDEX(Тексты!$Q$1:$Q$61,$U61)>90),"история RU "&INDEX(Тексты!$Q$1:$Q$61,$U61)&" сл. (нужно 40–90); ",""))&IF(INDEX(Тексты!$K$1:$K$61,$U61)=0,"нет подробнее EN; ",IF(OR(INDEX(Тексты!$K$1:$K$61,$U61)<1,INDEX(Тексты!$K$1:$K$61,$U61)>250),"подробнее EN "&INDEX(Тексты!$K$1:$K$61,$U61)&" сл. (нужно 1–250); ",""))&IF(INDEX(Тексты!$M$1:$M$61,$U61)=0,"нет подробнее PT; ",IF(OR(INDEX(Тексты!$M$1:$M$61,$U61)<1,INDEX(Тексты!$M$1:$M$61,$U61)>250),"подробнее PT "&INDEX(Тексты!$M$1:$M$61,$U61)&" сл. (нужно 1–250); ",""))&IF(INDEX(Тексты!$S$1:$S$61,$U61)=0,"нет подробнее RU; ",IF(OR(INDEX(Тексты!$S$1:$S$61,$U61)<1,INDEX(Тексты!$S$1:$S$61,$U61)>250),"подробнее RU "&INDEX(Тексты!$S$1:$S$61,$U61)&" сл. (нужно 1–250); ","")))&IF($V61=0,"нет строки в «Места»; ",IF(OR(INDEX(Места!$B$1:$B$61,$V61)="",INDEX(Места!$C$1:$C$61,$V61)="",INDEX(Места!$Q$1:$Q$61,$V61)=""),"нет названия EN/PT/RU; ","")&IF(OR(INDEX(Места!$D$1:$D$61,$V61)="",INDEX(Места!$E$1:$E$61,$V61)="",INDEX(Места!$R$1:$R$61,$V61)=""),"нет slug EN/PT/RU; ","")&IF(INDEX(Места!$K$1:$K$61,$V61)="","нет моста в сегодня; ","")&IF(OR(INDEX(Места!$O$1:$O$61,$V61)="",INDEX(Места!$O$1:$O$61,$V61)="TODO"),"нет сайта моста; ","")&IF(INDEX(Места!$P$1:$P$61,$V61)<>"да","координаты не проверены; ",""))&IF(AND($L61="готово",OR($R61="",$S61="")),"нет рецензента/даты; ",""))

Sheet Тексты
A1: id | B1: Крючок EN (до 12 сл.) | C1: сл. | D1: Крючок PT (до 12 сл.) | E1: сл. | F1: История EN (40–90 сл.) | G1: сл. | H1: История PT (40–90 сл.) | I1: сл. | J1: Подробнее EN (до 250 сл.) | K1: сл. | L1: Подробнее PT (до 250 сл.) | M1: сл. | N1: Крючок RU (до 12 сл.) | O1: сл. | P1: История RU (40–90 сл.) | Q1: сл. | R1: Подробнее RU (до 250 сл.) | S1: сл. | T1: Идеи / вариант v2 / заметки к тексту | U1: Мои правки (владелец)
A2: cantino-1502 | B2: He came to trade horses. He left with the world. | C2: =IF($A2="","",IF(TRIM(SUBSTITUTE(B2,CHAR(10)," "))="",0,LEN(TRIM(SUBSTITUTE(B2,CHAR(10)," ")))-LEN(SUBSTITUTE(TRIM(SUBSTITUTE(B2,CHAR(10)," "))," ",""))+1)) -> 10 | D2: Veio negociar cavalos. Levou o mundo. | E2: =IF($A2="","",IF(TRIM(SUBSTITUTE(D2,CHAR(10)," "))="",0,LEN(TRIM(SUBSTITUTE(D2,CHAR(10)," ")))-LEN(SUBSTITUTE(TRIM(SUBSTITUTE(D2,CHAR(10)," "))," ",""))+1)) -> 6 | F2: Alberto Cantino arrived in Lisbon in 1501 as a horse dealer. He was really a spy for the Duke of Ferrara, sent to learn what Portuguese captains found. Maps of the new routes were state secrets, yet for 12 gold ducats someone in Lisbon drew him a copy of the world: Brazil, Africa, the way to India. In 1502 he slipped it out of Portugal. In Genoa a mapmaker copied it, and from there its coastlines reached Waldseemüller's 1507 map, the one that gave America its name. | G2: =IF($A2="","",IF(TRIM(SUBSTITUTE(F2,CHAR(10)," "))="",0,LEN(TRIM(SUBSTITUTE(F2,CHAR(10)," ")))-LEN(SUBSTITUTE(TRIM(SUBSTITUTE(F2,CHAR(10)," "))," ",""))+1)) -> 87 | H2: Em 1501, Alberto Cantino chegou a Lisboa a dizer que vinha tratar de cavalos. Era espião do duque de Ferrara e queria saber o que os capitães andavam a descobrir. Os mapas das novas rotas eram segredo de Estado, mas por 12 ducados de ouro alguém em Lisboa desenhou-lhe uma cópia do mundo: o Brasil, África, o caminho para a Índia. Em 1502 levou-a às escondidas. Em Génova copiaram-na, e as suas costas chegaram ao mapa de Waldseemüller, de 1507, o que deu nome à América. | I2: =IF($A2="","",IF(TRIM(SUBSTITUTE(H2,CHAR(10)," "))="",0,LEN(TRIM(SUBSTITUTE(H2,CHAR(10)," ")))-LEN(SUBSTITUTE(TRIM(SUBSTITUTE(H2,CHAR(10)," "))," ",""))+1)) -> 86 | J2: Cantino's letters survive. In one, from 1501, he says he overheard Gaspar Corte-Real report to King Manuel on his voyage to Newfoundland. How he got the map is debated: a bribe to a Portuguese official, a purchase, or both. His price, according to the letters, was 12 gold ducats. The map is huge, over two metres wide, drawn on six sheets of parchment. It already shows the Tordesillas line, the coast of Brazil and the Portuguese fort of Elmina, and it is the earliest surviving chart to place parts of Africa, Brazil and India by latitude. The secret did not last. In 1504 King Manuel banned mapmakers from drawing the African coast beyond São Tomé, but copies were already travelling, and the Cantino map itself aged fast: Caverio's and Waldseemüller's maps soon overtook it. It sat in the library of Ferrara, then Modena. In 1859 a revolt ransacked the palace, and the library director found it in a pork butcher's shop, pasted on a screen. Today it is in Modena's Biblioteca Estense. A copy is kept in Lisbon's Museu de Marinha, in Belém. | K2: =IF($A2="","",IF(TRIM(SUBSTITUTE(J2,CHAR(10)," "))="",0,LEN(TRIM(SUBSTITUTE(J2,CHAR(10)," ")))-LEN(SUBSTITUTE(TRIM(SUBSTITUTE(J2,CHAR(10)," "))," ",""))+1)) -> 183 | L2: As cartas de Cantino sobrevivem. Numa delas, de 1501, diz que ouviu Gaspar Corte-Real fazer ao rei D. Manuel o relato da sua viagem à Terra Nova. Como obteve o mapa é discutido: suborno a um funcionário português, compra, ou as duas coisas. O preço, segundo as cartas, foi de 12 ducados de ouro. O mapa é enorme, com mais de dois metros de largura, desenhado em seis folhas de pergaminho. Já mostra a linha de Tordesilhas, a costa do Brasil e o forte português da Mina, e é a mais antiga carta que se conserva a colocar partes de África, do Brasil e da Índia por latitude. O segredo não durou. Em 1504, D. Manuel proibiu os cartógrafos de desenhar a costa africana para lá de São Tomé, mas as cópias já circulavam, e o próprio mapa de Cantino envelheceu depressa: os mapas de Caverio e de Waldseemüller depressa o ultrapassaram. Ficou na biblioteca de Ferrara e depois em Módena. Em 1859, uma revolta saqueou o palácio, e o diretor da biblioteca encontrou-o num talho, colado num biombo. Hoje está na Biblioteca Estense, em Módena. Há uma cópia no Museu de Marinha, em Belém. | M2: =IF($A2="","",IF(TRIM(SUBSTITUTE(L2,CHAR(10)," "))="",0,LEN(TRIM(SUBSTITUTE(L2,CHAR(10)," ")))-LEN(SUBSTITUTE(TRIM(SUBSTITUTE(L2,CHAR(10)," "))," ",""))+1)) -> 195 | N2: Он приехал торговать лошадьми. Увёз целый мир. | O2: =IF($A2="","",IF(TRIM(SUBSTITUTE(N2,CHAR(10)," "))="",0,LEN(TRIM(SUBSTITUTE(N2,CHAR(10)," ")))-LEN(SUBSTITUTE(TRIM(SUBSTITUTE(N2,CHAR(10)," "))," ",""))+1)) -> 7 | P2: Альберто Кантино приехал в Лиссабон в 1501 году под видом торговца лошадьми. На самом деле он был шпионом герцога Феррарского и выяснял, что находят португальские капитаны. Карты новых маршрутов были государственной тайной, но за 12 золотых дукатов кто-то в Лиссабоне нарисовал ему копию мира: Бразилию, Африку, дорогу в Индию. В 1502 году он тайно вывез её. В Генуе карту скопировал картограф, и оттуда её берега попали на карту Вальдземюллера 1507 года, ту самую, что дала имя Америке. | Q2: =IF($A2="","",IF(TRIM(SUBSTITUTE(P2,CHAR(10)," "))="",0,LEN(TRIM(SUBSTITUTE(P2,CHAR(10)," ")))-LEN(SUBSTITUTE(TRIM(SUBSTITUTE(P2,CHAR(10)," "))," ",""))+1)) -> 77 | R2: Письма Кантино сохранились. В одном из них, 1501 года, он пишет, что подслушал, как Гашпар Кортиреал докладывал королю Мануэлу о плавании к Ньюфаундленду. Как он получил карту, спорят: подкуп португальского чиновника, покупка или и то и другое. Цена, по письмам, 12 золотых дукатов. Карта огромна, свыше двух метров в ширину, нарисована на шести листах пергамента. На ней уже есть линия Тордесильяса, побережье Бразилии и португальская крепость Эльмина, и это древнейшая сохранившаяся карта, где части Африки, Бразилии и Индии размещены по широте. Секрет не продержался. В 1504 году король Мануэл запретил картографам рисовать побережье Африки дальше Сан-Томе, но копии уже разошлись, а сама карта быстро устарела: карты Каверио и Вальдземюллера скоро её превзошли. Она лежала в библиотеке Феррары, потом Модены. В 1859 году мятеж разграбил дворец, и директор библиотеки нашёл её в мясной лавке, наклеенной на ширму. Сегодня она хранится в библиотеке Эстенсе в Модене. Копия лежит в Морском музее Лиссабона, в Белеме. | S2: =IF($A2="","",IF(TRIM(SUBSTITUTE(R2,CHAR(10)," "))="",0,LEN(TRIM(SUBSTITUTE(R2,CHAR(10)," ")))-LEN(SUBSTITUTE(TRIM(SUBSTITUTE(R2,CHAR(10)," "))," ",""))+1)) -> 152 | T2: Запасные крючки: «Portugal guardava o mapa como um segredo. Um negociante de cavalos comprou-o.» / «It cost 12 ducats and ended up as a butcher's curtain.» (последнее: по одному источнику карта служила занавеской, не использовать без второго.) ⚠ В тексте «someone in Lisbon drew him a copy»: источники расходятся (подкуп чиновника, картографа или покупка). [PT переписан отдельно по-европейски, не переводом с EN.] [RU добавлен 16.10.2026: рабочий язык для вычитки, на сайте появится после переключателя.]
A3: rinoceronte-1515 | B3: The king pitted a rhino against an elephant. The elephant fled. | C3: =IF($A3="","",IF(TRIM(SUBSTITUTE(B3,CHAR(10)," "))="",0,LEN(TRIM(SUBSTITUTE(B3,CHAR(10)," ")))-LEN(SUBSTITUTE(TRIM(SUBSTITUTE(B3,CHAR(10)," "))," ",""))+1)) -> 11 | D3: O rei pôs um rinoceronte contra um elefante. O elefante fugiu. | E3: =IF($A3="","",IF(TRIM(SUBSTITUTE(D3,CHAR(10)," "))="",0,LEN(TRIM(SUBSTITUTE(D3,CHAR(10)," ")))-LEN(SUBSTITUTE(TRIM(SUBSTITUTE(D3,CHAR(10)," "))," ",""))+1)) -> 11 | F3: In May 1515 a rhinoceros arrived in Lisbon from India, the first live one in Europe since Roman times. On 3 June King Manuel I decided to test Pliny's claim that elephants and rhinos are bitter enemies. A young elephant was brought out before a crowd. It panicked at the noisy crowd and fled before a single blow was struck. | G3: =IF($A3="","",IF(TRIM(SUBSTITUTE(F3,CHAR(10)," "))="",0,LEN(TRIM(SUBSTITUTE(F3,CHAR(10)," ")))-LEN(SUBSTITUTE(TRIM(SUBSTITUTE(F3,CHAR(10)," "))," ",""))+1)) -> 60 | H3: Em maio de 1515 chegou a Lisboa um rinoceronte vindo da Índia, o primeiro vivo que a Europa via desde os romanos. A 3 de junho, D. Manuel I quis ver se era verdade o que Plínio escrevera: que elefantes e rinocerontes são inimigos de morte. Trouxeram um elefante novo perante a multidão. O bicho assustou-se com o barulho e fugiu antes de a luta começar. | I3: =IF($A3="","",IF(TRIM(SUBSTITUTE(H3,CHAR(10)," "))="",0,LEN(TRIM(SUBSTITUTE(H3,CHAR(10)," ")))-LEN(SUBSTITUTE(TRIM(SUBSTITUTE(H3,CHAR(10)," "))," ",""))+1)) -> 66 | J3: The rhino was a gift from Sultan Muzaffar of Cambay (Gujarat) to the governor Afonso de Albuquerque, who sent it on to Manuel after a four-month voyage. It lived in Europe from 20 May 1515 to January 1516. A year earlier Manuel had sent Pope Leo X an elephant, Hanno, and in December 1515 he decided to send the rhino too. The ship sank in a storm off La Spezia at the end of January 1516, and the animal drowned. Accounts of the body differ: most say it washed ashore and was stuffed and sent on to the Pope, others that the skin went back to Lisbon first. We found no trace of a stuffed rhino today. Albrecht Dürer never saw it: he worked from a sketch and a description from Lisbon, but his woodcut, with its extra horn on the shoulder, became Europe's standard rhinoceros for centuries. In Lisbon, a stone rhinoceros is thought to look out from a corner turret of Belém Tower, built in those same years. | K3: =IF($A3="","",IF(TRIM(SUBSTITUTE(J3,CHAR(10)," "))="",0,LEN(TRIM(SUBSTITUTE(J3,CHAR(10)," ")))-LEN(SUBSTITUTE(TRIM(SUBSTITUTE(J3,CHAR(10)," "))," ",""))+1)) -> 170 | L3: O rinoceronte foi uma oferta do sultão Muzaffar de Cambaia (Guzerate) ao governador Afonso de Albuquerque, que o enviou a D. Manuel depois de quatro meses de viagem. Viveu na Europa de 20 de maio de 1515 a janeiro de 1516. Um ano antes, D. Manuel tinha enviado ao Papa Leão X um elefante, Hanão, e em dezembro de 1515 decidiu enviar também o rinoceronte. O navio afundou-se numa tempestade ao largo de La Spezia, no fim de janeiro de 1516, e o animal morreu afogado. Os relatos sobre o corpo divergem: a maioria diz que deu à costa, foi empalhado e seguiu para o Papa, outros que a pele voltou primeiro a Lisboa. Não encontrámos rasto de nenhum rinoceronte empalhado que exista hoje. Albrecht Dürer nunca o viu: baseou-se no esboço e na descrição de um mercador, mas a sua gravura, com um corno a mais no ombro, passou séculos a ser o rinoceronte da Europa. Em Lisboa, diz-se que há um rinoceronte de pedra numa guarita da Torre de Belém, construída por essa altura. | M3: =IF($A3="","",IF(TRIM(SUBSTITUTE(L3,CHAR(10)," "))="",0,LEN(TRIM(SUBSTITUTE(L3,CHAR(10)," ")))-LEN(SUBSTITUTE(TRIM(SUBSTITUTE(L3,CHAR(10)," "))," ",""))+1)) -> 176 | N3: Король стравил носорога со слоном. Слон убежал. | O3: =IF($A3="","",IF(TRIM(SUBSTITUTE(N3,CHAR(10)," "))="",0,LEN(TRIM(SUBSTITUTE(N3,CHAR(10)," ")))-LEN(SUBSTITUTE(TRIM(SUBSTITUTE(N3,CHAR(10)," "))," ",""))+1)) -> 7 | P3: В мае 1515 года в Лиссабон из Индии привезли носорога, первого живого носорога в Европе со времён римлян. 3 июня король Мануэл I решил проверить слова Плиния о том, что слоны и носороги смертельные враги. К носорогу вывели молодого слона перед толпой. Слон испугался шума и убежал, не дождавшись первого удара. | Q3: =IF($A3="","",IF(TRIM(SUBSTITUTE(P3,CHAR(10)," "))="",0,LEN(TRIM(SUBSTITUTE(P3,CHAR(10)," ")))-LEN(SUBSTITUTE(TRIM(SUBSTITUTE(P3,CHAR(10)," "))," ",""))+1)) -> 51 | R3: Носорог был подарком султана Музаффара Камбейского (Гуджарат) губернатору Афонсу де Албукерки, который переслал его Мануэлу после четырёхмесячного плавания. Он прожил в Европе с 20 мая 1515 года по январь 1516-го. Годом раньше Мануэл отправил папе Льву X слона по имени Ханно, а в декабре 1515 года решил послать и носорога. Корабль затонул в шторм у Специи в конце января 1516 года, и животное утонуло. О судьбе тела рассказывают по-разному: чаще пишут, что его выбросило на берег, из него сделали чучело и отправили папе, но есть версия, что шкуру сначала вернули в Лиссабон. Следов сохранившегося чучела мы не нашли. Альбрехт Дюрер его никогда не видел: он работал по наброску и описанию купца, но его гравюра с лишним рогом на плече на века стала в Европе образцом носорога. В Лиссабоне, как считают, каменный носорог выглядывает с угловой башенки Белемской башни, построенной в те же годы. | S3: =IF($A3="","",IF(TRIM(SUBSTITUTE(R3,CHAR(10)," "))="",0,LEN(TRIM(SUBSTITUTE(R3,CHAR(10)," ")))-LEN(SUBSTITUTE(TRIM(SUBSTITUTE(R3,CHAR(10)," "))," ",""))+1)) -> 143 | T3: Работает. Проверить, нужна ли фраза про Плиния (источник: Crouch Rare Books и Pachyderm, подтвердить у историка). [PT переписан отдельно по-европейски, не переводом с EN.] [RU добавлен 16.10.2026: рабочий язык для вычитки, на сайте появится после переключателя.]
A4: tripeiros-1415 | B4: Porto gave away its meat, kept the tripe, and got a nickname. | C4: =IF($A4="","",IF(TRIM(SUBSTITUTE(B4,CHAR(10)," "))="",0,LEN(TRIM(SUBSTITUTE(B4,CHAR(10)," ")))-LEN(SUBSTITUTE(TRIM(SUBSTITUTE(B4,CHAR(10)," "))," ",""))+1)) -> 12 | D4: O Porto deu a carne, ficou com as tripas, ganhou alcunha. | E4: =IF($A4="","",IF(TRIM(SUBSTITUTE(D4,CHAR(10)," "))="",0,LEN(TRIM(SUBSTITUTE(D4,CHAR(10)," ")))-LEN(SUBSTITUTE(TRIM(SUBSTITUTE(D4,CHAR(10)," "))," ",""))+1)) -> 11 | F4: According to legend, in 1415 Porto's shipyards were secretly building a fleet for Ceuta. Prince Henry, born in the city, turned up unannounced and told the foreman, Master Vaz, the real target. Vaz promised the ships all the city's meat; the people would keep the tripe. Henry called the nickname 'tripe-eaters' an honour. Porto has worn it ever since. | G4: =IF($A4="","",IF(TRIM(SUBSTITUTE(F4,CHAR(10)," "))="",0,LEN(TRIM(SUBSTITUTE(F4,CHAR(10)," ")))-LEN(SUBSTITUTE(TRIM(SUBSTITUTE(F4,CHAR(10)," "))," ",""))+1)) -> 59 | H4: Diz a lenda que, em 1415, os estaleiros do Porto construíam em segredo uma armada para Ceuta. O infante D. Henrique, nascido na cidade, apareceu sem avisar e contou ao mestre Vaz o verdadeiro destino. Vaz prometeu toda a carne da cidade aos navios; o povo ficava com as tripas. O infante disse que a alcunha de «tripeiros» era uma honra. O Porto nunca mais a largou. | I4: =IF($A4="","",IF(TRIM(SUBSTITUTE(H4,CHAR(10)," "))="",0,LEN(TRIM(SUBSTITUTE(H4,CHAR(10)," ")))-LEN(SUBSTITUTE(TRIM(SUBSTITUTE(H4,CHAR(10)," "))," ",""))+1)) -> 67 | J4: We found no chronicle of the time that tells this story, and versions differ: in one, the nickname is already thirty years old, from a war with Castile. The dish, however, is real: tripas à moda do Porto, tripe stewed with beans, sausages and cuts of pork, chicken and veal. In 1960 a bronze monument by Lagoa Henriques was placed beside the old yards, thanking the people of Porto who equipped the fleet. Its inscription says À Grei, 'to the people'. | K4: =IF($A4="","",IF(TRIM(SUBSTITUTE(J4,CHAR(10)," "))="",0,LEN(TRIM(SUBSTITUTE(J4,CHAR(10)," ")))-LEN(SUBSTITUTE(TRIM(SUBSTITUTE(J4,CHAR(10)," "))," ",""))+1)) -> 81 | L4: Não encontrámos nenhuma crónica da época com esta história, e as versões variam: numa delas, a alcunha já tinha trinta anos, vinda de uma guerra com Castela. O prato, esse, existe mesmo: tripas à moda do Porto, tripas guisadas com feijão, enchidos e carnes de porco, frango e vitela. Em 1960, foi colocado um monumento de bronze de Lagoa Henriques junto aos antigos estaleiros, em agradecimento ao povo do Porto que equipou a armada. Na inscrição lê-se «À Grei». | M4: =IF($A4="","",IF(TRIM(SUBSTITUTE(L4,CHAR(10)," "))="",0,LEN(TRIM(SUBSTITUTE(L4,CHAR(10)," ")))-LEN(SUBSTITUTE(TRIM(SUBSTITUTE(L4,CHAR(10)," "))," ",""))+1)) -> 79 | N4: Порту отдал мясо, оставил потроха и получил прозвище. | O4: =IF($A4="","",IF(TRIM(SUBSTITUTE(N4,CHAR(10)," "))="",0,LEN(TRIM(SUBSTITUTE(N4,CHAR(10)," ")))-LEN(SUBSTITUTE(TRIM(SUBSTITUTE(N4,CHAR(10)," "))," ",""))+1)) -> 8 | P4: Согласно легенде, в 1415 году верфи Порту втайне строили флот для похода на Сеуту. Инфант Энрике (Генрих Мореплаватель), родившийся в этом городе, нагрянул без предупреждения и открыл настоящую цель мастеру верфи по имени Ваш. Ваш пообещал кораблям всё мясо города, а людям остались потроха. Энрике назвал прозвище «tripeiros», то есть любители потрохов, почётным. Порту носит его до сих пор. | Q4: =IF($A4="","",IF(TRIM(SUBSTITUTE(P4,CHAR(10)," "))="",0,LEN(TRIM(SUBSTITUTE(P4,CHAR(10)," ")))-LEN(SUBSTITUTE(TRIM(SUBSTITUTE(P4,CHAR(10)," "))," ",""))+1)) -> 59 | R4: Мы не нашли хроники того времени с этой историей, и версии расходятся: в одной прозвищу уже тридцать лет, оно пришло из войны с Кастилией. Зато блюдо настоящее: tripas à moda do Porto, рубец, тушёный с фасолью, колбасами и кусками свинины, курицы и телятины. В 1960 году у старых верфей поставили бронзовый памятник работы Лагоа Энрикеша в благодарность жителям Порту, снарядившим флот. На нём надпись À Grei, «народу». | S4: =IF($A4="","",IF(TRIM(SUBSTITUTE(R4,CHAR(10)," "))="",0,LEN(TRIM(SUBSTITUTE(R4,CHAR(10)," ")))-LEN(SUBSTITUTE(TRIM(SUBSTITUTE(R4,CHAR(10)," "))," ",""))+1)) -> 67 | T4: Запасной крючок: «Quem dá a carne fica com as tripas.» (игра с поговоркой, проверить, что поговорка так звучит). Фраза «We found no chronicle...» говорит от лица проекта: при редактуре поменять на нейтральную, если у сайта другой голос. ⚠ Блюдо в «Подробнее» перечислено по туристическим и кулинарным источникам, не по историческим. [PT переписан отдельно по-европейски, не переводом с EN.] [RU добавлен 16.10.2026: рабочий язык для вычитки, на сайте появится после переключателя.]
A5: guerra-laranjas-1801 | B5: The war named after a sprig of oranges sent to a queen. | C5: =IF($A5="","",IF(TRIM(SUBSTITUTE(B5,CHAR(10)," "))="",0,LEN(TRIM(SUBSTITUTE(B5,CHAR(10)," ")))-LEN(SUBSTITUTE(TRIM(SUBSTITUTE(B5,CHAR(10)," "))," ",""))+1)) -> 12 | D5: A guerra batizada por um ramo de laranjeira enviado à rainha. | E5: =IF($A5="","",IF(TRIM(SUBSTITUTE(D5,CHAR(10)," "))="",0,LEN(TRIM(SUBSTITUTE(D5,CHAR(10)," ")))-LEN(SUBSTITUTE(TRIM(SUBSTITUTE(D5,CHAR(10)," "))," ",""))+1)) -> 11 | F5: In May 1801 Spain, pushed by Napoleon's France, invaded Portugal. The army was led by Manuel Godoy, the prime minister and, people said, the queen's lover. He could not take the fortress of Elvas, but he took Olivença and a few border towns. Outside Elvas, says the tradition, Godoy picked a branch of oranges and sent it to Queen María Luisa as a token of victory. His enemies turned it into a joke, and the war became the War of the Oranges. | G5: =IF($A5="","",IF(TRIM(SUBSTITUTE(F5,CHAR(10)," "))="",0,LEN(TRIM(SUBSTITUTE(F5,CHAR(10)," ")))-LEN(SUBSTITUTE(TRIM(SUBSTITUTE(F5,CHAR(10)," "))," ",""))+1)) -> 82 | H5: Em maio de 1801, a Espanha, empurrada pela França de Napoleão, invadiu Portugal. O exército era comandado por Manuel Godoy, o primeiro-ministro e, diziam, amante da rainha. Não conseguiu tomar a fortaleza de Elvas, mas tomou Olivença e algumas vilas da fronteira. Diante de Elvas, conta a tradição, Godoy colheu um ramo de laranjas e enviou-o à rainha Maria Luísa como sinal de vitória. Os inimigos transformaram-no em anedota, e a guerra ficou a ser a Guerra das Laranjas. | I5: =IF($A5="","",IF(TRIM(SUBSTITUTE(H5,CHAR(10)," "))="",0,LEN(TRIM(SUBSTITUTE(H5,CHAR(10)," ")))-LEN(SUBSTITUTE(TRIM(SUBSTITUTE(H5,CHAR(10)," "))," ",""))+1)) -> 79 | J5: The war lasted about eighteen days, from 20 May to the Treaty of Badajoz on 6 June 1801. Elvas, under General Francisco de Noronha, held out. Spain gave back most of the towns it had taken but kept Olivença, and Portugal had to close its ports to British ships. In 1815 the Congress of Vienna recognised Portugal's right to Olivença, and Spain ratified the final act in 1817, yet the town was never returned. Today Olivença, 23 km from Elvas, has about 12,000 inhabitants and is administered by Spain. Whether it should return to Portugal is still argued. The orange episode is tradition, not a documented fact. Portuguese sources speak of a branch of orange blossom, Spanish and English ones of oranges, and it is the opponents of Godoy who are said to have turned it into a joke. | K5: =IF($A5="","",IF(TRIM(SUBSTITUTE(J5,CHAR(10)," "))="",0,LEN(TRIM(SUBSTITUTE(J5,CHAR(10)," ")))-LEN(SUBSTITUTE(TRIM(SUBSTITUTE(J5,CHAR(10)," "))," ",""))+1)) -> 139 | L5: A guerra durou cerca de dezoito dias, de 20 de maio ao Tratado de Badajoz, a 6 de junho de 1801. Elvas, sob o comando do general Francisco de Noronha, resistiu. A Espanha devolveu a maioria das praças que tinha tomado, mas ficou com Olivença, e Portugal teve de fechar os portos aos navios britânicos. Em 1815, o Congresso de Viena reconheceu o direito de Portugal a Olivença, e a Espanha ratificou a ata final em 1817, mas a vila nunca foi devolvida. Hoje, Olivença, a 23 km de Elvas, tem cerca de 12 000 habitantes e é administrada pela Espanha. Se deve voltar a Portugal continua em discussão. O episódio das laranjas é tradição, não um facto documentado. As fontes portuguesas falam de um ramo de flores de laranjeira, as espanholas e inglesas de laranjas, e diz-se que foram os adversários de Godoy a fazer dele uma anedota. | M5: =IF($A5="","",IF(TRIM(SUBSTITUTE(L5,CHAR(10)," "))="",0,LEN(TRIM(SUBSTITUTE(L5,CHAR(10)," ")))-LEN(SUBSTITUTE(TRIM(SUBSTITUTE(L5,CHAR(10)," "))," ",""))+1)) -> 149 | N5: Война, названная в честь апельсиновой ветки для королевы. | O5: =IF($A5="","",IF(TRIM(SUBSTITUTE(N5,CHAR(10)," "))="",0,LEN(TRIM(SUBSTITUTE(N5,CHAR(10)," ")))-LEN(SUBSTITUTE(TRIM(SUBSTITUTE(N5,CHAR(10)," "))," ",""))+1)) -> 8 | P5: В мае 1801 года Испания, подталкиваемая наполеоновской Францией, вторглась в Португалию. Армией командовал Мануэль Годой, первый министр и, как говорили, любовник королевы. Крепость Элваш он взять не смог, зато взял Оливенсу и несколько приграничных городков. Под Элвашем, гласит предание, Годой сорвал ветку апельсинов и отправил королеве Марии Луизе как знак победы. Его враги превратили это в шутку, и война осталась в истории «Апельсиновой». | Q5: =IF($A5="","",IF(TRIM(SUBSTITUTE(P5,CHAR(10)," "))="",0,LEN(TRIM(SUBSTITUTE(P5,CHAR(10)," ")))-LEN(SUBSTITUTE(TRIM(SUBSTITUTE(P5,CHAR(10)," "))," ",""))+1)) -> 63 | R5: Война длилась около восемнадцати дней, с 20 мая до Бадахосского договора 6 июня 1801 года. Элваш под командованием генерала Франсишку де Норонья устоял. Испания вернула большинство захваченных городов, но оставила Оливенсу, а Португалия должна была закрыть порты для британских кораблей. В 1815 году Венский конгресс признал право Португалии на Оливенсу, а Испания ратифицировала заключительный акт в 1817 году, но город так и не вернули. Сегодня Оливенса, в 23 км от Элваша, насчитывает около 12 000 жителей и управляется Испанией. Должна ли она вернуться в Португалию, по-прежнему спорят. Эпизод с апельсинами это предание, а не документированный факт. Португальские источники пишут о ветке апельсинового цвета, испанские и английские об апельсинах, а превратили это в шутку, как говорят, противники Годоя. | S5: =IF($A5="","",IF(TRIM(SUBSTITUTE(R5,CHAR(10)," "))="",0,LEN(TRIM(SUBSTITUTE(R5,CHAR(10)," ")))-LEN(SUBSTITUTE(TRIM(SUBSTITUTE(R5,CHAR(10)," "))," ",""))+1)) -> 117 | T5: Запасной крючок: «A guerra mais curta de Portugal tem nome de fruta, e uma vila perdida.» (⚠ «самая короткая» не проверено, не использовать без источника). ⚠ «Godoy failed to take Elvas»: Wikipedia и статья Dialnet (отбит гарнизоном Элваша), нужен ещё источник. «Favourite»: DN. [PT написан отдельно по-европейски.] [Перепроверка 16.10.2026] «Signed» заменено на «ratified»: Испания не подписывала Заключительный акт 1815, а ратифицировала его 7.05.1817 (Observador, MNE). Хук говорит «laranjas», история «ramo de flores de laranjeira»: оставлено, это игра предания. [RU добавлен 16.10.2026: рабочий язык для вычитки, на сайте появится после переключателя.]
A6: casa-da-neve-1782 | B6: Lisbon's oldest café was opened by the king's own ice-master. | C6: =IF($A6="","",IF(TRIM(SUBSTITUTE(B6,CHAR(10)," "))="",0,LEN(TRIM(SUBSTITUTE(B6,CHAR(10)," ")))-LEN(SUBSTITUTE(TRIM(SUBSTITUTE(B6,CHAR(10)," "))," ",""))+1)) -> 10 | D6: O café mais antigo de Lisboa foi aberto pelo neveiro do rei. | E6: =IF($A6="","",IF(TRIM(SUBSTITUTE(D6,CHAR(10)," "))="",0,LEN(TRIM(SUBSTITUTE(D6,CHAR(10)," ")))-LEN(SUBSTITUTE(TRIM(SUBSTITUTE(D6,CHAR(10)," "))," ",""))+1)) -> 12 | F6: In the second half of the 18th century, under the arcades of what is now Praça do Comércio, Lisbon got a shop that sold a luxury: ice (sources say 1778 or 1782). Its founder, Julião Pereira de Castro, was the royal household's chief snow-keeper. In a city of taverns, his Casa da Neve served cold drinks and flavoured ices to those who could pay. Today it is Lisbon's oldest café, Martinho da Arcada, and Fernando Pessoa's table is still reserved. | G6: =IF($A6="","",IF(TRIM(SUBSTITUTE(F6,CHAR(10)," "))="",0,LEN(TRIM(SUBSTITUTE(F6,CHAR(10)," ")))-LEN(SUBSTITUTE(TRIM(SUBSTITUTE(F6,CHAR(10)," "))," ",""))+1)) -> 80 | H6: Na segunda metade do século XVIII, sob as arcadas da atual Praça do Comércio, Lisboa ganhou uma loja que vendia um luxo: gelo (as fontes dizem 1778 ou 1782). O fundador, Julião Pereira de Castro, era o neveiro da Casa Real. Numa cidade de tabernas, a sua Casa da Neve servia bebidas geladas e «neves» com sabores a quem podia pagar. Hoje é o café mais antigo de Lisboa, o Martinho da Arcada, e a mesa de Fernando Pessoa continua reservada. | I6: =IF($A6="","",IF(TRIM(SUBSTITUTE(H6,CHAR(10)," "))="",0,LEN(TRIM(SUBSTITUTE(H6,CHAR(10)," ")))-LEN(SUBSTITUTE(TRIM(SUBSTITUTE(H6,CHAR(10)," "))," ",""))+1)) -> 81 | J6: Where did the ice come from? At first snow was gathered in the Serra da Estrela and the Serra da Lousã, packed in pits and carried by ox-cart and donkey to the Tagus, then by boat to Lisbon. Later the Royal Ice Factory in the Serra de Montejunto, much closer to the city, froze water at night in shallow tanks. Julião bought and rebuilt it in January 1782, as an inscription above its door says, and he held the kingdom's monopoly on snow and ice. What was 'neve'? Not snow but flavoured ice, something between a sorbet and a granita. Eça de Queirós has a character taste orange and strawberry in 1877. In the 18th century the Casa da Neve even quarrelled with another historic café, Marrare, which also claimed a share of the ice reaching Lisbon. Sources disagree on small details: the opening year (1778 or 1782) and day (2 or 7 January), and when the café took the name of its owner, Martinho Bartolomeu Rodrigues (1829 or 1845). In between it was an Italian coffee house. Its guests are said to include Bocage, Eça de Queirós and Pessoa. The square had been rebuilt after the 1755 earthquake. | K6: =IF($A6="","",IF(TRIM(SUBSTITUTE(J6,CHAR(10)," "))="",0,LEN(TRIM(SUBSTITUTE(J6,CHAR(10)," ")))-LEN(SUBSTITUTE(TRIM(SUBSTITUTE(J6,CHAR(10)," "))," ",""))+1)) -> 199 | L6: De onde vinha o gelo? Primeiro, a neve era recolhida na Serra da Estrela e na Serra da Lousã, prensada em poços e levada em carros de bois e burros até ao Tejo, e depois de barco até Lisboa. Mais tarde, a Real Fábrica do Gelo, na Serra de Montejunto, muito mais perto da cidade, congelava a água de noite em tanques rasos. Julião comprou-a e reedificou-a em janeiro de 1782, como diz uma inscrição sobre a porta, e tinha o monopólio da neve e do gelo do reino. O que era a «neve»? Não era neve, era gelo com sabores, algo entre um sorvete e um granizado. Eça de Queirós põe uma personagem a provar laranja e morango, em 1877. No século XVIII, a Casa da Neve chegou a andar à rixa com outro café histórico, o Marrare, que também reclamava uma parte do gelo que chegava a Lisboa. As fontes divergem em pormenores: o ano da abertura (1778 ou 1782) e o dia (2 ou 7 de janeiro), e quando o café passou a ter o nome do dono, Martinho Bartolomeu Rodrigues (1829 ou 1845). Pelo meio foi Casa de Café Italiana. Diz-se que por lá passaram Bocage, Eça de Queirós e Pessoa. A praça tinha sido reconstruída depois do terramoto de 1755. | M6: =IF($A6="","",IF(TRIM(SUBSTITUTE(L6,CHAR(10)," "))="",0,LEN(TRIM(SUBSTITUTE(L6,CHAR(10)," ")))-LEN(SUBSTITUTE(TRIM(SUBSTITUTE(L6,CHAR(10)," "))," ",""))+1)) -> 215 | N6: Старейшее кафе Лиссабона основал королевский хранитель льда. | O6: =IF($A6="","",IF(TRIM(SUBSTITUTE(N6,CHAR(10)," "))="",0,LEN(TRIM(SUBSTITUTE(N6,CHAR(10)," ")))-LEN(SUBSTITUTE(TRIM(SUBSTITUTE(N6,CHAR(10)," "))," ",""))+1)) -> 7 | P6: Во второй половине XVIII века под аркадами нынешней площади Коммерсио в Лиссабоне открылась лавка, продававшая роскошь: лёд (по разным источникам, в 1778 или 1782 году). Её основатель Жулиан Перейра де Кастру был главным хранителем снега при королевском дворе. В городе таверн его Каза-да-Нев подавала холодные напитки и фруктовый лёд тем, кто мог заплатить. Сегодня это старейшее кафе Лиссабона, Мартиньо да Аркада, а стол Фернандо Пессоа по-прежнему зарезервирован. | Q6: =IF($A6="","",IF(TRIM(SUBSTITUTE(P6,CHAR(10)," "))="",0,LEN(TRIM(SUBSTITUTE(P6,CHAR(10)," ")))-LEN(SUBSTITUTE(TRIM(SUBSTITUTE(P6,CHAR(10)," "))," ",""))+1)) -> 67 | R6: Откуда брался лёд? Сначала снег собирали в Серра-да-Эштрела и Серра-да-Лозан, утрамбовывали в ямах и везли на волах и ослах до Тежу, а затем на лодках в Лиссабон. Позже Королевская ледяная фабрика в Серра-ди-Монтежунту, гораздо ближе к городу, замораживала воду по ночам в мелких бассейнах. Жулиан купил и перестроил её в январе 1782 года, как говорит надпись над дверью, и владел монополией на снег и лёд в королевстве. Что такое «neve»? Не снег, а ароматный лёд, что-то среднее между щербетом и гранитой. У Эсы де Кейроша в 1877 году персонаж пробует апельсиновый с клубничным. В XVIII веке Каза-да-Нев даже ссорилась с другим историческим кафе, Марраре, которое тоже претендовало на часть льда, приходившего в Лиссабон. Источники расходятся в мелочах: год открытия (1778 или 1782) и день (2 или 7 января), и когда кафе получило имя владельца, Мартиньо Бартоломеу Родригиша (1829 или 1845). Между тем это была итальянская кофейня. Говорят, среди гостей были Бокаже, Эса де Кейрош и Пессоа. Площадь была отстроена заново после землетрясения 1755 года. | S6: =IF($A6="","",IF(TRIM(SUBSTITUTE(R6,CHAR(10)," "))="",0,LEN(TRIM(SUBSTITUTE(R6,CHAR(10)," ")))-LEN(SUBSTITUTE(TRIM(SUBSTITUTE(R6,CHAR(10)," "))," ",""))+1)) -> 164 | T6: Крючок: «ice-master» = neveiro-mor da Casa Real (CM). Запасной крючок: «Em 1782, Lisboa descobriu o gelo. O dono era do palácio.» ⚠ «Fernando Pessoa's table is still reserved»: по Lisboa Secreta и Lojas com História, проверить на месте/на сайте. [PT написан отдельно по-европейски.] [Перепроверка 16.10.2026] Монополия на поставку льда двору: DN (Dentinho), поэтому добавлена в «Подробнее». Имя Martinho: Ara (1829, внук основателя) против Lisboa Secreta и DN (1845, покупатель Martinho Bartolomeu Rodrigues): в тексте оба года, «dono» оставлено как есть. «Старейшее кафе»: CM пишет «café de porta aberta mais antigo». Не использовано: последний кофе Пессоа за этим столом 27.11.1935 (Ara); Revolta da Sé 1959, планировавшийся за столом Martinho (колонка DN): идея для карточки эпохи 8. [RU добавлен 16.10.2026: рабочий язык для вычитки, на сайте появится после переключателя.] [16.10.2026] Реестр города «Lojas com História» (CML) называет 1829 годом, когда Martinho Bartolomeu Rodrigues дал кафе имя; DN и Lisboa Secreta пишут 1845: в тексте оба года. Дата открытия: 2 января 1782 (Lisboa Secreta) против 2 или 7 января в других источниках. livetheworld.com ошибочно пишет «открыл маркиз Помбал»: слабый источник, не использован.
A7: douro-1756 | B7: To save port, Pombal had the Douro's elder trees uprooted. | C7: =IF($A7="","",IF(TRIM(SUBSTITUTE(B7,CHAR(10)," "))="",0,LEN(TRIM(SUBSTITUTE(B7,CHAR(10)," ")))-LEN(SUBSTITUTE(TRIM(SUBSTITUTE(B7,CHAR(10)," "))," ",""))+1)) -> 10 | D7: Para salvar o vinho do Porto, Pombal mandou arrancar os sabugueiros. | E7: =IF($A7="","",IF(TRIM(SUBSTITUTE(D7,CHAR(10)," "))="",0,LEN(TRIM(SUBSTITUTE(D7,CHAR(10)," ")))-LEN(SUBSTITUTE(TRIM(SUBSTITUTE(D7,CHAR(10)," "))," ",""))+1)) -> 11 | F7: By the 1750s the port wine trade was in crisis: too much wine, too many fakes, and most of it sold by British merchants in Porto. In 1756 Sebastião José de Carvalho e Melo, the future Marquis of Pombal, created a company with a monopoly on the trade with England and Brazil, and the elder trees were uprooted. Two years later the first of 335 granite pillars went up to mark the region's borders, often called the world's first demarcated wine region. | G7: =IF($A7="","",IF(TRIM(SUBSTITUTE(F7,CHAR(10)," "))="",0,LEN(TRIM(SUBSTITUTE(F7,CHAR(10)," ")))-LEN(SUBSTITUTE(TRIM(SUBSTITUTE(F7,CHAR(10)," "))," ",""))+1)) -> 82 | H7: Nos anos 1750, o comércio do vinho do Porto estava em crise: vinho a mais, falsificações a mais, e a maior parte vendida por comerciantes britânicos no Porto. Em 1756, Sebastião José de Carvalho e Melo, o futuro marquês de Pombal, criou uma companhia com o monopólio do comércio com Inglaterra e o Brasil, e arrancaram-se os sabugueiros. Dois anos depois foi erguido o primeiro dos 335 marcos de granito que delimitam a região, muitas vezes apontada como a primeira região vinhateira demarcada do mundo. | I7: =IF($A7="","",IF(TRIM(SUBSTITUTE(H7,CHAR(10)," "))="",0,LEN(TRIM(SUBSTITUTE(H7,CHAR(10)," ")))-LEN(SUBSTITUTE(TRIM(SUBSTITUTE(H7,CHAR(10)," "))," ",""))+1)) -> 85 | J7: The stones were carved with 'Feitoria' and a year, the first in 1758, and about a hundred of the 335 still stand in the vineyards. In Portuguese they are the marcos pombalinos. The company founded in 1756 is still alive: today it is the Real Companhia Velha, and its cellars and a small museum, 17•56, stand on the banks of the Douro in Vila Nova de Gaia. Not everyone welcomed the new rules. In February 1757 Porto's tavern-keepers rose against the Company; that story has its own card. | K7: =IF($A7="","",IF(TRIM(SUBSTITUTE(J7,CHAR(10)," "))="",0,LEN(TRIM(SUBSTITUTE(J7,CHAR(10)," ")))-LEN(SUBSTITUTE(TRIM(SUBSTITUTE(J7,CHAR(10)," "))," ",""))+1)) -> 88 | L7: Os marcos tinham gravado «Feitoria» e um ano, os primeiros de 1758, e cerca de cem dos 335 ainda estão de pé nas vinhas. Chamam-se marcos pombalinos. A companhia fundada em 1756 continua viva: hoje é a Real Companhia Velha, e as suas caves e um pequeno museu, o 17•56, ficam à beira do Douro, em Vila Nova de Gaia. Nem todos receberam bem as novas regras. Em fevereiro de 1757, os taberneiros do Porto revoltaram-se contra a Companhia; essa história tem cartão próprio. | M7: =IF($A7="","",IF(TRIM(SUBSTITUTE(L7,CHAR(10)," "))="",0,LEN(TRIM(SUBSTITUTE(L7,CHAR(10)," ")))-LEN(SUBSTITUTE(TRIM(SUBSTITUTE(L7,CHAR(10)," "))," ",""))+1)) -> 84 | N7: Чтобы спасти портвейн, Помбал велел вырвать бузину в долине Дору. | O7: =IF($A7="","",IF(TRIM(SUBSTITUTE(N7,CHAR(10)," "))="",0,LEN(TRIM(SUBSTITUTE(N7,CHAR(10)," ")))-LEN(SUBSTITUTE(TRIM(SUBSTITUTE(N7,CHAR(10)," "))," ",""))+1)) -> 10 | P7: К 1750-м торговля портвейном была в кризисе: вина слишком много, подделок слишком много, а продавали его в основном британские купцы в Порту. В 1756 году Себастьян Жозе де Карвалью-и-Мелу, будущий маркиз Помбал, создал компанию с монополией на торговлю с Англией и Бразилией, и бузину вырвали. Через два года поставили первый из 335 гранитных столбов, отмечавших границы региона, который часто называют первым в мире демаркированным винным регионом. | Q7: =IF($A7="","",IF(TRIM(SUBSTITUTE(P7,CHAR(10)," "))="",0,LEN(TRIM(SUBSTITUTE(P7,CHAR(10)," ")))-LEN(SUBSTITUTE(TRIM(SUBSTITUTE(P7,CHAR(10)," "))," ",""))+1)) -> 66 | R7: На камнях вырезали «Feitoria» и год, первые в 1758-м, и около сотни из 335 до сих пор стоят среди виноградников. По-португальски они называются marcos pombalinos. Компания, основанная в 1756 году, существует до сих пор: сегодня это Real Companhia Velha, а её погреба и небольшой музей 17•56 стоят на берегу Дору в Вила-Нова-ди-Гая. Не все приняли новые правила. В феврале 1757 года хозяева таверн Порту восстали против Компании: эта история в отдельной карточке. | S7: =IF($A7="","",IF(TRIM(SUBSTITUTE(R7,CHAR(10)," "))="",0,LEN(TRIM(SUBSTITUTE(R7,CHAR(10)," ")))-LEN(SUBSTITUTE(TRIM(SUBSTITUTE(R7,CHAR(10)," "))," ",""))+1)) -> 72 | T7: [16.10.2026] Хук про бузину взят из того, что бузину вырывали ради борьбы с подделками (Taylor's, Wine Anorak). Цвет вина и подробности подделки в тексте не заявлены.
A8: elefantes-malaca-1511 | B8: The sultan unleashed war elephants. They turned on his own men. | C8: =IF($A8="","",IF(TRIM(SUBSTITUTE(B8,CHAR(10)," "))="",0,LEN(TRIM(SUBSTITUTE(B8,CHAR(10)," ")))-LEN(SUBSTITUTE(TRIM(SUBSTITUTE(B8,CHAR(10)," "))," ",""))+1)) -> 11 | D8: O sultão lançou elefantes de guerra. Viraram-se contra os seus. | E8: =IF($A8="","",IF(TRIM(SUBSTITUTE(D8,CHAR(10)," "))="",0,LEN(TRIM(SUBSTITUTE(D8,CHAR(10)," ")))-LEN(SUBSTITUTE(TRIM(SUBSTITUTE(D8,CHAR(10)," "))," ",""))+1)) -> 10 | F8: «Whoever is lord of Malacca has his hand on the throat of Venice,» wrote the Portuguese apothecary Tomé Pires, because Malacca controlled the spice route. On 25 July 1511 Afonso de Albuquerque attacked it with about a thousand men. The sultan answered with war elephants. One Portuguese jabbed his lance into the lead elephant's eye. Howling, the animal turned back, the others panicked and trampled their own side, and the sultan fell from his mount, wounded. A month later the city was Portuguese. | G8: =IF($A8="","",IF(TRIM(SUBSTITUTE(F8,CHAR(10)," "))="",0,LEN(TRIM(SUBSTITUTE(F8,CHAR(10)," ")))-LEN(SUBSTITUTE(TRIM(SUBSTITUTE(F8,CHAR(10)," "))," ",""))+1)) -> 83 | H8: «Quem for senhor de Malaca tem a mão na garganta de Veneza», escreveu o boticário Tomé Pires, porque Malaca controlava a rota das especiarias. A 25 de julho de 1511, Afonso de Albuquerque atacou-a com cerca de mil homens. O sultão respondeu com elefantes de guerra. Um português espetou a lança no olho do elefante da frente. O bicho recuou aos berros, os outros entraram em pânico e esmagaram os seus, e o sultão caiu da montada, ferido. Um mês depois, a cidade era portuguesa. | I8: =IF($A8="","",IF(TRIM(SUBSTITUTE(H8,CHAR(10)," "))="",0,LEN(TRIM(SUBSTITUTE(H8,CHAR(10)," ")))-LEN(SUBSTITUTE(TRIM(SUBSTITUTE(H8,CHAR(10)," "))," ",""))+1)) -> 85 | J8: The numbers vary: some sources mention about twenty elephants, and the defenders are put at 20,000 to 30,000. Albuquerque is given between 1,000 and 1,200 men, about 700 of them Portuguese. He pulled back after the first assault, attacked again in August and took the city after about forty days of fighting. The monument to Albuquerque in Belém shows the taking of Malacca on one of its four reliefs. Much of what we know of his campaigns comes from his son Brás, who turned his father's papers into the Commentaries and built Lisbon's Casa dos Bicos with the fortune his father had made. | K8: =IF($A8="","",IF(TRIM(SUBSTITUTE(J8,CHAR(10)," "))="",0,LEN(TRIM(SUBSTITUTE(J8,CHAR(10)," ")))-LEN(SUBSTITUTE(TRIM(SUBSTITUTE(J8,CHAR(10)," "))," ",""))+1)) -> 103 | L8: Os números variam: algumas fontes falam em cerca de vinte elefantes, e os defensores são calculados entre 20 000 e 30 000. A Albuquerque dão-se entre 1000 e 1200 homens, uns 700 deles portugueses. Recuou depois do primeiro assalto, voltou a atacar em agosto e tomou a cidade ao fim de cerca de quarenta dias de combates. O monumento a Afonso de Albuquerque, em Belém, mostra a tomada de Malaca num dos seus quatro relevos. Muito do que sabemos das suas campanhas vem do filho, Brás, que transformou os papéis do pai nos Comentários e construiu em Lisboa a Casa dos Bicos com a fortuna que o pai juntara. | M8: =IF($A8="","",IF(TRIM(SUBSTITUTE(L8,CHAR(10)," "))="",0,LEN(TRIM(SUBSTITUTE(L8,CHAR(10)," ")))-LEN(SUBSTITUTE(TRIM(SUBSTITUTE(L8,CHAR(10)," "))," ",""))+1)) -> 109 | N8: Султан вывел боевых слонов. Они развернулись против него. | O8: =IF($A8="","",IF(TRIM(SUBSTITUTE(N8,CHAR(10)," "))="",0,LEN(TRIM(SUBSTITUTE(N8,CHAR(10)," ")))-LEN(SUBSTITUTE(TRIM(SUBSTITUTE(N8,CHAR(10)," "))," ",""))+1)) -> 8 | P8: «Кто владеет Малаккой, тот держит Венецию за горло», писал португальский аптекарь Томе Пиреш, ведь Малакка контролировала путь пряностей. 25 июля 1511 года Афонсу де Албукерки атаковал её с тысячей человек. Султан ответил боевыми слонами. Один португалец вонзил копьё в глаз передовому слону. С рёвом зверь повернул назад, остальные в панике затоптали своих, а султан упал с животного и был ранен. Через месяц город стал португальским. | Q8: =IF($A8="","",IF(TRIM(SUBSTITUTE(P8,CHAR(10)," "))="",0,LEN(TRIM(SUBSTITUTE(P8,CHAR(10)," ")))-LEN(SUBSTITUTE(TRIM(SUBSTITUTE(P8,CHAR(10)," "))," ",""))+1)) -> 65 | R8: Цифры расходятся: одни источники упоминают около двадцати слонов, а защитников оценивают в 20 000–30 000. Албукерки дают от 1000 до 1200 человек, около 700 из них португальцы. После первого штурма он отступил, в августе атаковал снова и взял город после примерно сорока дней боёв. Памятник Албукерки в Белеме показывает взятие Малакки на одном из четырёх рельефов. Многое о его походах известно от сына Браша, который превратил бумаги отца в «Комментарии» и построил в Лиссабоне Каза-душ-Бикуш на состояние отца. | S8: =IF($A8="","",IF(TRIM(SUBSTITUTE(R8,CHAR(10)," "))="",0,LEN(TRIM(SUBSTITUTE(R8,CHAR(10)," ")))-LEN(SUBSTITUTE(TRIM(SUBSTITUTE(R8,CHAR(10)," "))," ",""))+1)) -> 78 | T8: Запасной крючок: «O sultão tinha elefantes. Os portugueses tinham lanças compridas.» ⚠ Хронология в источниках склеена: нападение 25 июля, отход, новый штурм в августе, падение 24 августа. Фраза «A month later» упрощает: осада шла около сорока дней. [PT написан отдельно по-европейски, не переводом.] [16.10.2026] Нашёл при поиске картинок: Wikipedia даёт силы Албукерки как «около 1200 человек» (Portuguese Malacca) и как «700 португальцев и 300 малабарских вспомогательных» (Malay–Portuguese conflicts), а дату взятия города в одной статье 15 августа (врезка), в другой 24-го (текст). Конкретная дата из текста убрана, пока не сверено по Barros или «Комментариям». [RU добавлен 16.10.2026: рабочий язык для вычитки, на сайте появится после переключателя.]
A9: torres-vedras-1810 | B9: Portugal spent a year building forts the French barely knew existed. | C9: =IF($A9="","",IF(TRIM(SUBSTITUTE(B9,CHAR(10)," "))="",0,LEN(TRIM(SUBSTITUTE(B9,CHAR(10)," ")))-LEN(SUBSTITUTE(TRIM(SUBSTITUTE(B9,CHAR(10)," "))," ",""))+1)) -> 11 | D9: Um ano a construir fortes que os franceses mal sabiam que existiam. | E9: =IF($A9="","",IF(TRIM(SUBSTITUTE(D9,CHAR(10)," "))="",0,LEN(TRIM(SUBSTITUTE(D9,CHAR(10)," ")))-LEN(SUBSTITUTE(TRIM(SUBSTITUTE(D9,CHAR(10)," "))," ",""))+1)) -> 12 | F9: In October 1809, Wellington ordered fortifications built on the hills north of Lisbon. Portuguese workers raised forts and redoubts in secret. In September 1810, Marshal Masséna marched on Lisbon with about 60,000 men, through a land stripped of food by its own farmers. On 11 October he reached the Lines of Torres Vedras. A month later, hungry, he turned back. | G9: =IF($A9="","",IF(TRIM(SUBSTITUTE(F9,CHAR(10)," "))="",0,LEN(TRIM(SUBSTITUTE(F9,CHAR(10)," ")))-LEN(SUBSTITUTE(TRIM(SUBSTITUTE(F9,CHAR(10)," "))," ",""))+1)) -> 60 | H9: Em outubro de 1809, Wellington mandou fortificar as colinas a norte de Lisboa. Trabalhadores portugueses ergueram fortes e redutos em segredo. Em setembro de 1810, o marechal Masséna avançou para Lisboa com cerca de 60 000 homens, por uma terra sem comida, que os próprios camponeses tinham destruído. A 11 de outubro chegou às Linhas de Torres Vedras. Um mês depois, com fome, voltou para trás. | I9: =IF($A9="","",IF(TRIM(SUBSTITUTE(H9,CHAR(10)," "))="",0,LEN(TRIM(SUBSTITUTE(H9,CHAR(10)," ")))-LEN(SUBSTITUTE(TRIM(SUBSTITUTE(H9,CHAR(10)," "))," ",""))+1)) -> 66 | J9: The system had three lines of forts and redoubts between the Tagus and the Atlantic, designed by Wellington's chief engineer, Colonel Richard Fletcher. The biggest fort, São Vicente at Torres Vedras, had a garrison of about 2,000 men and room for around 4,000. Portuguese farmers left their land and destroyed the food they could not carry, so the French army went hungry. The French probed the lines at Sobral on 13 and 14 October, then camped in front of them until mid-November. Sources differ on the number of forts, and put Masséna's army at the lines between just over 50,000 and 61,000 men. The campaign was also a disaster for civilians: some estimates speak of tens of thousands of Portuguese dead from hunger and disease. | K9: =IF($A9="","",IF(TRIM(SUBSTITUTE(J9,CHAR(10)," "))="",0,LEN(TRIM(SUBSTITUTE(J9,CHAR(10)," ")))-LEN(SUBSTITUTE(TRIM(SUBSTITUTE(J9,CHAR(10)," "))," ",""))+1)) -> 125 | L9: O sistema tinha três linhas de fortes e redutos entre o Tejo e o Atlântico, desenhadas pelo engenheiro-chefe de Wellington, o coronel Richard Fletcher. O maior forte, o de São Vicente, em Torres Vedras, tinha uma guarnição de cerca de 2000 homens e espaço para uns 4000. Os camponeses portugueses abandonaram as terras e destruíram a comida que não podiam levar, e o exército francês passou fome. Os franceses testaram as linhas em Sobral, a 13 e 14 de outubro, e acamparam diante delas até meados de novembro. As fontes divergem quanto ao número de fortes e situam o exército de Masséna junto às linhas entre pouco mais de 50 000 e 61 000 homens. A campanha foi também um desastre para os civis: algumas estimativas apontam para dezenas de milhares de mortos portugueses por fome e doença. | M9: =IF($A9="","",IF(TRIM(SUBSTITUTE(L9,CHAR(10)," "))="",0,LEN(TRIM(SUBSTITUTE(L9,CHAR(10)," ")))-LEN(SUBSTITUTE(TRIM(SUBSTITUTE(L9,CHAR(10)," "))," ",""))+1)) -> 138 | N9: Целый год строили линию фортов, о которой французы почти не знали. | O9: =IF($A9="","",IF(TRIM(SUBSTITUTE(N9,CHAR(10)," "))="",0,LEN(TRIM(SUBSTITUTE(N9,CHAR(10)," ")))-LEN(SUBSTITUTE(TRIM(SUBSTITUTE(N9,CHAR(10)," "))," ",""))+1)) -> 11 | P9: В октябре 1809 года Веллингтон приказал построить укрепления на холмах севернее Лиссабона. Португальские рабочие втайне возводили форты и редуты. В сентябре 1810 года маршал Массена двинулся на Лиссабон примерно с 60 тысячами человек через землю, где крестьяне сами уничтожили всю еду. 11 октября он дошёл до линий Торриш-Ведраш. Через месяц, голодный, он повернул назад. | Q9: =IF($A9="","",IF(TRIM(SUBSTITUTE(P9,CHAR(10)," "))="",0,LEN(TRIM(SUBSTITUTE(P9,CHAR(10)," ")))-LEN(SUBSTITUTE(TRIM(SUBSTITUTE(P9,CHAR(10)," "))," ",""))+1)) -> 54 | R9: Система состояла из трёх линий фортов и редутов между Тежу и Атлантикой, спроектированных главным инженером Веллингтона полковником Ричардом Флетчером. Крупнейший форт, Сан-Висенте в Торриш-Ведраш, имел гарнизон около 2000 человек и место примерно для 4000. Португальские крестьяне покидали земли и уничтожали еду, которую не могли унести, поэтому французская армия голодала. Французы прощупали линии у Собрала 13 и 14 октября, а затем стояли перед ними до середины ноября. Источники расходятся в числе фортов и оценивают армию Массена у линий от чуть более 50 000 до 61 000 человек. Кампания стала катастрофой и для гражданских: по некоторым оценкам, десятки тысяч португальцев умерли от голода и болезней. | S9: =IF($A9="","",IF(TRIM(SUBSTITUTE(R9,CHAR(10)," "))="",0,LEN(TRIM(SUBSTITUTE(R9,CHAR(10)," ")))-LEN(SUBSTITUTE(TRIM(SUBSTITUTE(R9,CHAR(10)," "))," ",""))+1)) -> 103 | T9: Запасной крючок: «O marechal chegou a Lisboa. Lisboa já tinha uma muralha de colinas.» ⚠ «Секретность»: Wikipedia, historyofwar.org говорят «почти полностью секретно», это не «никто не знал»: хроники Массены не читаны. Отход «a month later»: ночь 14/15 ноября 1810. [PT написан отдельно по-европейски.] [Перепроверка 16.10.2026] Хук смягчён: раньше «found ... only when he reached it» читалось как факт, а источники говорят «почти полностью секретно» (HistoryofWar) и «говорят, Массена спросил штаб, почему не знали» (Military Wiki). Ёмкость форта São Vicente: «5000» (HistoryofWar) против «гарнизон 2000–2200, места для ≈4000» (Portugal Film Commission, муниципалитет): взяты данные муниципалитета. Численность Массены у линий: 61 000 (Wikipedia) против «чуть больше 50 000» (HistoryofWar): в «Подробнее» диапазон, в истории «about 60,000» осталось. 152 форта: BHS Portugal. [RU добавлен 16.10.2026: рабочий язык для вычитки, на сайте появится после переключателя.]
A10: aljubarrota-1385 | B10: At 25, he left the war council and chose the battlefield himself. | C10: =IF($A10="","",IF(TRIM(SUBSTITUTE(B10,CHAR(10)," "))="",0,LEN(TRIM(SUBSTITUTE(B10,CHAR(10)," ")))-LEN(SUBSTITUTE(TRIM(SUBSTITUTE(B10,CHAR(10)," "))," ",""))+1)) -> 12 | D10: Aos 25 anos, deixou o conselho e escolheu o campo de batalha. | E10: =IF($A10="","",IF(TRIM(SUBSTITUTE(D10,CHAR(10)," "))="",0,LEN(TRIM(SUBSTITUTE(D10,CHAR(10)," ")))-LEN(SUBSTITUTE(TRIM(SUBSTITUTE(D10,CHAR(10)," "))," ",""))+1)) -> 12 | F10: In 1385 Nuno Álvares Pereira was 25 and Portugal's constable. The war council could not agree where to fight, so on 6 August he left the camp with about 2,000 men and chose the battlefield himself. Froissart says he had ditches and wolf pits dug across a narrow plateau. On 14 August, at the hour of vespers, the French knights who charged first rode straight into them. The Castilians, several times more numerous, lost. | G10: =IF($A10="","",IF(TRIM(SUBSTITUTE(F10,CHAR(10)," "))="",0,LEN(TRIM(SUBSTITUTE(F10,CHAR(10)," ")))-LEN(SUBSTITUTE(TRIM(SUBSTITUTE(F10,CHAR(10)," "))," ",""))+1)) -> 74 | H10: Em 1385, Nuno Álvares Pereira tinha 25 anos e era condestável de Portugal. O conselho de guerra não chegou a acordo sobre onde combater, por isso, a 6 de agosto, saiu do acampamento com uns 2000 homens e escolheu sozinho o campo de batalha. Segundo Froissart, mandou abrir valas e covas de lobo num planalto estreito. A 14, à hora das vésperas, os franceses que atacaram primeiro caíram lá dentro. Os castelhanos, muito mais numerosos, perderam. | I10: =IF($A10="","",IF(TRIM(SUBSTITUTE(H10,CHAR(10)," "))="",0,LEN(TRIM(SUBSTITUTE(H10,CHAR(10)," ")))-LEN(SUBSTITUTE(TRIM(SUBSTITUTE(H10,CHAR(10)," "))," ",""))+1)) -> 76 | J10: After the victory, Nuno gave most of his wealth to his veterans. In 1423, aged 63, he entered the Carmo convent he had founded in Lisbon and became Friar Nuno of Saint Mary. The 1755 earthquake destroyed the convent's roof; today its nave stands open to the sky. Numbers for the armies vary widely: the Aljubarrota Battle Foundation puts the Portuguese at about 7,000 and the Castilians at 31,000–44,000, of whom only about 10,000 fought. The 'Portuguese square' is now called a myth, and the baker woman who killed fleeing Castilians first appears in sources in the 16th century. He was canonised in 2009. The ditches and pits come from Froissart; Ayala, the Castilian eyewitness chronicler, and Fernão Lopes, sixty years later, do not describe them. | K10: =IF($A10="","",IF(TRIM(SUBSTITUTE(J10,CHAR(10)," "))="",0,LEN(TRIM(SUBSTITUTE(J10,CHAR(10)," ")))-LEN(SUBSTITUTE(TRIM(SUBSTITUTE(J10,CHAR(10)," "))," ",""))+1)) -> 126 | L10: Depois da vitória, Nuno deu a maior parte da fortuna aos seus veteranos. Em 1423, com 63 anos, entrou no Convento do Carmo, que ele próprio fundara em Lisboa, e passou a ser o Frei Nuno de Santa Maria. O terramoto de 1755 destruiu o telhado do convento; hoje a nave está aberta ao céu. Os números dos exércitos variam muito: a Fundação Batalha de Aljubarrota fala em cerca de 7000 portugueses e 31 000 a 44 000 castelhanos, dos quais só uns 10 000 combateram. O famoso «quadrado» português é hoje tido como mito, e a padeira que matou castelhanos em fuga só aparece nas fontes no século XVI. Foi canonizado em 2009. Fossos e covas vêm de Froissart; Ayala, cronista castelhano e testemunha ocular, e Fernão Lopes, sessenta anos depois, não os descrevem. | M10: =IF($A10="","",IF(TRIM(SUBSTITUTE(L10,CHAR(10)," "))="",0,LEN(TRIM(SUBSTITUTE(L10,CHAR(10)," ")))-LEN(SUBSTITUTE(TRIM(SUBSTITUTE(L10,CHAR(10)," "))," ",""))+1)) -> 135 | N10: 25-летний коннетабль ушёл с совета и сам выбрал поле боя. | O10: =IF($A10="","",IF(TRIM(SUBSTITUTE(N10,CHAR(10)," "))="",0,LEN(TRIM(SUBSTITUTE(N10,CHAR(10)," ")))-LEN(SUBSTITUTE(TRIM(SUBSTITUTE(N10,CHAR(10)," "))," ",""))+1)) -> 10 | P10: В 1385 году Нуну Алвариш Перейра был 25-летним коннетаблем Португалии. Военный совет не мог решить, где принимать бой, и 6 августа он ушёл из лагеря с двумя тысячами человек и сам выбрал поле боя. По Фруассару, он велел вырыть рвы и волчьи ямы на узком плато. 14 августа, в час вечерни, французские рыцари, атаковавшие первыми, влетели прямо в них. Кастильцы, которых было в разы больше, проиграли. | Q10: =IF($A10="","",IF(TRIM(SUBSTITUTE(P10,CHAR(10)," "))="",0,LEN(TRIM(SUBSTITUTE(P10,CHAR(10)," ")))-LEN(SUBSTITUTE(TRIM(SUBSTITUTE(P10,CHAR(10)," "))," ",""))+1)) -> 66 | R10: После победы Нуну раздал большую часть состояния своим ветеранам. В 1423 году, в 63 года, он вступил в основанный им в Лиссабоне монастырь Кармо и стал братом Нуну де Санта-Мария. Землетрясение 1755 года разрушило крышу монастыря, и сегодня его неф стоит открытым небу. Численность армий оценивают очень по-разному: Фонд битвы при Алжубарроте называет около 7000 португальцев и 31 000–44 000 кастильцев, из которых сражались лишь около 10 000. «Португальский квадрат» сегодня считают мифом, а пекарша, убившая бегущих кастильцев, появляется в источниках лишь в XVI веке. В 2009 году он был канонизирован. Рвы и ямы известны по Фруассару; кастильский хронист-очевидец Айяла и Фернан Лопеш, писавший через шестьдесят лет, их не описывают. | S10: =IF($A10="","",IF(TRIM(SUBSTITUTE(R10,CHAR(10)," "))="",0,LEN(TRIM(SUBSTITUTE(R10,CHAR(10)," ")))-LEN(SUBSTITUTE(TRIM(SUBSTITUTE(R10,CHAR(10)," "))," ",""))+1)) -> 110 | T10: Версия 3 внедрена (человек в центре: 25-летний Нуну, ушёл с совета; конец истории через монастырь Кармо связывает с карточкой 1755). Выброшено из v2 как неподтверждённое: «15 000 стрел за первые минуты» и «король Кастилии уплыл мимо Лиссабона». ⚠ «Чем ночью были рвы»: источники говорят только, что они были. «Час вечерни» по Лопешу (через панно CIBA). [PT переписан отдельно по-европейски, не переводом.] [RU добавлен 16.10.2026: рабочий язык для вычитки, на сайте появится после переключателя.] [16.10.2026] ВАЖНО: рвы и волчьи ямы (на них держался хук «buracos no chão») подтверждены Froissart, а очевидец Айяла молчит, и Лопеш, писавший через 60 лет, не описывает «оборонительную систему» (статья Antiquity, 1963; в 1960 Комиссия военной истории заказала отдельное исследование). Музей CIBA подаёт ямы как факт, и его опыт показал, что 700 человек могли выкопать их за несколько часов, но это не доказательство, что их копали. Поэтому хук и история смягчены («Froissart says», «maybe»). Если откатить, потеряется честность метки.
A11: terramoto-1755 | B11: The king left Lisbon that morning because his daughter asked. | C11: =IF($A11="","",IF(TRIM(SUBSTITUTE(B11,CHAR(10)," "))="",0,LEN(TRIM(SUBSTITUTE(B11,CHAR(10)," ")))-LEN(SUBSTITUTE(TRIM(SUBSTITUTE(B11,CHAR(10)," "))," ",""))+1)) -> 10 | D11: O rei saiu de Lisboa nessa manhã porque uma filha quis. | E11: =IF($A11="","",IF(TRIM(SUBSTITUTE(D11,CHAR(10)," "))="",0,LEN(TRIM(SUBSTITUTE(D11,CHAR(10)," ")))-LEN(SUBSTITUTE(TRIM(SUBSTITUTE(D11,CHAR(10)," "))," ",""))+1)) -> 11 | F11: On 1 November 1755, All Saints' Day, King José I heard Mass at sunrise and left Lisbon, because a daughter wanted to spend the holiday outside the city. At 9:40 the earthquake hit; the churches were full. A tsunami and days of fire followed; tens of thousands died. The king lived, but afterwards feared living within walls, and the court moved into tents on the hills of Ajuda. | G11: =IF($A11="","",IF(TRIM(SUBSTITUTE(F11,CHAR(10)," "))="",0,LEN(TRIM(SUBSTITUTE(F11,CHAR(10)," ")))-LEN(SUBSTITUTE(TRIM(SUBSTITUTE(F11,CHAR(10)," "))," ",""))+1)) -> 68 | H11: A 1 de novembro de 1755, Dia de Todos os Santos, D. José I ouviu missa logo de manhã e saiu de Lisboa, porque uma filha queria passar o feriado fora. Às 9h40, o terramoto; as igrejas estavam cheias. Seguiram-se o tsunami e dias de fogo, e morreram dezenas de milhares. O rei escapou, mas ficou com medo de paredes, e a corte mudou-se para tendas na Ajuda. | I11: =IF($A11="","",IF(TRIM(SUBSTITUTE(H11,CHAR(10)," "))="",0,LEN(TRIM(SUBSTITUTE(H11,CHAR(10)," ")))-LEN(SUBSTITUTE(TRIM(SUBSTITUTE(H11,CHAR(10)," "))," ",""))+1)) -> 68 | J11: Numbers are uncertain. Economic historian Álvaro Pereira estimates 30,000–40,000 deaths in Lisbon and 40,000–50,000 across Portugal, Spain and Morocco; other estimates range from 10,000 to 100,000. Wave heights are disputed too: a study of primary documents says long-repeated figures, such as 14–16 m at Tangier, should be abandoned. Pombal, the king's chief minister, reportedly said: bury the dead and heal the living. Records show he ordered the bodies removed the very next day, to prevent plague. The king wrote to his brother-in-law in Spain that he had no house, no servants, no subjects, no money, no bread. Today the roofless nave of the Carmo convent, founded by Nuno Álvares Pereira of Aljubarrota fame, serves as the memorial. | K11: =IF($A11="","",IF(TRIM(SUBSTITUTE(J11,CHAR(10)," "))="",0,LEN(TRIM(SUBSTITUTE(J11,CHAR(10)," ")))-LEN(SUBSTITUTE(TRIM(SUBSTITUTE(J11,CHAR(10)," "))," ",""))+1)) -> 117 | L11: Os números são incertos. O historiador de economia Álvaro Pereira estima entre 30 000 e 40 000 mortos em Lisboa e entre 40 000 e 50 000 em Portugal, Espanha e Marrocos; outras estimativas vão dos 10 000 aos 100 000. Também as alturas das ondas são discutidas: um estudo feito a partir de documentos da época diz que valores muito repetidos, como os 14 a 16 metros em Tânger, devem ser postos de parte. Pombal, o ministro do rei, terá dito: enterrar os mortos e tratar dos vivos. Os registos mostram que mandou retirar os corpos logo no dia seguinte, para evitar a peste. O rei escreveu ao cunhado, em Espanha, que ficara sem casa, sem criados, sem súbditos, sem dinheiro e sem pão. Hoje, a nave sem telhado do Convento do Carmo, fundado pelo vencedor de Aljubarrota, é o memorial do terramoto. | M11: =IF($A11="","",IF(TRIM(SUBSTITUTE(L11,CHAR(10)," "))="",0,LEN(TRIM(SUBSTITUTE(L11,CHAR(10)," ")))-LEN(SUBSTITUTE(TRIM(SUBSTITUTE(L11,CHAR(10)," "))," ",""))+1)) -> 144 | N11: Король уехал из Лиссабона в то утро, потому что дочь попросила. | O11: =IF($A11="","",IF(TRIM(SUBSTITUTE(N11,CHAR(10)," "))="",0,LEN(TRIM(SUBSTITUTE(N11,CHAR(10)," ")))-LEN(SUBSTITUTE(TRIM(SUBSTITUTE(N11,CHAR(10)," "))," ",""))+1)) -> 11 | P11: 1 ноября 1755 года, в День всех святых, король Жозе I выслушал мессу на рассвете и уехал из Лиссабона: одна из дочерей хотела провести праздник за городом. В 9:40 началось землетрясение, церкви были полны. Затем пришли цунами и несколько дней пожаров, погибли десятки тысяч человек. Король остался жив, но с тех пор боялся жить в стенах, и двор переехал в палатки на холмах Ажуды. | Q11: =IF($A11="","",IF(TRIM(SUBSTITUTE(P11,CHAR(10)," "))="",0,LEN(TRIM(SUBSTITUTE(P11,CHAR(10)," ")))-LEN(SUBSTITUTE(TRIM(SUBSTITUTE(P11,CHAR(10)," "))," ",""))+1)) -> 64 | R11: Цифры неточны. Историк экономики Альваро Перейра оценивает число погибших в 30 000–40 000 в Лиссабоне и 40 000–50 000 в Португалии, Испании и Марокко; другие оценки колеблются от 10 000 до 100 000. Высоты волн тоже оспариваются: исследование по документам эпохи говорит, что давно повторяемые цифры, например 14–16 м в Танжере, нужно отбросить. Помбал, главный министр короля, якобы сказал: хоронить мёртвых и лечить живых. Записи показывают, что уже на следующий день он приказал убрать тела, чтобы предотвратить чуму. Король написал шурину в Испанию, что у него нет ни дома, ни слуг, ни подданных, ни денег, ни хлеба. Сегодня неф монастыря Кармо без крыши, основанного победителем при Алжубарроте Нуну Алваришем Перейрой, служит мемориалом. | S11: =IF($A11="","",IF(TRIM(SUBSTITUTE(R11,CHAR(10)," "))="",0,LEN(TRIM(SUBSTITUTE(R11,CHAR(10)," ")))-LEN(SUBSTITUTE(TRIM(SUBSTITUTE(R11,CHAR(10)," "))," ",""))+1)) -> 112 | T11: Версия 2 внедрена: человек в центре (король уехал из города из-за дочери), без шуток, без громких слов. ⚠ Письмо короля к Фердинанду VI (дом, слуги, подданные, деньги, хлеб): один источник (New Criterion), нужен второй (Molesky, This Gulf of Fire). Фраза Помбала приписывается, поэтому в тексте «reportedly»; документировано, что он распорядился убрать тела 2 ноября. Высоту цунами в Лиссабоне по-прежнему не пишем. «Страх перед стенами» и палатки в Ажуде: Wikipedia; «отказывался спать в доме всю жизнь» из слабого источника, не использовано. [PT переписан отдельно по-европейски, не переводом.] [RU добавлен 16.10.2026: рабочий язык для вычитки, на сайте появится после переключателя.]
A12: ponte-das-barcas-1809 | B12: Thousands fled over a bridge made of boats. It gave way. | C12: =IF($A12="","",IF(TRIM(SUBSTITUTE(B12,CHAR(10)," "))="",0,LEN(TRIM(SUBSTITUTE(B12,CHAR(10)," ")))-LEN(SUBSTITUTE(TRIM(SUBSTITUTE(B12,CHAR(10)," "))," ",""))+1)) -> 11 | D12: Milhares fugiram por uma ponte de barcos. A ponte cedeu. | E12: =IF($A12="","",IF(TRIM(SUBSTITUTE(D12,CHAR(10)," "))="",0,LEN(TRIM(SUBSTITUTE(D12,CHAR(10)," ")))-LEN(SUBSTITUTE(TRIM(SUBSTITUTE(D12,CHAR(10)," "))," ",""))+1)) -> 10 | F12: In March 1809, French troops under Marshal Soult took Porto. In panic, residents fled toward Gaia over the Ponte das Barcas, a floating bridge of boats built in 1806. Chased by soldiers, the crowd packed onto the planks until the bridge gave way. Estimates of the dead run from several hundred to over 4,000. | G12: =IF($A12="","",IF(TRIM(SUBSTITUTE(F12,CHAR(10)," "))="",0,LEN(TRIM(SUBSTITUTE(F12,CHAR(10)," ")))-LEN(SUBSTITUTE(TRIM(SUBSTITUTE(F12,CHAR(10)," "))," ",""))+1)) -> 54 | H12: Em março de 1809, as tropas francesas do marechal Soult tomaram o Porto. Em pânico, os moradores fugiram para Gaia pela Ponte das Barcas, uma ponte flutuante de barcaças construída em 1806. Perseguida pelos soldados, a multidão apinhou-se nas tábuas até a ponte ceder. As estimativas dos mortos vão de algumas centenas a mais de 4000. | I12: =IF($A12="","",IF(TRIM(SUBSTITUTE(H12,CHAR(10)," "))="",0,LEN(TRIM(SUBSTITUTE(H12,CHAR(10)," ")))-LEN(SUBSTITUTE(TRIM(SUBSTITUTE(H12,CHAR(10)," "))," ",""))+1)) -> 56 | J12: The Ponte das Barcas had 20 barges joined by cables and covered with planks. In Porto it is simply 'the Disaster'. Its memorial on the Ribeira, the Alminhas da Ponte ('little souls of the bridge'), has had a bronze relief by the sculptor José Joaquim Teixeira Lopes since 1897, and candles are kept burning there. The church of São José das Taipas also serves as a memorial, and every 29 March a Mass is said for the victims. The exact number of dead was never established. | K12: =IF($A12="","",IF(TRIM(SUBSTITUTE(J12,CHAR(10)," "))="",0,LEN(TRIM(SUBSTITUTE(J12,CHAR(10)," ")))-LEN(SUBSTITUTE(TRIM(SUBSTITUTE(J12,CHAR(10)," "))," ",""))+1)) -> 86 | L12: A Ponte das Barcas tinha vinte barcaças ligadas por cabos e cobertas de pranchas. No Porto, é simplesmente «o Desastre». O memorial na Ribeira, as Alminhas da Ponte, tem desde 1897 um baixo-relevo em bronze do escultor José Joaquim Teixeira Lopes, e há sempre velas acesas. A Igreja de São José das Taipas também serve de memorial, e todos os anos, a 29 de março, diz-se missa pelas vítimas. O número exato de mortos nunca foi apurado. | M12: =IF($A12="","",IF(TRIM(SUBSTITUTE(L12,CHAR(10)," "))="",0,LEN(TRIM(SUBSTITUTE(L12,CHAR(10)," ")))-LEN(SUBSTITUTE(TRIM(SUBSTITUTE(L12,CHAR(10)," "))," ",""))+1)) -> 77 | N12: Тысячи бежали по мосту из лодок. Он не выдержал. | O12: =IF($A12="","",IF(TRIM(SUBSTITUTE(N12,CHAR(10)," "))="",0,LEN(TRIM(SUBSTITUTE(N12,CHAR(10)," ")))-LEN(SUBSTITUTE(TRIM(SUBSTITUTE(N12,CHAR(10)," "))," ",""))+1)) -> 9 | P12: В марте 1809 года французские войска маршала Сульта взяли Порту. В панике жители бросились в сторону Гаи по мосту Понте-даш-Баркаш, плавучему мосту из лодок, построенному в 1806 году. Преследуемая солдатами толпа набилась на доски, пока мост не рухнул. Оценки числа погибших колеблются от нескольких сотен до более чем 4000. | Q12: =IF($A12="","",IF(TRIM(SUBSTITUTE(P12,CHAR(10)," "))="",0,LEN(TRIM(SUBSTITUTE(P12,CHAR(10)," ")))-LEN(SUBSTITUTE(TRIM(SUBSTITUTE(P12,CHAR(10)," "))," ",""))+1)) -> 49 | R12: У Понте-даш-Баркаш было 20 барж, соединённых канатами и покрытых досками. В Порту её называют просто «Бедствие». На мемориале на набережной Рибейра, Алминьяш-да-Понте («маленькие души моста»), с 1897 года есть бронзовый барельеф скульптора Жозе Жоакина Тейшейры Лопеша, и там всегда горят свечи. Церковь Сан-Жозе-даш-Тайпаш тоже служит мемориалом, а каждый год 29 марта служат мессу по жертвам. Точное число погибших так и не установили. | S12: =IF($A12="","",IF(TRIM(SUBSTITUTE(R12,CHAR(10)," "))="",0,LEN(TRIM(SUBSTITUTE(R12,CHAR(10)," ")))-LEN(SUBSTITUTE(TRIM(SUBSTITUTE(R12,CHAR(10)," "))," ",""))+1)) -> 62 | T12: Запасной крючок: «A ponte era de barcos. O medo era de todos.» ⚠ Формулировка «gave way / ceder»: Infopédia (не выдержала веса толпы); версия «под огнём французов» в документе не подтверждена. ⚠ «No exact count exists»: утверждение автора, подтвердить научной работой (academia.edu 1772346, статья о картине дезастре). [PT написан отдельно по-европейски.] [Перепроверка 16.10.2026] Число погибших в истории было «4000–5000»: слишком уверенно. Wikipedia: точное число неизвестно, обычно ≈4000; DN (Germano Silva): историки от «больших сотен» до более 4000. Теперь «от нескольких сотен до более 4000». Свечи у барельефа и ежегодная месса 29 марта: DN. «Simply the Disaster»: блог Portoalities, слабый источник. Церковь São José das Taipas как место памяти: Wikipedia (останки жертв, картина на Altar das Almas). [RU добавлен 16.10.2026: рабочий язык для вычитки, на сайте появится после переключателя.]
A13: motim-companhia-1757 | B13: Porto rose against the king's minister, shouting 'Long live the king!' | C13: =IF($A13="","",IF(TRIM(SUBSTITUTE(B13,CHAR(10)," "))="",0,LEN(TRIM(SUBSTITUTE(B13,CHAR(10)," ")))-LEN(SUBSTITUTE(TRIM(SUBSTITUTE(B13,CHAR(10)," "))," ",""))+1)) -> 11 | D13: O Porto revoltou-se contra o ministro do rei, a gritar «Viva el-Rei!» | E13: =IF($A13="","",IF(TRIM(SUBSTITUTE(D13,CHAR(10)," "))="",0,LEN(TRIM(SUBSTITUTE(D13,CHAR(10)," ")))-LEN(SUBSTITUTE(TRIM(SUBSTITUTE(D13,CHAR(10)," "))," ",""))+1)) -> 12 | F13: On Ash Wednesday, 23 February 1757, crowds filled the streets of Porto, shouting for the king and against the new Wine Company. Tavern-keepers saw only a monopoly. People roughed up a judge and wrecked property. Pombal answered with troops and trials. By October, between 14 and 17 people were put to death. | G13: =IF($A13="","",IF(TRIM(SUBSTITUTE(F13,CHAR(10)," "))="",0,LEN(TRIM(SUBSTITUTE(F13,CHAR(10)," ")))-LEN(SUBSTITUTE(TRIM(SUBSTITUTE(F13,CHAR(10)," "))," ",""))+1)) -> 52 | H13: Na quarta-feira de cinzas, 23 de fevereiro de 1757, a multidão encheu as ruas do Porto a gritar pelo rei e contra a nova Companhia do vinho. Os taberneiros só viam um monopólio. Agrediram um juiz e destruíram bens. Pombal respondeu com tropas e julgamentos. Em outubro, entre 14 e 17 pessoas foram executadas. | I13: =IF($A13="","",IF(TRIM(SUBSTITUTE(H13,CHAR(10)," "))="",0,LEN(TRIM(SUBSTITUTE(H13,CHAR(10)," ")))-LEN(SUBSTITUTE(TRIM(SUBSTITUTE(H13,CHAR(10)," "))," ",""))+1)) -> 54 | J13: In Portuguese the riot is the Motim da Companhia. Troops and martial law followed. Counts of the executed differ, from 14 to 17 in the sources we found; one lists 13 men and four women on 14 October 1757. Behind the anger lay prices and control: the Company decided who could buy and sell Douro wine, and English traders, Douro growers and Porto's tavern-keepers all had grievances. The Company outlived Pombal by far: its name and trademark are still in use today. How it began, and the stones that marked its borders, are told on another card. | K13: =IF($A13="","",IF(TRIM(SUBSTITUTE(J13,CHAR(10)," "))="",0,LEN(TRIM(SUBSTITUTE(J13,CHAR(10)," ")))-LEN(SUBSTITUTE(TRIM(SUBSTITUTE(J13,CHAR(10)," "))," ",""))+1)) -> 97 | L13: Em Portugal, a revolta chama-se Motim da Companhia. Seguiram-se tropas e lei marcial. As contagens dos executados variam, de 14 a 17 nas fontes que encontrámos; uma indica 13 homens e quatro mulheres, a 14 de outubro de 1757. Por trás da raiva estavam preços e controlo: a Companhia decidia quem comprava e vendia vinho do Douro, e ingleses, lavradores do Douro e taberneiros do Porto tinham queixas. A Companhia sobreviveu muito a Pombal: o nome e a marca ainda se usam hoje. Como tudo começou, e os marcos que lhe delimitaram a região, contam-se noutro cartão. | M13: =IF($A13="","",IF(TRIM(SUBSTITUTE(L13,CHAR(10)," "))="",0,LEN(TRIM(SUBSTITUTE(L13,CHAR(10)," ")))-LEN(SUBSTITUTE(TRIM(SUBSTITUTE(L13,CHAR(10)," "))," ",""))+1)) -> 97 | N13: Порту восстал против министра, крича «Да здравствует король!» | O13: =IF($A13="","",IF(TRIM(SUBSTITUTE(N13,CHAR(10)," "))="",0,LEN(TRIM(SUBSTITUTE(N13,CHAR(10)," ")))-LEN(SUBSTITUTE(TRIM(SUBSTITUTE(N13,CHAR(10)," "))," ",""))+1)) -> 8 | P13: В пепельную среду, 23 февраля 1757 года, толпы заполнили улицы Порту с криками в защиту короля и против новой Винной компании. Хозяева таверн видели в ней только монополию. Избили судью и разгромили имущество. Помбал ответил войсками и судами. К октябрю от 14 до 17 человек были казнены. | Q13: =IF($A13="","",IF(TRIM(SUBSTITUTE(P13,CHAR(10)," "))="",0,LEN(TRIM(SUBSTITUTE(P13,CHAR(10)," ")))-LEN(SUBSTITUTE(TRIM(SUBSTITUTE(P13,CHAR(10)," "))," ",""))+1)) -> 47 | R13: По-португальски бунт называется Motim da Companhia. Затем пришли войска и военное положение. Число казнённых расходится: от 14 до 17 в найденных нами источниках, один перечисляет 13 мужчин и четырёх женщин 14 октября 1757 года. За гневом стояли цены и контроль: Компания решала, кто может покупать и продавать вино Дору, и англичане, виноделы Дору и хозяева таверн Порту имели претензии. Компания пережила Помбала намного: её название и торговая марка в ходу до сих пор. Как всё началось и какие камни отметили её границы, рассказано в другой карточке. | S13: =IF($A13="","",IF(TRIM(SUBSTITUTE(R13,CHAR(10)," "))="",0,LEN(TRIM(SUBSTITUTE(R13,CHAR(10)," ")))-LEN(SUBSTITUTE(TRIM(SUBSTITUTE(R13,CHAR(10)," "))," ",""))+1)) -> 86 | T13: Лозунг взят из научной статьи (UP): «Viva el-Rei! Morra a Companhia!». Запасной крючок: «Gritavam pelo rei e contra a Companhia do rei.» (игра: компанию создал министр короля). ⚠ Дата 23 февраля = Пепельная среда (UP). Цифры казней из блога, перепроверить. [PT написан отдельно по-европейски.] [Перепроверка 16.10.2026] АНАХРОНИЗМ исправлен: в 1756 он ещё не маркиз («the future Marquis of Pombal»). Число казнённых: 17 (13 м., 4 ж.) только в блоге Executed Today, в слайде UMN 14 повешенных и 400 сосланных или осуждённых: в тексте диапазон 14–17, пока нет Ribeiro da Silva. Фраза про «первую демаркированную зону» перенесена из истории в «Подробнее» (в источниках звучит как «часто называют»). Основание Компании: 10.09.1756 (сайт RCV). [RU добавлен 16.10.2026: рабочий язык для вычитки, на сайте появится после переключателя.]
A14: legiao-portuguesa-1812 | B14: After Russia, about a hundred of Napoleon's Portuguese Legion were left. | C14: =IF($A14="","",IF(TRIM(SUBSTITUTE(B14,CHAR(10)," "))="",0,LEN(TRIM(SUBSTITUTE(B14,CHAR(10)," ")))-LEN(SUBSTITUTE(TRIM(SUBSTITUTE(B14,CHAR(10)," "))," ",""))+1)) -> 11 | D14: Depois da Rússia, restavam uns cem homens da Legião de Napoleão. | E14: =IF($A14="","",IF(TRIM(SUBSTITUTE(D14,CHAR(10)," "))="",0,LEN(TRIM(SUBSTITUTE(D14,CHAR(10)," ")))-LEN(SUBSTITUTE(TRIM(SUBSTITUTE(D14,CHAR(10)," "))," ",""))+1)) -> 11 | F14: In 1808 the French occupiers disbanded Portugal's army, then built a legion from its units. About 9,000 men, led by the Marquis of Alorna, marched off to France as the Portuguese Legion. They fought at Wagram in 1809 and in 1812 went to Russia, to Smolensk and Borodino. By 1813 only about a hundred were left. | G14: =IF($A14="","",IF(TRIM(SUBSTITUTE(F14,CHAR(10)," "))="",0,LEN(TRIM(SUBSTITUTE(F14,CHAR(10)," ")))-LEN(SUBSTITUTE(TRIM(SUBSTITUTE(F14,CHAR(10)," "))," ",""))+1)) -> 56 | H14: Em 1808, os ocupantes franceses dissolveram o exército português e formaram uma legião com as suas unidades. Cerca de 9000 homens, comandados pelo marquês de Alorna, partiram para França como Legião Portuguesa. Combateram em Wagram, em 1809, e em 1812 foram para a Rússia, a Smolensk e a Borodino. Em 1813, restavam apenas uns cem. | I14: =IF($A14="","",IF(TRIM(SUBSTITUTE(H14,CHAR(10)," "))="",0,LEN(TRIM(SUBSTITUTE(H14,CHAR(10)," ")))-LEN(SUBSTITUTE(TRIM(SUBSTITUTE(H14,CHAR(10)," "))," ",""))+1)) -> 55 | J14: The Legion was organised from February 1808 and left for Spain in April; a decree of 5 May made it official. In 1810 sixty of its men received the Legion of Honour. Its second-in-command, Gomes Freire de Andrade, had earlier served in Catherine II's Russian army. After Russia the survivors fought at Lützen and Bautzen, and when Napoleon dissolved the 'foreign' armies in November 1813, the rest joined French engineer units. Sources put the Legion's size at 8,000 to 12,000, and differ on its losses and on how willingly its men served. Its commander, the Marquis of Alorna, died at Königsberg. | K14: =IF($A14="","",IF(TRIM(SUBSTITUTE(J14,CHAR(10)," "))="",0,LEN(TRIM(SUBSTITUTE(J14,CHAR(10)," ")))-LEN(SUBSTITUTE(TRIM(SUBSTITUTE(J14,CHAR(10)," "))," ",""))+1)) -> 101 | L14: A Legião foi organizada a partir de fevereiro de 1808 e partiu para Espanha em abril; um decreto de 5 de maio tornou-a oficial. Em 1810, sessenta dos seus homens receberam a Legião de Honra. O segundo-comandante, Gomes Freire de Andrade, servira antes no exército russo de Catarina II. Depois da Rússia, os sobreviventes combateram em Lützen e Bautzen, e quando Napoleão dissolveu os exércitos «estrangeiros», em novembro de 1813, os restantes foram integrados em corpos de sapadores franceses. As fontes dão à Legião entre 8000 e 12 000 homens e divergem quanto às perdas e à vontade com que os homens serviram. O comandante, o marquês de Alorna, morreu em Königsberg. | M14: =IF($A14="","",IF(TRIM(SUBSTITUTE(L14,CHAR(10)," "))="",0,LEN(TRIM(SUBSTITUTE(L14,CHAR(10)," ")))-LEN(SUBSTITUTE(TRIM(SUBSTITUTE(L14,CHAR(10)," "))," ",""))+1)) -> 112 | N14: Из португальского легиона Наполеона после России осталась примерно сотня. | O14: =IF($A14="","",IF(TRIM(SUBSTITUTE(N14,CHAR(10)," "))="",0,LEN(TRIM(SUBSTITUTE(N14,CHAR(10)," ")))-LEN(SUBSTITUTE(TRIM(SUBSTITUTE(N14,CHAR(10)," "))," ",""))+1)) -> 9 | P14: В 1808 году французские оккупанты распустили португальскую армию, а затем набрали из её частей легион. Около 9000 человек под командованием маркиза д’Алорна отправились во Францию как Португальский легион. Они сражались при Ваграме в 1809 году, а в 1812 году ушли в Россию, под Смоленск и Бородино. К 1813 году в строю осталось около ста человек. | Q14: =IF($A14="","",IF(TRIM(SUBSTITUTE(P14,CHAR(10)," "))="",0,LEN(TRIM(SUBSTITUTE(P14,CHAR(10)," ")))-LEN(SUBSTITUTE(TRIM(SUBSTITUTE(P14,CHAR(10)," "))," ",""))+1)) -> 55 | R14: Легион был организован с февраля 1808 года и выступил в Испанию в апреле; декрет от 5 мая сделал его официальным. В 1810 году шестьдесят его солдат получили орден Почётного легиона. Его заместитель, Гомеш Фрейре де Андраде, раньше служил в русской армии Екатерины II. После России уцелевшие сражались при Лютцене и Баутцене, а когда Наполеон в ноябре 1813 года распустил «иностранные» армии, остальные влились во французские сапёрные части. Источники оценивают размер Легиона от 8000 до 12 000 человек и расходятся в оценке потерь и в том, насколько охотно служили его люди. Его командир, маркиз д’Алорна, умер в Кёнигсберге. | S14: =IF($A14="","",IF(TRIM(SUBSTITUTE(R14,CHAR(10)," "))="",0,LEN(TRIM(SUBSTITUTE(R14,CHAR(10)," ")))-LEN(SUBSTITUTE(TRIM(SUBSTITUTE(R14,CHAR(10)," "))," ",""))+1)) -> 97 | T14: Запасной крючок: «Portugal tinha dois exércitos em 1812: um contra Napoleão, outro com ele.» ⚠ Выражение «best units»: Wikipedia («the best units of the disbanded Portuguese Army»). «Выжившие»: Infopédia пишет о ~100 в 1813, не о возвращении из России: в тексте так и сказано. Исправление к списку: «из России вернулось несколько сотен» не подтвердилось. [PT написан отдельно по-европейски.] [Перепроверка 16.10.2026] Размер Легиона: 9000 (Wikipedia, Lemos Pires), 8000 (weaponsandwarfare), 12 000 (Observador): в тексте диапазон. Смерть Алорны в Кёнигсберге: работа Lemos Pires со ссылкой на Boppe (1897), второго источника нет. «60 крестов Почётного легиона» из Infopédia: в моих проверках не открывалось, пометка остаётся. [RU добавлен 16.10.2026: рабочий язык для вычитки, на сайте появится после переключателя.]
C15: =IF($A15="","",IF(TRIM(SUBSTITUTE(B15,CHAR(10)," "))="",0,LEN(TRIM(SUBSTITUTE(B15,CHAR(10)," ")))-LEN(SUBSTITUTE(TRIM(SUBSTITUTE(B15,CHAR(10)," "))," ",""))+1)) | E15: =IF($A15="","",IF(TRIM(SUBSTITUTE(D15,CHAR(10)," "))="",0,LEN(TRIM(SUBSTITUTE(D15,CHAR(10)," ")))-LEN(SUBSTITUTE(TRIM(SUBSTITUTE(D15,CHAR(10)," "))," ",""))+1)) | G15: =IF($A15="","",IF(TRIM(SUBSTITUTE(F15,CHAR(10)," "))="",0,LEN(TRIM(SUBSTITUTE(F15,CHAR(10)," ")))-LEN(SUBSTITUTE(TRIM(SUBSTITUTE(F15,CHAR(10)," "))," ",""))+1)) | I15: =IF($A15="","",IF(TRIM(SUBSTITUTE(H15,CHAR(10)," "))="",0,LEN(TRIM(SUBSTITUTE(H15,CHAR(10)," ")))-LEN(SUBSTITUTE(TRIM(SUBSTITUTE(H15,CHAR(10)," "))," ",""))+1)) | K15: =IF($A15="","",IF(TRIM(SUBSTITUTE(J15,CHAR(10)," "))="",0,LEN(TRIM(SUBSTITUTE(J15,CHAR(10)," ")))-LEN(SUBSTITUTE(TRIM(SUBSTITUTE(J15,CHAR(10)," "))," ",""))+1)) | M15: =IF($A15="","",IF(TRIM(SUBSTITUTE(L15,CHAR(10)," "))="",0,LEN(TRIM(SUBSTITUTE(L15,CHAR(10)," ")))-LEN(SUBSTITUTE(TRIM(SUBSTITUTE(L15,CHAR(10)," "))," ",""))+1)) | O15: =IF($A15="","",IF(TRIM(SUBSTITUTE(N15,CHAR(10)," "))="",0,LEN(TRIM(SUBSTITUTE(N15,CHAR(10)," ")))-LEN(SUBSTITUTE(TRIM(SUBSTITUTE(N15,CHAR(10)," "))," ",""))+1)) | Q15: =IF($A15="","",IF(TRIM(SUBSTITUTE(P15,CHAR(10)," "))="",0,LEN(TRIM(SUBSTITUTE(P15,CHAR(10)," ")))-LEN(SUBSTITUTE(TRIM(SUBSTITUTE(P15,CHAR(10)," "))," ",""))+1)) | S15: =IF($A15="","",IF(TRIM(SUBSTITUTE(R15,CHAR(10)," "))="",0,LEN(TRIM(SUBSTITUTE(R15,CHAR(10)," ")))-LEN(SUBSTITUTE(TRIM(SUBSTITUTE(R15,CHAR(10)," "))," ",""))+1))
C16: =IF($A16="","",IF(TRIM(SUBSTITUTE(B16,CHAR(10)," "))="",0,LEN(TRIM(SUBSTITUTE(B16,CHAR(10)," ")))-LEN(SUBSTITUTE(TRIM(SUBSTITUTE(B16,CHAR(10)," "))," ",""))+1)) | E16: =IF($A16="","",IF(TRIM(SUBSTITUTE(D16,CHAR(10)," "))="",0,LEN(TRIM(SUBSTITUTE(D16,CHAR(10)," ")))-LEN(SUBSTITUTE(TRIM(SUBSTITUTE(D16,CHAR(10)," "))," ",""))+1)) | G16: =IF($A16="","",IF(TRIM(SUBSTITUTE(F16,CHAR(10)," "))="",0,LEN(TRIM(SUBSTITUTE(F16,CHAR(10)," ")))-LEN(SUBSTITUTE(TRIM(SUBSTITUTE(F16,CHAR(10)," "))," ",""))+1)) | I16: =IF($A16="","",IF(TRIM(SUBSTITUTE(H16,CHAR(10)," "))="",0,LEN(TRIM(SUBSTITUTE(H16,CHAR(10)," ")))-LEN(SUBSTITUTE(TRIM(SUBSTITUTE(H16,CHAR(10)," "))," ",""))+1)) | K16: =IF($A16="","",IF(TRIM(SUBSTITUTE(J16,CHAR(10)," "))="",0,LEN(TRIM(SUBSTITUTE(J16,CHAR(10)," ")))-LEN(SUBSTITUTE(TRIM(SUBSTITUTE(J16,CHAR(10)," "))," ",""))+1)) | M16: =IF($A16="","",IF(TRIM(SUBSTITUTE(L16,CHAR(10)," "))="",0,LEN(TRIM(SUBSTITUTE(L16,CHAR(10)," ")))-LEN(SUBSTITUTE(TRIM(SUBSTITUTE(L16,CHAR(10)," "))," ",""))+1)) | O16: =IF($A16="","",IF(TRIM(SUBSTITUTE(N16,CHAR(10)," "))="",0,LEN(TRIM(SUBSTITUTE(N16,CHAR(10)," ")))-LEN(SUBSTITUTE(TRIM(SUBSTITUTE(N16,CHAR(10)," "))," ",""))+1)) | Q16: =IF($A16="","",IF(TRIM(SUBSTITUTE(P16,CHAR(10)," "))="",0,LEN(TRIM(SUBSTITUTE(P16,CHAR(10)," ")))-LEN(SUBSTITUTE(TRIM(SUBSTITUTE(P16,CHAR(10)," "))," ",""))+1)) | S16: =IF($A16="","",IF(TRIM(SUBSTITUTE(R16,CHAR(10)," "))="",0,LEN(TRIM(SUBSTITUTE(R16,CHAR(10)," ")))-LEN(SUBSTITUTE(TRIM(SUBSTITUTE(R16,CHAR(10)," "))," ",""))+1))
C17: =IF($A17="","",IF(TRIM(SUBSTITUTE(B17,CHAR(10)," "))="",0,LEN(TRIM(SUBSTITUTE(B17,CHAR(10)," ")))-LEN(SUBSTITUTE(TRIM(SUBSTITUTE(B17,CHAR(10)," "))," ",""))+1)) | E17: =IF($A17="","",IF(TRIM(SUBSTITUTE(D17,CHAR(10)," "))="",0,LEN(TRIM(SUBSTITUTE(D17,CHAR(10)," ")))-LEN(SUBSTITUTE(TRIM(SUBSTITUTE(D17,CHAR(10)," "))," ",""))+1)) | G17: =IF($A17="","",IF(TRIM(SUBSTITUTE(F17,CHAR(10)," "))="",0,LEN(TRIM(SUBSTITUTE(F17,CHAR(10)," ")))-LEN(SUBSTITUTE(TRIM(SUBSTITUTE(F17,CHAR(10)," "))," ",""))+1)) | I17: =IF($A17="","",IF(TRIM(SUBSTITUTE(H17,CHAR(10)," "))="",0,LEN(TRIM(SUBSTITUTE(H17,CHAR(10)," ")))-LEN(SUBSTITUTE(TRIM(SUBSTITUTE(H17,CHAR(10)," "))," ",""))+1)) | K17: =IF($A17="","",IF(TRIM(SUBSTITUTE(J17,CHAR(10)," "))="",0,LEN(TRIM(SUBSTITUTE(J17,CHAR(10)," ")))-LEN(SUBSTITUTE(TRIM(SUBSTITUTE(J17,CHAR(10)," "))," ",""))+1)) | M17: =IF($A17="","",IF(TRIM(SUBSTITUTE(L17,CHAR(10)," "))="",0,LEN(TRIM(SUBSTITUTE(L17,CHAR(10)," ")))-LEN(SUBSTITUTE(TRIM(SUBSTITUTE(L17,CHAR(10)," "))," ",""))+1)) | O17: =IF($A17="","",IF(TRIM(SUBSTITUTE(N17,CHAR(10)," "))="",0,LEN(TRIM(SUBSTITUTE(N17,CHAR(10)," ")))-LEN(SUBSTITUTE(TRIM(SUBSTITUTE(N17,CHAR(10)," "))," ",""))+1)) | Q17: =IF($A17="","",IF(TRIM(SUBSTITUTE(P17,CHAR(10)," "))="",0,LEN(TRIM(SUBSTITUTE(P17,CHAR(10)," ")))-LEN(SUBSTITUTE(TRIM(SUBSTITUTE(P17,CHAR(10)," "))," ",""))+1)) | S17: =IF($A17="","",IF(TRIM(SUBSTITUTE(R17,CHAR(10)," "))="",0,LEN(TRIM(SUBSTITUTE(R17,CHAR(10)," ")))-LEN(SUBSTITUTE(TRIM(SUBSTITUTE(R17,CHAR(10)," "))," ",""))+1))
C18: =IF($A18="","",IF(TRIM(SUBSTITUTE(B18,CHAR(10)," "))="",0,LEN(TRIM(SUBSTITUTE(B18,CHAR(10)," ")))-LEN(SUBSTITUTE(TRIM(SUBSTITUTE(B18,CHAR(10)," "))," ",""))+1)) | E18: =IF($A18="","",IF(TRIM(SUBSTITUTE(D18,CHAR(10)," "))="",0,LEN(TRIM(SUBSTITUTE(D18,CHAR(10)," ")))-LEN(SUBSTITUTE(TRIM(SUBSTITUTE(D18,CHAR(10)," "))," ",""))+1)) | G18: =IF($A18="","",IF(TRIM(SUBSTITUTE(F18,CHAR(10)," "))="",0,LEN(TRIM(SUBSTITUTE(F18,CHAR(10)," ")))-LEN(SUBSTITUTE(TRIM(SUBSTITUTE(F18,CHAR(10)," "))," ",""))+1)) | I18: =IF($A18="","",IF(TRIM(SUBSTITUTE(H18,CHAR(10)," "))="",0,LEN(TRIM(SUBSTITUTE(H18,CHAR(10)," ")))-LEN(SUBSTITUTE(TRIM(SUBSTITUTE(H18,CHAR(10)," "))," ",""))+1)) | K18: =IF($A18="","",IF(TRIM(SUBSTITUTE(J18,CHAR(10)," "))="",0,LEN(TRIM(SUBSTITUTE(J18,CHAR(10)," ")))-LEN(SUBSTITUTE(TRIM(SUBSTITUTE(J18,CHAR(10)," "))," ",""))+1)) | M18: =IF($A18="","",IF(TRIM(SUBSTITUTE(L18,CHAR(10)," "))="",0,LEN(TRIM(SUBSTITUTE(L18,CHAR(10)," ")))-LEN(SUBSTITUTE(TRIM(SUBSTITUTE(L18,CHAR(10)," "))," ",""))+1)) | O18: =IF($A18="","",IF(TRIM(SUBSTITUTE(N18,CHAR(10)," "))="",0,LEN(TRIM(SUBSTITUTE(N18,CHAR(10)," ")))-LEN(SUBSTITUTE(TRIM(SUBSTITUTE(N18,CHAR(10)," "))," ",""))+1)) | Q18: =IF($A18="","",IF(TRIM(SUBSTITUTE(P18,CHAR(10)," "))="",0,LEN(TRIM(SUBSTITUTE(P18,CHAR(10)," ")))-LEN(SUBSTITUTE(TRIM(SUBSTITUTE(P18,CHAR(10)," "))," ",""))+1)) | S18: =IF($A18="","",IF(TRIM(SUBSTITUTE(R18,CHAR(10)," "))="",0,LEN(TRIM(SUBSTITUTE(R18,CHAR(10)," ")))-LEN(SUBSTITUTE(TRIM(SUBSTITUTE(R18,CHAR(10)," "))," ",""))+1))
C19: =IF($A19="","",IF(TRIM(SUBSTITUTE(B19,CHAR(10)," "))="",0,LEN(TRIM(SUBSTITUTE(B19,CHAR(10)," ")))-LEN(SUBSTITUTE(TRIM(SUBSTITUTE(B19,CHAR(10)," "))," ",""))+1)) | E19: =IF($A19="","",IF(TRIM(SUBSTITUTE(D19,CHAR(10)," "))="",0,LEN(TRIM(SUBSTITUTE(D19,CHAR(10)," ")))-LEN(SUBSTITUTE(TRIM(SUBSTITUTE(D19,CHAR(10)," "))," ",""))+1)) | G19: =IF($A19="","",IF(TRIM(SUBSTITUTE(F19,CHAR(10)," "))="",0,LEN(TRIM(SUBSTITUTE(F19,CHAR(10)," ")))-LEN(SUBSTITUTE(TRIM(SUBSTITUTE(F19,CHAR(10)," "))," ",""))+1)) | I19: =IF($A19="","",IF(TRIM(SUBSTITUTE(H19,CHAR(10)," "))="",0,LEN(TRIM(SUBSTITUTE(H19,CHAR(10)," ")))-LEN(SUBSTITUTE(TRIM(SUBSTITUTE(H19,CHAR(10)," "))," ",""))+1)) | K19: =IF($A19="","",IF(TRIM(SUBSTITUTE(J19,CHAR(10)," "))="",0,LEN(TRIM(SUBSTITUTE(J19,CHAR(10)," ")))-LEN(SUBSTITUTE(TRIM(SUBSTITUTE(J19,CHAR(10)," "))," ",""))+1)) | M19: =IF($A19="","",IF(TRIM(SUBSTITUTE(L19,CHAR(10)," "))="",0,LEN(TRIM(SUBSTITUTE(L19,CHAR(10)," ")))-LEN(SUBSTITUTE(TRIM(SUBSTITUTE(L19,CHAR(10)," "))," ",""))+1)) | O19: =IF($A19="","",IF(TRIM(SUBSTITUTE(N19,CHAR(10)," "))="",0,LEN(TRIM(SUBSTITUTE(N19,CHAR(10)," ")))-LEN(SUBSTITUTE(TRIM(SUBSTITUTE(N19,CHAR(10)," "))," ",""))+1)) | Q19: =IF($A19="","",IF(TRIM(SUBSTITUTE(P19,CHAR(10)," "))="",0,LEN(TRIM(SUBSTITUTE(P19,CHAR(10)," ")))-LEN(SUBSTITUTE(TRIM(SUBSTITUTE(P19,CHAR(10)," "))," ",""))+1)) | S19: =IF($A19="","",IF(TRIM(SUBSTITUTE(R19,CHAR(10)," "))="",0,LEN(TRIM(SUBSTITUTE(R19,CHAR(10)," ")))-LEN(SUBSTITUTE(TRIM(SUBSTITUTE(R19,CHAR(10)," "))," ",""))+1))
C20: =IF($A20="","",IF(TRIM(SUBSTITUTE(B20,CHAR(10)," "))="",0,LEN(TRIM(SUBSTITUTE(B20,CHAR(10)," ")))-LEN(SUBSTITUTE(TRIM(SUBSTITUTE(B20,CHAR(10)," "))," ",""))+1)) | E20: =IF($A20="","",IF(TRIM(SUBSTITUTE(D20,CHAR(10)," "))="",0,LEN(TRIM(SUBSTITUTE(D20,CHAR(10)," ")))-LEN(SUBSTITUTE(TRIM(SUBSTITUTE(D20,CHAR(10)," "))," ",""))+1)) | G20: =IF($A20="","",IF(TRIM(SUBSTITUTE(F20,CHAR(10)," "))="",0,LEN(TRIM(SUBSTITUTE(F20,CHAR(10)," ")))-LEN(SUBSTITUTE(TRIM(SUBSTITUTE(F20,CHAR(10)," "))," ",""))+1)) | I20: =IF($A20="","",IF(TRIM(SUBSTITUTE(H20,CHAR(10)," "))="",0,LEN(TRIM(SUBSTITUTE(H20,CHAR(10)," ")))-LEN(SUBSTITUTE(TRIM(SUBSTITUTE(H20,CHAR(10)," "))," ",""))+1)) | K20: =IF($A20="","",IF(TRIM(SUBSTITUTE(J20,CHAR(10)," "))="",0,LEN(TRIM(SUBSTITUTE(J20,CHAR(10)," ")))-LEN(SUBSTITUTE(TRIM(SUBSTITUTE(J20,CHAR(10)," "))," ",""))+1)) | M20: =IF($A20="","",IF(TRIM(SUBSTITUTE(L20,CHAR(10)," "))="",0,LEN(TRIM(SUBSTITUTE(L20,CHAR(10)," ")))-LEN(SUBSTITUTE(TRIM(SUBSTITUTE(L20,CHAR(10)," "))," ",""))+1)) | O20: =IF($A20="","",IF(TRIM(SUBSTITUTE(N20,CHAR(10)," "))="",0,LEN(TRIM(SUBSTITUTE(N20,CHAR(10)," ")))-LEN(SUBSTITUTE(TRIM(SUBSTITUTE(N20,CHAR(10)," "))," ",""))+1)) | Q20: =IF($A20="","",IF(TRIM(SUBSTITUTE(P20,CHAR(10)," "))="",0,LEN(TRIM(SUBSTITUTE(P20,CHAR(10)," ")))-LEN(SUBSTITUTE(TRIM(SUBSTITUTE(P20,CHAR(10)," "))," ",""))+1)) | S20: =IF($A20="","",IF(TRIM(SUBSTITUTE(R20,CHAR(10)," "))="",0,LEN(TRIM(SUBSTITUTE(R20,CHAR(10)," ")))-LEN(SUBSTITUTE(TRIM(SUBSTITUTE(R20,CHAR(10)," "))," ",""))+1))
C21: =IF($A21="","",IF(TRIM(SUBSTITUTE(B21,CHAR(10)," "))="",0,LEN(TRIM(SUBSTITUTE(B21,CHAR(10)," ")))-LEN(SUBSTITUTE(TRIM(SUBSTITUTE(B21,CHAR(10)," "))," ",""))+1)) | E21: =IF($A21="","",IF(TRIM(SUBSTITUTE(D21,CHAR(10)," "))="",0,LEN(TRIM(SUBSTITUTE(D21,CHAR(10)," ")))-LEN(SUBSTITUTE(TRIM(SUBSTITUTE(D21,CHAR(10)," "))," ",""))+1)) | G21: =IF($A21="","",IF(TRIM(SUBSTITUTE(F21,CHAR(10)," "))="",0,LEN(TRIM(SUBSTITUTE(F21,CHAR(10)," ")))-LEN(SUBSTITUTE(TRIM(SUBSTITUTE(F21,CHAR(10)," "))," ",""))+1)) | I21: =IF($A21="","",IF(TRIM(SUBSTITUTE(H21,CHAR(10)," "))="",0,LEN(TRIM(SUBSTITUTE(H21,CHAR(10)," ")))-LEN(SUBSTITUTE(TRIM(SUBSTITUTE(H21,CHAR(10)," "))," ",""))+1)) | K21: =IF($A21="","",IF(TRIM(SUBSTITUTE(J21,CHAR(10)," "))="",0,LEN(TRIM(SUBSTITUTE(J21,CHAR(10)," ")))-LEN(SUBSTITUTE(TRIM(SUBSTITUTE(J21,CHAR(10)," "))," ",""))+1)) | M21: =IF($A21="","",IF(TRIM(SUBSTITUTE(L21,CHAR(10)," "))="",0,LEN(TRIM(SUBSTITUTE(L21,CHAR(10)," ")))-LEN(SUBSTITUTE(TRIM(SUBSTITUTE(L21,CHAR(10)," "))," ",""))+1)) | O21: =IF($A21="","",IF(TRIM(SUBSTITUTE(N21,CHAR(10)," "))="",0,LEN(TRIM(SUBSTITUTE(N21,CHAR(10)," ")))-LEN(SUBSTITUTE(TRIM(SUBSTITUTE(N21,CHAR(10)," "))," ",""))+1)) | Q21: =IF($A21="","",IF(TRIM(SUBSTITUTE(P21,CHAR(10)," "))="",0,LEN(TRIM(SUBSTITUTE(P21,CHAR(10)," ")))-LEN(SUBSTITUTE(TRIM(SUBSTITUTE(P21,CHAR(10)," "))," ",""))+1)) | S21: =IF($A21="","",IF(TRIM(SUBSTITUTE(R21,CHAR(10)," "))="",0,LEN(TRIM(SUBSTITUTE(R21,CHAR(10)," ")))-LEN(SUBSTITUTE(TRIM(SUBSTITUTE(R21,CHAR(10)," "))," ",""))+1))
C22: =IF($A22="","",IF(TRIM(SUBSTITUTE(B22,CHAR(10)," "))="",0,LEN(TRIM(SUBSTITUTE(B22,CHAR(10)," ")))-LEN(SUBSTITUTE(TRIM(SUBSTITUTE(B22,CHAR(10)," "))," ",""))+1)) | E22: =IF($A22="","",IF(TRIM(SUBSTITUTE(D22,CHAR(10)," "))="",0,LEN(TRIM(SUBSTITUTE(D22,CHAR(10)," ")))-LEN(SUBSTITUTE(TRIM(SUBSTITUTE(D22,CHAR(10)," "))," ",""))+1)) | G22: =IF($A22="","",IF(TRIM(SUBSTITUTE(F22,CHAR(10)," "))="",0,LEN(TRIM(SUBSTITUTE(F22,CHAR(10)," ")))-LEN(SUBSTITUTE(TRIM(SUBSTITUTE(F22,CHAR(10)," "))," ",""))+1)) | I22: =IF($A22="","",IF(TRIM(SUBSTITUTE(H22,CHAR(10)," "))="",0,LEN(TRIM(SUBSTITUTE(H22,CHAR(10)," ")))-LEN(SUBSTITUTE(TRIM(SUBSTITUTE(H22,CHAR(10)," "))," ",""))+1)) | K22: =IF($A22="","",IF(TRIM(SUBSTITUTE(J22,CHAR(10)," "))="",0,LEN(TRIM(SUBSTITUTE(J22,CHAR(10)," ")))-LEN(SUBSTITUTE(TRIM(SUBSTITUTE(J22,CHAR(10)," "))," ",""))+1)) | M22: =IF($A22="","",IF(TRIM(SUBSTITUTE(L22,CHAR(10)," "))="",0,LEN(TRIM(SUBSTITUTE(L22,CHAR(10)," ")))-LEN(SUBSTITUTE(TRIM(SUBSTITUTE(L22,CHAR(10)," "))," ",""))+1)) | O22: =IF($A22="","",IF(TRIM(SUBSTITUTE(N22,CHAR(10)," "))="",0,LEN(TRIM(SUBSTITUTE(N22,CHAR(10)," ")))-LEN(SUBSTITUTE(TRIM(SUBSTITUTE(N22,CHAR(10)," "))," ",""))+1)) | Q22: =IF($A22="","",IF(TRIM(SUBSTITUTE(P22,CHAR(10)," "))="",0,LEN(TRIM(SUBSTITUTE(P22,CHAR(10)," ")))-LEN(SUBSTITUTE(TRIM(SUBSTITUTE(P22,CHAR(10)," "))," ",""))+1)) | S22: =IF($A22="","",IF(TRIM(SUBSTITUTE(R22,CHAR(10)," "))="",0,LEN(TRIM(SUBSTITUTE(R22,CHAR(10)," ")))-LEN(SUBSTITUTE(TRIM(SUBSTITUTE(R22,CHAR(10)," "))," ",""))+1))
C23: =IF($A23="","",IF(TRIM(SUBSTITUTE(B23,CHAR(10)," "))="",0,LEN(TRIM(SUBSTITUTE(B23,CHAR(10)," ")))-LEN(SUBSTITUTE(TRIM(SUBSTITUTE(B23,CHAR(10)," "))," ",""))+1)) | E23: =IF($A23="","",IF(TRIM(SUBSTITUTE(D23,CHAR(10)," "))="",0,LEN(TRIM(SUBSTITUTE(D23,CHAR(10)," ")))-LEN(SUBSTITUTE(TRIM(SUBSTITUTE(D23,CHAR(10)," "))," ",""))+1)) | G23: =IF($A23="","",IF(TRIM(SUBSTITUTE(F23,CHAR(10)," "))="",0,LEN(TRIM(SUBSTITUTE(F23,CHAR(10)," ")))-LEN(SUBSTITUTE(TRIM(SUBSTITUTE(F23,CHAR(10)," "))," ",""))+1)) | I23: =IF($A23="","",IF(TRIM(SUBSTITUTE(H23,CHAR(10)," "))="",0,LEN(TRIM(SUBSTITUTE(H23,CHAR(10)," ")))-LEN(SUBSTITUTE(TRIM(SUBSTITUTE(H23,CHAR(10)," "))," ",""))+1)) | K23: =IF($A23="","",IF(TRIM(SUBSTITUTE(J23,CHAR(10)," "))="",0,LEN(TRIM(SUBSTITUTE(J23,CHAR(10)," ")))-LEN(SUBSTITUTE(TRIM(SUBSTITUTE(J23,CHAR(10)," "))," ",""))+1)) | M23: =IF($A23="","",IF(TRIM(SUBSTITUTE(L23,CHAR(10)," "))="",0,LEN(TRIM(SUBSTITUTE(L23,CHAR(10)," ")))-LEN(SUBSTITUTE(TRIM(SUBSTITUTE(L23,CHAR(10)," "))," ",""))+1)) | O23: =IF($A23="","",IF(TRIM(SUBSTITUTE(N23,CHAR(10)," "))="",0,LEN(TRIM(SUBSTITUTE(N23,CHAR(10)," ")))-LEN(SUBSTITUTE(TRIM(SUBSTITUTE(N23,CHAR(10)," "))," ",""))+1)) | Q23: =IF($A23="","",IF(TRIM(SUBSTITUTE(P23,CHAR(10)," "))="",0,LEN(TRIM(SUBSTITUTE(P23,CHAR(10)," ")))-LEN(SUBSTITUTE(TRIM(SUBSTITUTE(P23,CHAR(10)," "))," ",""))+1)) | S23: =IF($A23="","",IF(TRIM(SUBSTITUTE(R23,CHAR(10)," "))="",0,LEN(TRIM(SUBSTITUTE(R23,CHAR(10)," ")))-LEN(SUBSTITUTE(TRIM(SUBSTITUTE(R23,CHAR(10)," "))," ",""))+1))
C24: =IF($A24="","",IF(TRIM(SUBSTITUTE(B24,CHAR(10)," "))="",0,LEN(TRIM(SUBSTITUTE(B24,CHAR(10)," ")))-LEN(SUBSTITUTE(TRIM(SUBSTITUTE(B24,CHAR(10)," "))," ",""))+1)) | E24: =IF($A24="","",IF(TRIM(SUBSTITUTE(D24,CHAR(10)," "))="",0,LEN(TRIM(SUBSTITUTE(D24,CHAR(10)," ")))-LEN(SUBSTITUTE(TRIM(SUBSTITUTE(D24,CHAR(10)," "))," ",""))+1)) | G24: =IF($A24="","",IF(TRIM(SUBSTITUTE(F24,CHAR(10)," "))="",0,LEN(TRIM(SUBSTITUTE(F24,CHAR(10)," ")))-LEN(SUBSTITUTE(TRIM(SUBSTITUTE(F24,CHAR(10)," "))," ",""))+1)) | I24: =IF($A24="","",IF(TRIM(SUBSTITUTE(H24,CHAR(10)," "))="",0,LEN(TRIM(SUBSTITUTE(H24,CHAR(10)," ")))-LEN(SUBSTITUTE(TRIM(SUBSTITUTE(H24,CHAR(10)," "))," ",""))+1)) | K24: =IF($A24="","",IF(TRIM(SUBSTITUTE(J24,CHAR(10)," "))="",0,LEN(TRIM(SUBSTITUTE(J24,CHAR(10)," ")))-LEN(SUBSTITUTE(TRIM(SUBSTITUTE(J24,CHAR(10)," "))," ",""))+1)) | M24: =IF($A24="","",IF(TRIM(SUBSTITUTE(L24,CHAR(10)," "))="",0,LEN(TRIM(SUBSTITUTE(L24,CHAR(10)," ")))-LEN(SUBSTITUTE(TRIM(SUBSTITUTE(L24,CHAR(10)," "))," ",""))+1)) | O24: =IF($A24="","",IF(TRIM(SUBSTITUTE(N24,CHAR(10)," "))="",0,LEN(TRIM(SUBSTITUTE(N24,CHAR(10)," ")))-LEN(SUBSTITUTE(TRIM(SUBSTITUTE(N24,CHAR(10)," "))," ",""))+1)) | Q24: =IF($A24="","",IF(TRIM(SUBSTITUTE(P24,CHAR(10)," "))="",0,LEN(TRIM(SUBSTITUTE(P24,CHAR(10)," ")))-LEN(SUBSTITUTE(TRIM(SUBSTITUTE(P24,CHAR(10)," "))," ",""))+1)) | S24: =IF($A24="","",IF(TRIM(SUBSTITUTE(R24,CHAR(10)," "))="",0,LEN(TRIM(SUBSTITUTE(R24,CHAR(10)," ")))-LEN(SUBSTITUTE(TRIM(SUBSTITUTE(R24,CHAR(10)," "))," ",""))+1))
C25: =IF($A25="","",IF(TRIM(SUBSTITUTE(B25,CHAR(10)," "))="",0,LEN(TRIM(SUBSTITUTE(B25,CHAR(10)," ")))-LEN(SUBSTITUTE(TRIM(SUBSTITUTE(B25,CHAR(10)," "))," ",""))+1)) | E25: =IF($A25="","",IF(TRIM(SUBSTITUTE(D25,CHAR(10)," "))="",0,LEN(TRIM(SUBSTITUTE(D25,CHAR(10)," ")))-LEN(SUBSTITUTE(TRIM(SUBSTITUTE(D25,CHAR(10)," "))," ",""))+1)) | G25: =IF($A25="","",IF(TRIM(SUBSTITUTE(F25,CHAR(10)," "))="",0,LEN(TRIM(SUBSTITUTE(F25,CHAR(10)," ")))-LEN(SUBSTITUTE(TRIM(SUBSTITUTE(F25,CHAR(10)," "))," ",""))+1)) | I25: =IF($A25="","",IF(TRIM(SUBSTITUTE(H25,CHAR(10)," "))="",0,LEN(TRIM(SUBSTITUTE(H25,CHAR(10)," ")))-LEN(SUBSTITUTE(TRIM(SUBSTITUTE(H25,CHAR(10)," "))," ",""))+1)) | K25: =IF($A25="","",IF(TRIM(SUBSTITUTE(J25,CHAR(10)," "))="",0,LEN(TRIM(SUBSTITUTE(J25,CHAR(10)," ")))-LEN(SUBSTITUTE(TRIM(SUBSTITUTE(J25,CHAR(10)," "))," ",""))+1)) | M25: =IF($A25="","",IF(TRIM(SUBSTITUTE(L25,CHAR(10)," "))="",0,LEN(TRIM(SUBSTITUTE(L25,CHAR(10)," ")))-LEN(SUBSTITUTE(TRIM(SUBSTITUTE(L25,CHAR(10)," "))," ",""))+1)) | O25: =IF($A25="","",IF(TRIM(SUBSTITUTE(N25,CHAR(10)," "))="",0,LEN(TRIM(SUBSTITUTE(N25,CHAR(10)," ")))-LEN(SUBSTITUTE(TRIM(SUBSTITUTE(N25,CHAR(10)," "))," ",""))+1)) | Q25: =IF($A25="","",IF(TRIM(SUBSTITUTE(P25,CHAR(10)," "))="",0,LEN(TRIM(SUBSTITUTE(P25,CHAR(10)," ")))-LEN(SUBSTITUTE(TRIM(SUBSTITUTE(P25,CHAR(10)," "))," ",""))+1)) | S25: =IF($A25="","",IF(TRIM(SUBSTITUTE(R25,CHAR(10)," "))="",0,LEN(TRIM(SUBSTITUTE(R25,CHAR(10)," ")))-LEN(SUBSTITUTE(TRIM(SUBSTITUTE(R25,CHAR(10)," "))," ",""))+1))
C26: =IF($A26="","",IF(TRIM(SUBSTITUTE(B26,CHAR(10)," "))="",0,LEN(TRIM(SUBSTITUTE(B26,CHAR(10)," ")))-LEN(SUBSTITUTE(TRIM(SUBSTITUTE(B26,CHAR(10)," "))," ",""))+1)) | E26: =IF($A26="","",IF(TRIM(SUBSTITUTE(D26,CHAR(10)," "))="",0,LEN(TRIM(SUBSTITUTE(D26,CHAR(10)," ")))-LEN(SUBSTITUTE(TRIM(SUBSTITUTE(D26,CHAR(10)," "))," ",""))+1)) | G26: =IF($A26="","",IF(TRIM(SUBSTITUTE(F26,CHAR(10)," "))="",0,LEN(TRIM(SUBSTITUTE(F26,CHAR(10)," ")))-LEN(SUBSTITUTE(TRIM(SUBSTITUTE(F26,CHAR(10)," "))," ",""))+1)) | I26: =IF($A26="","",IF(TRIM(SUBSTITUTE(H26,CHAR(10)," "))="",0,LEN(TRIM(SUBSTITUTE(H26,CHAR(10)," ")))-LEN(SUBSTITUTE(TRIM(SUBSTITUTE(H26,CHAR(10)," "))," ",""))+1)) | K26: =IF($A26="","",IF(TRIM(SUBSTITUTE(J26,CHAR(10)," "))="",0,LEN(TRIM(SUBSTITUTE(J26,CHAR(10)," ")))-LEN(SUBSTITUTE(TRIM(SUBSTITUTE(J26,CHAR(10)," "))," ",""))+1)) | M26: =IF($A26="","",IF(TRIM(SUBSTITUTE(L26,CHAR(10)," "))="",0,LEN(TRIM(SUBSTITUTE(L26,CHAR(10)," ")))-LEN(SUBSTITUTE(TRIM(SUBSTITUTE(L26,CHAR(10)," "))," ",""))+1)) | O26: =IF($A26="","",IF(TRIM(SUBSTITUTE(N26,CHAR(10)," "))="",0,LEN(TRIM(SUBSTITUTE(N26,CHAR(10)," ")))-LEN(SUBSTITUTE(TRIM(SUBSTITUTE(N26,CHAR(10)," "))," ",""))+1)) | Q26: =IF($A26="","",IF(TRIM(SUBSTITUTE(P26,CHAR(10)," "))="",0,LEN(TRIM(SUBSTITUTE(P26,CHAR(10)," ")))-LEN(SUBSTITUTE(TRIM(SUBSTITUTE(P26,CHAR(10)," "))," ",""))+1)) | S26: =IF($A26="","",IF(TRIM(SUBSTITUTE(R26,CHAR(10)," "))="",0,LEN(TRIM(SUBSTITUTE(R26,CHAR(10)," ")))-LEN(SUBSTITUTE(TRIM(SUBSTITUTE(R26,CHAR(10)," "))," ",""))+1))
